Workbook

Sheet Summary List
E2: Out of Total
B3: TRADE | E3: Number of Contractors | G3: Physical Shops | I3: Installation | K3: Import Supply | M3: Local Supply | O3: Delivery
B4: Maltese Balconies | E4: 0 | G4: 0 | I4: 0 | K4: 0 | M4: 0 | O4: 0
B5: Office Hardware | E5: =COUNTA(Hardware!B2:B40) -> 17 | G5: =COUNTIF(Hardware!H1:H18, "yes") & " out of " & E5 -> 9 out of 17 | I5: =COUNTIF(Hardware!G2:G18, "yes") & " out of " & E5 -> 16 out of 17 | K5: =COUNTIF(Hardware!K2:K18, "yes") & " out of " & E5 -> 17 out of 17 | M5: =COUNTIF(Hardware!J2:J18, "yes") & " out of " & E5 -> 17 out of 17 | O5: =COUNTIF(Hardware!I2:I18, "yes") & " out of " & E5 -> 17 out of 17
B6: Lasers | E6: =COUNTA(Laser!B2:B40) -> 1 | G6: =COUNTIF(Laser!H1:H18, "yes") & " out of " & E6 -> 1 out of 1 | I6: =COUNTIF(Laser!G2:G18, "yes") & " out of " & E6 -> 1 out of 1 | K6: =COUNTIF(Laser!J2:J8, "yes") & " out of " & E6 -> 0 out of 1 | M6: =COUNTIF(Laser!I2:I7, "yes") & " out of " & E6 -> 1 out of 1 | O6: =COUNTIF(Laser!H2:H7, "yes") & " out of " & E6 -> 1 out of 1
B7: Surveyors | E7: =COUNTA(Surveyors!B2:B40) -> 13 | G7: N/A | I7: N/A | K7: N/A | M7: N/A | O7: N/A
B8: Waterproofing | E8: =COUNTA(Waterproofing!B2:B40) -> 30 | G8: =COUNTIF(Waterproofing!H1:H40, "yes") & " out of " & E8 -> 30 out of 30 | I8: =COUNTIF(Waterproofing!G2:G32, "yes") & " out of " & E8 -> 8 out of 30 | K8: =COUNTIF(Waterproofing!K2:K41, "yes") & " out of " & E8 -> 8 out of 30 | M8: =COUNTIF(Waterproofing!J2:J41, "yes") & " out of " & E8 -> 22 out of 30 | O8: =COUNTIF(Waterproofing!I2:I41, "yes") & " out of " & E8 -> 30 out of 30
B9: Surface Finishes | E9: 0 | G9: 0 | I9: 0 | K9: 0 | M9: 0 | O9: 0
B10: Terrazzo Slabs | E10: =COUNTA('Terrazzo Slabs'!B2:B21) -> 12 | G10: =COUNTIF('Terrazzo Slabs'!H2:H30, "yes") & " out of " & E10 -> 9 out of 12 | I10: =COUNTIF('Terrazzo Slabs'!G2:G29, "yes") & " out of " & E10 -> 9 out of 12 | K10: =COUNTIF('Terrazzo Slabs'!K2:K31, "yes") & " out of " & E10 -> 7 out of 12 | M10: =COUNTIF('Terrazzo Slabs'!J2:J31, "yes") & " out of " & E10 -> 10 out of 12 | O10: =COUNTIF('Terrazzo Slabs'!I2:I31, "yes") & " out of " & E10 -> 12 out of 12
B11: Washing Machines | E11: =COUNTA('Washing Machines'!B2:B30) -> 23 | G11: =COUNTIF('Washing Machines'!H2:H31, "yes") & " out of " & E11 -> 19 out of 23 | I11: =COUNTIF('Washing Machines'!G2:G31, "yes") & " out of " & E11 -> 19 out of 23 | K11: =COUNTIF('Washing Machines'!K2:K31, "yes") & " out of " & E11 -> 23 out of 23 | M11: =COUNTIF('Washing Machines'!J2:J31, "yes") & " out of " & E11 -> 23 out of 23 | O11: =COUNTIF('Washing Machines'!I2:I24, "yes") & " out of " & E11 -> 21 out of 23
B12: Tumble Dryer | E12: =COUNTA('Tumble Dryer'!B2:B31) -> 17 | G12: =COUNTIF('Tumble Dryer'!H2:H31, "yes") & " out of " & E12 -> 16 out of 17 | I12: =COUNTIF('Tumble Dryer'!G2:G31, "yes") & " out of " & E12 -> 17 out of 17 | K12: =COUNTIF('Tumble Dryer'!J2:J31, "yes") & " out of " & E12 -> 17 out of 17 | M12: =COUNTIF('Tumble Dryer'!J2:J31, "yes") & " out of " & E12 -> 17 out of 17 | O12: =COUNTIF('Tumble Dryer'!K2:K31, "yes") & " out of " & E12 -> 17 out of 17
B13: Gypsum | E13: =COUNTA(Gypsum!B2:B31) -> 22 | G13: =COUNTIF(Gypsum!H2:H31, "yes") & " out of " & E13 -> 17 out of 22 | I13: =COUNTIF(Gypsum!G2:G31, "yes") & " out of " & E13 -> 5 out of 22 | K13: =COUNTIF(Gypsum!I2:I31, "yes") & " out of " & E13 -> 22 out of 22 | M13: =COUNTIF(Gypsum!J2:J31, "yes") & " out of " & E13 -> 17 out of 22 | O13: =COUNTIF(Gypsum!K2:K31, "yes") & " out of " & E13 -> 5 out of 22
B14: Site Clearance | E14: =COUNTA('Site Clearance'!B2:B31) -> 2 | G14: N/A | I14: N/A | K14: N/A | M14: N/A | O14: N/A
B15: Industrial Shelving | E15: =COUNTA('Industrial Shelving'!B2:B31) -> 15 | G15: =COUNTIF('Industrial Shelving'!G2:G31, "yes") & " out of " & E15 -> 15 out of 15 | I15: =COUNTIF('Industrial Shelving'!H2:H31, "yes") & " out of " & E15 -> 14 out of 15 | K15: =COUNTIF('Industrial Shelving'!I2:I31, "yes") & " out of " & E15 -> 15 out of 15 | M15: =COUNTIF('Industrial Shelving'!J2:J31, "yes") & " out of " & E15 -> 0 out of 15 | O15: =COUNTIF('Industrial Shelving'!K2:K31, "yes") & " out of " & E15 -> 15 out of 15
B16: Multisensory Rooms | E16: =COUNTA('multysensory room'!B3:B31) -> 5 | G16: =COUNTIF('multysensory room'!G2:G31, "yes") & " out of " & E16 -> 5 out of 5
B17: Bathrooms
B18: Bedrooms
B19: Kitchens
B20: Wall Panels
B21: Office Furniture

Sheet Fibreglass
A1: item | B1: supplier | C1: email | D1: phone number | E1: location | F1: website | G1: notes
C2: info@micalleffibreglassworks.com
C3: info@silvercraftltd.com
C4: etienne@silvercraftltd.com
C5: angela@silvercraftltd.com
C6: info@crownfibreglass.com
C7: info@micallefpools.com
B8: Glassfibre Industries | C8: natasha@glassfibreindustries.net | D8: 21470282 | E8: Birkirkara | F8: http://www.glassfibreindustries.net/?utm_source=Yellow&utm_medium=Yellow-Website&utm_campaign=Landing-Page
B9: Crown Fibreglass | C9: info@crownfibreglass.com | D9: 99 420 586 | E9: Zetjun | F9: http://www.crownfibreglass.com/?utm_source=Yellow&utm_medium=Yellow-Website&utm_campaign=Landing-Page
B10: Silvercraft Products Ltd | C10: info@silvercraftltd.com | D10: 21 898 046 | E10: Marsa | F10: http://www.silvercraftltd.com/?utm_source=Yellow&utm_medium=Yellow-Website&utm_campaign=Landing-Page
B11: Fashion Fibreglass | C11: fashionfibre@hotmail.com | D11: 21 485 748 | E11: Qormi
B12: Seabrave Marine | C12: info@seabravemarine.com | D12: 7905 0545 | E12: Birzebbugia | F12: https://www.facebook.com/people/Seabrave-Marine/100057368593400/

Sheet Extractors
A1: c | B1: supplier | C1: email | D1: phone number | E1: location | F1: website
A2: Ventilation | B2: Econova | C2: econovamalta@gmail.com | D2: 9942 1158 | E2: 50, Triq Salvu Psaila, Birkirkara, Malta, BKR9072 | F2: https://www.facebook.com/econovamalta/ | G2: Wants us to book a consultation (but costs 50euro for them to come on site) https://docs.google.com/forms/d/e/1FAIpQLSeB6v8JWo79RIujHFRtUz1Z2D1YFwtXp6QogrjMGIh5-JjSqw/viewform
A3: Ventilation | B3: Titan
A4: Ventilation | B4: HVAC | C4: info@hvacsupplies.eu | D4: 9999 4570 | E4: Triq Ħal Luqa, Qormi, QRM 9070, Malta | F4: https://hvacsupplies.eu/about-us/
A5: Ventilation | B5: Cutrico | C5: info@cutrico.com | D5: 2149 8658 | E5: Cutrico Ltd, Mriehel By-pass, Mriehel, Malta | F5: https://www.cutrico.com/en/home.htm
A6: Ventilation | B6: Comfortek | C6: dpcomfortek@gmail.com | D6: 2143 7403 | E6: 94 Triq wied hal-Balzan, Balzan, Malta | F6: comfortek.mt
A7: Ventilation | B7: Bezzina Bros | C7: info@bezzbros.com | D7: 2123 1892 | E7: Aldo Moro Rd., Marsa, Malta, MRS9065 | F7: https://bezzbros.com/
A8: Ventilation | B8: GI Maintenance
A9: Ventilation | B9: C&D Electrical & Mechanical Installations | C9: info@cdinstallations.com.mt | D9: 79206640 | E9: 28, Triq Borg, Fleur-De-Lys, Birkirkara, BKR 4963 | F9: https://www.cdinstallations.com.mt/
A10: Ventilation | B10: Energex | C10: energexservices@gmail.com | D10: 9947 6119
A11: Ventilation | B11: Cooltec | C11: info@cooltekservices.com.mt | F11: https://cooltekservices.com.mt/contact-us/
A12: Ventilation | B12: DR Installations | C12: rosamonddesira@gmail.com
A13: Ventilation | B13: CE Installations | C13: info@ceinstallations.com.mt | D13: 2767 7822 | F13: https://ceinstallations.com.mt/
A14: Ventilation | B14: WeDuct | C14: info@weduct.com.mt
A15: Ventilation | B15: Proklima | C15: projects@proklimamalta.com | D15: 99 401 247 | E15: Garage V15 Warehouse First Floor, Binja San Guzepp Haddiem Triq Indri Psaila Qormi | F15: https://www.proklimamalta.com/
A16: Ventilation | B16: Midea Malta | C16: sales@midea.mt | D16: 7966 7908 | F16: https://midea.mt/contact/
A17: Ventilation | B17: Callejja | C17: webshop@calleja.com.mt | F17: https://calleja.com.mt/contact/
A18: Ventilation | B18: Tabone Direct | C18: sales@tabonedirect.com
A19: Ventilation | B19: Geoholistic | C19: info@geoholistic.com | D19: 21370404 | E19: Geo Holistic Co. Ltd. G1, Five Star Business Park, Triq il-Belt Valletta, Ghaxaq | F19: https://www.geoholistic.com/ventilation.html
A20: Ventilation | B20: RS | C20: sales@thetccgroup.org
A21: Ventilation | B21: MFF Industrial Supplies | C21: sales@mff-isl.com
A22: Ventilation | B22: Smart Effects | C22: afenech@smarteffects.com.mt
B26: MV System
B27: Nonstop forced cross ventilation
B28: You need a fresh air system together with the ac unit
B30: We need to draft up an email to these guys to tell us what our options are.
B32: Econova is suggesting a tailored ventilation system (we need enough height in the room).
B33: They intall a bulkhead (to hide the ventilation pipes) and created a filtrated ventilation system.

Sheet Handyman
A1: item | B1: name | C1: email | D1: phone number | E1: location | F1: website | G1: Corporate/Self Employed | H1: Note
A3: Handyman | B3: Mr. Handy | C3: info@mrhandy.mt | D3: 2733 0364 | E3: 682, Triq il-Kbira San Ġużepp, Ħamrun, Malta | F3: briiz.com.mt/handyman | G3: Corporate
A4: Handyman | B4: Ewi home services Limited | C4: info@ewihomeservices.com | D4: 7922 1982 | E4: Registered in Malta (Service area: All Malta, no public storefront) | F4: ewihomeservices.com | G4: Corporate
A5: Handyman | B5: WS Installations | C5: info@wsinstallations.com | D5: 9965 5581 | E5: Triq Ċensu Busuttil, L-Iklin | F5: https://www.wsinstallationsmalta.com/ | G5: Corporate
A6: Handyman | B6: Handyman Solutions Ltd | C6: ilenia@actsmart.com.mt | D6: 7713 1210 | E6: 58c, Triq Patri Feliċjan Bilocca, Marsa | F6: N/A | G6: Corporate
A7: Handyman | B7: 24/7 Handyman Services (Kevin Bonnici) | C7: kevin.bonnici76@gmail.com | D7: 9911 1247 | E7: Registered in Qormi (Mobile contractor, no public storefront) | F7: N/A | G7: Self-Employed
A8: Handyman | B8: Homecare Malta | C8: info@homecaremalta.com | D8: 2152 9528 | E8: 881, Triq il-Kbira San Ġużepp, Ħamrun, HMR 1010 | F8: homecaremalta.com | G8: Corporate
A9: Handyman | B9: J D Maintenance & High-Up | C9: demicolijo@gmail.com | D9: 9947 5511 | E9: Registered in Mosta (Mobile contractor, no public storefront) | F9: N/A | G9: Self-Employed | H9: Agreed to the tems. Self-Employed, just one worker
A10: Handyman | B10: NLP Force Ltd | C10: nikola.pejovic@nlpforce.com | D10: 9958 0909 | E10: Triq Ġużeppi Xuereb ix-Xhudi, Swatar, Birkirkara | F10: nlpforce.com | G10: Corporate
A11: Handyman | B11: Joseph's Handy Solutions | C11: schembrijoseph91@gmail.com | D11: 7709 8188 | E11: Registered in Żejtun (Mobile contractor, no public storefront) | F11: N/A | G11: Self-Employed
A12: Handyman | B12: AB Installations By Formosa | C12: abinstallationsbyformosa@gmail.com | D12: 7929 9918 | E12: Registered in Żabbar (Mobile contractor, no public storefront) | F12: N/A | G12: Self-Employed
A13: Handyman | B13: Marco Vella Handyman Services | C13: Contact via website form | D13: 7900 0000 | E13: 31, Triq il-Merill, Mellieħa, MLH 2572 | F13: marcovella.com | G13: Corporate
A14: Handyman | B14: Briiz (Mr. Handyman) | C14: info@briiz.com.mt | D14: 2733 0364 | E14: 682, Triq il-Kbira San Ġużepp, Ħamrun, Malta | F14: briiz.com.mt/handyman | G14: Corporate
A15: Handyman | B15: Swift Solutions | C15: swiftsolution2025@gmail.com | D15: 9907 4325 | E15: Registered in Mosta (Service area: All Malta, no public storefront) | F15: N/A | G15: Self-Employed
A16: Handyman | B16: Better Call Tyrone | C16: tyrone.vassallo01@gmail.com | D16: 7944 2574 | E16: Registered in Qormi (Mobile contractor, no public storefront) | F16: N/A | G16: Self-Employed | H16: Reqiures a meeting to discuss further
A17: Handyman | B17: JC Handyman & Turnkey | C17: jason.cordina79@gmail.com | D17: 7982 7981 | E17: 176, Triq San Bastjan, Qormi | F17: N/A | G17: Self-Employed
A18: Handyman | B18: ZAG - Services & Finishes Malta | C18: ZAGinfo@gmail.com | D18: 7777 9098 | E18: 373, St Joseph High Street, Mosta | F18: N/A | G18: Corporate
A19: Handyman | B19: ACM Maintanace | C19: clivesammut@hotmail.co.uk | D19: 7905 5452 | E19: 45, Indri Borg Street, Rabat | F19: N/A | G19: Self-Employed
A20: Handyman | B20: EC Installations | C20: esteliocini@gmail.com | D20: 7999 3858 | E20: 152, St. Peter Paul, Triq il-Kbira, Qormi | F20: N/A | G20: Self-Employed
A21: Handyman | B21: GF Installations | C21: gfinstallations@gmail.com | D21: 2765 6533 | E21: Garage 64, Triq is-Sajjied, Qawra, San Pawl il-Baħar | F21: gfonlinestore.com | G21: Corporate
A22: Handyman | B22: Brian Handyman & Gypsum Works | C22: brifor06@hotmail.com | D22: 9982 5505 | E22: Registered in Tarxien (Mobile contractor, no public storefront) | F22: N/A | G22: Self-Employed
A23: Handyman | B23: Gino Handyman Service | C23: gino.bonnici.11@gmail.com | D23: 7905 1396 | E23: Registered in Żejtun (Mobile contractor, no public storefront) | F23: N/A | G23: Self-Employed
A24: Handyman | B24: MB Handyman Services | C24: mb.handymanservice@libero.it | D24: 9972 6390 | E24: Registered in Buġibba / St. Paul's Bay (Mobile contractor, no public storefront) | F24: N/A | G24: Self-Employed
A25: Handyman | B25: Emilio Bilocca Handyman Services | C25: info@emiliohandyman.com | D25: N/A | E25: 17 Madonnina, Triq il-Pluvieri, Gudja (Also lists: Milicent Garage, Triq il-Magħsar, Gudja) | F25: emiliohandyman.com | G25: Self-Employed | H25: Chanrges 40EUR/hr Per Person
A26: Handyman | B26: Manutek | C26: Manutek@kompleto.com.mt | D26: 2702 8282 | E26: GPL Business Centre, Office 1, Level 2, Sqaq il-Ghadam, Mriehel, BKR3000 | F26: www.kompleto.com.mt | G26: Corporate
A27: Handyman | B27: Pj Handyman | C27: pjhandyman@mail.com | D27: 7928 8241 | E27: Registered in Qormi (Mobile contractor, no public storefront) | F27: N/A | G27: Corporate | H27: Does not work on fixed rates but by quote on site.
A28: Handyman
A29: Handyman
A30: Handyman
A31: Handyman
A32: Handyman
A33: Handyman
A34: Handyman
A35: Handyman
A36: Handyman
A37: Handyman

Sheet Electricians
A1: item | B1: name | C1: email | D1: phone number | E1: location | F1: website | G1: Corporate/Self Employed | H1: Note
A3: Electrician | B3: Aaron Agius | C3: aaronagius82@gmail.com | D3: 7926 2384 | E3: Id-Dwejra, Triq il-Fidwa, Gudja, Malta | F3: N/A | G3: Self-Employed
A4: Electrician | B4: Anthony D'Anastasi | C4: danastasi.rt@outlook.com | D4: 9948 5960 | E4: 32 Virgo, Triq il-Battaljun, Mosta, MST 2721, Malta | F4: N/A | G4: Self-Employed
A5: Electrician | B5: Aaron Zammit | C5: N/A | D5: 7920 0196 | E5: Cawsli Court, Flt 4, Triq L-Imdina, Ħal Qormi, Malta | F5: N/A | G5: Self-Employed
A6: Electrician | B6: Better Call Tyrone | C6: tyrone.vassallo01@gmail.com | D6: 7944 2574 | E6: Registered in Qormi (Mobile contractor, no public street address listed) | F6: N/A | G6: Self-Employed
A7: Electrician | B7: Stefan (AC's By Stefan) | C7: N/A | D7: N/A | E7: Registered in Malta (Mobile contractor, no public street address listed) | F7: N/A | G7: Self-Employed
A8: Electrician | B8: Dorian Sciortino | C8: Contact via REWS registry | D8: N/A | E8: Blk C6 Flat 2, Triq il-Fraxxnu, Ħaż-Żebbuġ, Malta | F8: N/A | G8: Self-Employed
A9: Electrician | B9: HandySalv | C9: Contact via StarOfService directory | D9: N/A | E9: Registered in Birżebbuġa, BBG 1606, Malta (Mobile contractor) | F9: N/A | G9: Self-Employed
A10: Electrician | B10: Roderick Attard | C10: N/A | D10: 9947 6137 | E10: Registered in Central Malta (Mobile domestic electrician) | F10: N/A | G10: Self-Employed
A11: Electrician | B11: Michelle Colombo | C11: N/A | D11: 9942 3371 | E11: 92 Triq Blanche Huber, Sliema, Malta | F11: N/A | G11: Self-Employed
A12: Electrician | B12: Salvu Fenech Ta' Spekna | C12: salvufenech@gmail.com | D12: 7949 7456 | E12: 39 Siskina, Triq Raddet Ir-Roti, Mosta, Malta | F12: N/A | G12: Self-Employed
A13: Electrician | B13: Carmel Carabott | C13: N/A | D13: 7920 4466 | E13: Registered in Marsaxlokk (Mobile domestic electrician) | F13: N/A | G13: Self-Employed
A14: Electrician | B14: JC Electrical Plumbing Installation | C14: jcelectricalmalta@gmail.com | D14: 7909 3306 | E14: Registered in Qormi (Mobile contractor) | F14: N/A | G14: Self-Employed
A15: Electrician | B15: Stephen Micallef (Electrical & Plumbing) | C15: N/A | D15: 9982 4815 | E15: Registered in Naxxar (Mobile contractor) | F15: N/A | G15: Self-Employed
A16: Electrician
A17: Electrician
A18: Electrician
A19: Electrician
A20: Electrician
A21: Electrician
A22: Electrician
A23: Electrician
A24: Electrician
A25: Electrician
A26: Electrician
A27: Electrician
... A37: Electrician

Sheet Carpenters
A1: item | B1: name | C1: email | D1: phone number | E1: location | F1: website
A2: Carpenter | B2: Domestica | C2: info@domestica.com.mt | F2: https://domestica.com.mt
A3: Carpenter | B3: FV Carpentry | C3: fran@fvcarpentry.com | F3: https://www.fvcarpentry.com
A4: Carpenter | B4: Refalo Woodworks Ltd | C4: info@refalowoodworksltd.com | F4: https://refalowoodworks.com
A5: Carpenter | B5: Gauci Woodworks | C5: pdgl1969@gmail.com | F5: https://www.findit.com.mt/en/directory/listings/3682/gauci-woodworks.htm
A6: Carpenter | B6: BP Woodworks | C6: info@bpwoodworks.com | F6: https://www.bpwoodworks.com
A7: Carpenter | B7: Armstrong Woodworks Ltd | C7: info@armstrong.com.mt | F7: https://www.armstrong.com.mt
A8: Carpenter | B8: Shalom Woodworks | C8: sales@shalomwoodworks.com | F8: https://www.shalomwoodworks.com
A9: Carpenter | B9: Joseph Briffa Woodworks | C9: joseph.briffa.woodworks@hotmail.com | F9: —
A10: Carpenter | B10: Jomasero Woodworks | C10: joseph.taekwondo@gmail.com | F10: —
A11: Carpenter | B11: Baldacchino Woodworks Ltd | C11: info@baldacchinogroup.com | F11: https://baldacchinogroup.com/left-menu/woodworks.html

Sheet Second Hand Car Dealers
A1: item | B1: name | C1: email | D1: phone number | E1: location | F1: website
A2: Car Dealer | B2: A&A | C2: info@aacarimports.com.mt | F2: https://aacarimports.com.mt/
A3: Car Dealer | B3: A1 Autodealers | C3: dowlinga@go.net.mt | F3: https://www.yellow.com.mt/a-1-auto-dealers_auto-dealers+mosta/
A4: Car Dealer | B4: ABS Auto Dealer | C4: abs@onvol.net | F4: https://www.facebook.com/p/ABS-Auto-Dealer-100057348224337/
A5: Car Dealer | B5: AJ Motors | C5: ajmotorsales@gmail.com | F5: https://www.yellow.com.mt/aj-motors/auto-dealers/
A6: Car Dealer | B6: Alan Motors | C6: info@alanmotors.com.mt | F6: https://alanmotors.com.mt/
A7: Car Dealer | B7: Attard Auto Dealer | C7: attardautodealer@gmail.com | D7: 9949 4186 | F7: https://www.facebook.com/p/Attard-Auto-Dealer-100057253586326/
A8: Car Dealer | B8: Attards Motors | C8: taattardmotors@gmail.com | D8: 7990 2106 | F8: https://www.facebook.com/attardsmotors/
A9: Car Dealer | B9: AutoGama | D9: 9945 4154 | F9: https://www.facebook.com/autogamaimports/
A10: Car Dealer | B10: Autozone Autodealer | C10: autozoneautodealer@gmail.com | F10: https://www.facebook.com/autozonemalta/
A11: Car Dealer | B11: Avis Malta | C11: info@aviscarsales.mt | F11: https://www.facebook.com/AvisMaltaUsedCarSales/
A12: Car Dealer | B12: Brincat Auto Imports | C12: info@brincatautoimports.com | F12: https://brincatautoimports.com/
A13: Car Dealer | B13: BTL Autodealer | C13: btlautodealer@gmail.com | D13: 9925 2716 | F13: https://www.facebook.com/Btlautodeater/
A14: Car Dealer | B14: Canadis Autodealer | C14: canadisautodealer@gmail.com | F14: https://www.facebook.com/p/Canadis-Auto-Dealer-100063715533716/
A15: Car Dealer | B15: CarHub | C15: info@carhub.mt | F15: https://www.facebook.com/carhubmalta/
A16: Car Dealer | B16: Caromotors | D16: 9903 0870 | F16: https://www.facebook.com/Caromotors/
A17: Car Dealer | B17: Cars and More | C17: info@cam.com.mt | F17: https://www.facebook.com/carsandmoremalta
A18: Car Dealer | B18: Cars Unlimited | C18: info@carsunlimitedmalta.com | F18: https://carsunlimitedmalta.com/
A19: Car Dealer | B19: Charlie Auto Dealer | D19: 9949 4553 | F19: https://www.facebook.com/p/Charlie-Auto-Dealer-100054340519565/
A20: Car Dealer | B20: Chevron Auto Dealer | C20: sales@chevronautodealer.mt | F20: https://www.facebook.com/ChevronCarsAndmore/
A21: Car Dealer | B21: CR Cars | C21: sales@fordsparesmalta.com | F21: https://www.facebook.com/crcarsmalta/
A22: Car Dealer | B22: D & G Auto Dealer | D22: 77 474 746
A23: Car Dealer | B23: D & S Auto Dealer | C23: dandsautodealer@hotmail.com | D23: 9947 7956 | F23: https://www.facebook.com/dandsautodealer/
A24: Car Dealer | B24: DC Motors | C24: dcmotorsbkara@gmail.com | D24: 9975 5547 | F24: https://www.facebook.com/p/DC-motors-Auto-Sales-100057442128124/
A25: Car Dealer | B25: Dino's Motor Centre | C25: dinosreception@gmail.com | D25: 21485301 | E25: Dino's Motor Centre, Mosta Road, Lija. LJA9012. | F25: https://dinosmotors.com/contact-form/
A26: Car Dealer | B26: Drive Automotive Co Ltd | C26: info@drive.com.mt | F26: https://www.facebook.com/DriveAutomotiveCoLtd/
A27: Car Dealer | B27: DRM Auto Sales | C27: philmar87@hotmail.co.uk | F27: https://www.facebook.com/p/DRM-Autosales-100054512857141/
A28: Car Dealer | B28: Emotion Car Imports | C28: sales@emotionimports.com | F28: https://www.facebook.com/EmotionImports/
A29: Car Dealer | B29: Eucharist Mercieca Auto Ltd | C29: info@emauto.com.mt | F29: https://www.facebook.com/emautoltd/
A30: Car Dealer | B30: Fava Auto Dealers | C30: clivefava@gmail.com | F30: https://www.facebook.com/favacardealers/
A31: Car Dealer | B31: Galea General Services Ltd (GGS) | C31: info@ggs.com.mt | F31: https://www.facebook.com/GaleaGeneralServicesLtd/
A32: Car Dealer | B32: Gasan Enterprises Ltd | C32: automotive@gasan.com
A33: Car Dealer | B33: Gauci Automobiles Co Ltd | C33: sales@gauciautomobiles.com
A34: Car Dealer | B34: George and Rocco Car Centre | C34: rocco@georgeandrocco.com | F34: https://www.facebook.com/georgeandroccocarcentre/?locale=mt_MT
A35: Car Dealer | B35: George Autodealer | C35: georgeautodealer95@gmail.com
A36: Car Dealer | B36: Glenn's Highway Auto Dealer | C36: highwayauto@onvol.net
A37: Car Dealer | B37: Horace Auto Dealer | C37: craigscicluna@gmail.com
A38: Car Dealer | B38: J Auto Malta | C38: jautoimports@gmail.com
A39: Car Dealer | B39: J C Car Sales | C39: jeanpazzopardi@gmail.com
A40: Car Dealer | B40: J F Motors | C40: jfmotorsgozo@gmail.com
A41: Car Dealer | B41: J M Motors | C41: info@jmmotorsmalta.com
A42: Car Dealer | B42: Jason Imports | C42: sales@jasoncarimports.com | F42: https://jasoncarimports.com/
A43: Car Dealer | B43: Joe AutoDealer | C43: info@joeautodealer.com | F43: https://joeautodealer.com/
A44: Car Dealer | B44: Justin Autodealer | C44: justinauto@hotmail.com
A45: Car Dealer | B45: Kenky Cars | C45: kennethsch3mbri@gmail.com
A46: Car Dealer | B46: Kind's Auto Sales | C46: info@autosales.com.mt | F46: https://www.autosales.com.mt/
A47: Car Dealer | B47: Kurt's Auto Sales | C47: kurtsautosales@hotmail.com
A48: Car Dealer | B48: LF Motors | C48: falzonluca@gmail.com
A49: Car Dealer | B49: Mario Galea | C49: mariogalea@msn.com | F49: https://www.facebook.com/p/Mario-Galea-New-Second-Hand-Cars-100050330211879/
A50: Car Dealer | B50: Mark's Motors 4 x 4
A51: Car Dealer | B51: Melliehi Garage
A52: Car Dealer | B52: Mibrum Co. Ltd
A53: Car Dealer | B53: Michael Debono | C53: info@michaeldebonoused.mt | F53: https://michaeldebonoused.mt/
A54: Car Dealer | B54: Mizzi Motors Ltd
A55: Car Dealer | B55: Montebello Enterprises Ltd
A56: Car Dealer | B56: Mosta Auto Dealers
A57: Car Dealer | B57: Motors Inc
A58: Car Dealer | B58: Naxxar Motors
A59: Car Dealer | B59: Noel Second Hand Auto Dealer
A60: Car Dealer | B60: Owen Auto Dealer
A61: Car Dealer | B61: P Y M C A Auto Dealer
A62: Car Dealer | B62: Pajsu | C62: pajsurebus74@gimel.com | F62: https://www.facebook.com/www.pajsudealer.com.mt/
A63: Car Dealer | B63: Paola Car Centre
A64: Car Dealer | B64: PC Motors
A65: Car Dealer | B65: Portelli - Auto Dealer
A66: Car Dealer | B66: Premier Car Sales | C66: gattsammy@yahoo.com | F66: https://www.facebook.com/PremiereCarSales/
A67: Car Dealer | B67: Puli Motors
A68: Car Dealer | B68: Regina Auto Dealer Ltd
A69: Car Dealer | B69: Rocky Auto Dealer
A70: Car Dealer | B70: Rokku Auto Dealer | C70: rokkuautodealer@gmail.com | F70: https://www.facebook.com/rokkuautodealer/
A71: Car Dealer | B71: Route 66
A72: Car Dealer | B72: Sant Brothers Commercials Ltd
A73: Car Dealer | B73: SB Autocentre Ltd / SB Auto Centre Ltd
A74: Car Dealer | B74: Scotch Automobiles
A75: Car Dealer | B75: Sonic Auto Dealer / Sonic Car Importers
A76: Car Dealer | B76: Spiteri Autos
A77: Car Dealer | B77: Tal-Qasab Auto Dealer / Alexander Auto Sales
A78: Car Dealer | B78: Tasika Auto Ltd / Complete Motors
A79: Car Dealer | B79: Tonna Auto Dealer
A80: Car Dealer | B80: Ventur Motors | C80: venturmotors@gmail.com | F80: https://venturmotors.mt/
A81: Car Dealer | B81: Vince Auto Dealer
A82: Car Dealer | B82: Welcome Auto Dealer
A83: Car Dealer | B83: Winter Auto Dealer
A84: Car Dealer | B84: X Automobiles | C84: xautomobiles@gmail.com | F84: https://www.facebook.com/xauto007/
A85: Car Dealer | B85: Xclusv Auto Dealer

Sheet Archaeological Monitors
A1: item | B1: name | C1: email | D1: phone number | E1: location | F1: website
A2: Monitor | B2: Ader Charlene | C2: arkeomalta@gmail.com | D2: 79621262
A3: Monitor | B3: Besancon Jeremy | C3: jeremy@jbarchteam.com | D3: 79289569
A4: Monitor | B4: Bossini Samuela | C4: samuelabossini@gmail.com | D4: 77882898
A5: Monitor | B5: Borg Marlene | C5: ascoopltdmalta@gmail.com | D5: 99872954
A6: Monitor | B6: Borg Daniel | C6: ascoopltdmalta@gmail.com | D6: 79277408
A7: Monitor | B7: Busuttil Christopher | C7: chrisbu.su@gmail.com | D7: 99256349
A8: Monitor | B8: Cachia Karl | C8: karloco621@gmail.com | D8: 99275364
A9: Monitor | B9: Calleja Joseph | C9: ascoopltdmalta@gmail.com | D9: 79538973
A10: Monitor | B10: Cardona David | C10: skavarc@digiarc.mt | D10: 99822803
A11: Monitor | B11: Caruana Josef | C11: josefcaruana1@googlemail.com | D11: 79092230
A12: Monitor | B12: Cassar Chantal | C12: projects@aecmalta.com.mt | D12: 79254003
A13: Monitor | B13: Cherubini Rossano | C13: rossano.cherubini@qpml.com | D13: 99502126
... A35: Monitor | B35: Zarb Martina | C35: martinazarb@gmail.com | D35: 99192609

Sheet Maltese Balconies
A1: item | B1: name | C1: email | D1: phone number | E1: location | F1: website

Sheet Wall Mounted Speakers
A1: Item | B1: Supplier | C1: Email | D1: Phone number | E1: Location | F1: Website | G1: Physical store | H1: Installations
A2: Wall mounted speakers | B2: Powerhouse Malta | C2: nfo@powerhousemalta.com | D2: 356 79 499 432 | E2: Marsa | F2: Powerhouse Malta – AV (Audiovisuals) and Events Malta | G2: yes | H2: yes
A3: wall mounted sspakers | B3: Scan | C3: info@scanmalta.com
A4: Wall mounted speakers | B4: A to Z | C4: marketing@atoz.com.mt | D4: 356 99319111 | E4: Attard, Qormi, Swatar, Birkirkara | F4: AtoZ Electronics | Malta's Shop of Choice in 2026! | G4: yes | H4: yes
A5: Wall mounted speakers | B5: Digital Zone | C5: info@digitalzone.com.mt
A6: Wall mounted speakers | B6: Olimpus | C6: info@olimpusmusic.com
A7: Wall mounted speakers | B7: DONEO CO LTD | C7: nfo@doneo.com.mt | D7: 356 21 230 741 | E7: Hamrun | F7: Home page - Doneo | G7: yes | H7: yes
A8: Wall mounted speakers | B8: ASTRAL Enterprises LTD | C8: website@astral.com.mt | D8: 356 21340562 | E8: Ta' Xbiex | F8: ASTRAL Enterprises LTD | TV | Hifi | Custom Installations | G8: yes | H8: yes
A9: Wall mounted speakers | B9: AUDIO Malta | C9: info@audiomalta.com | D9: 356 2138 2876 | E9: Swieqi | F9: Audio Malta – Shop Smart, Rent Easy | G9: yes | H9: yes
A10: Wall mounted speakers | B10: Audio Hub Malta | C10: info@audiohub.mt | D10: 356 99 495 428 | E10: sales division of Lito’s Place | F10: Audio Hub Malta – Acoustics & Audio Equipment | G10: no | H10: yes
A11: Wall mounted speakers | B11: Futuretech pro Malta | C11: info@futuretech-malta.com | D11: 356 2799 2315 | E11: San Gwann | F11: Futuretech Pro Malta – Audio/Visual Specialists | G11: yes | H11: yes
A12: Wall mounted Speakers | B12: Audiotech | C12: info@audiotech.mt | D12: 356 21560719 | E12: Xghara, Gozo | F12: Audiotech Malta - your local electronics shop for Malta and Gozo - we deliver | G12: yes | H12: no
A13: Wall mounted speakers | B13: Ultimate Malta | C13: sales@ultimate.com.mt | D13: 356 21 444 545 | E13: San Gwann, Paola, Qormi | F13: Homepage - Ultimate | Electronics | Home Appliances | Deliveries in Malta & Gozo | G13: yes | H13: yes
A14: Wall mounted speakers | B14: studio7 | C14: info@studioseven.com.mt | D14: 356 2148 6301 | E14: Birkirkara | F14: Studo7.com.mt | G14: no | H14: yes
A15: Wall mouunted Speakers | B15: Genaudio Ltd | C15: joe@genaudiomalta.com | D15: 356 2145 9966 | E15: Birkirkara | F15: Contact – Genaudio Ltd | G15: yes | H15: yes
A16: Wall mounted speakers | B16: The sound system Co Ltd | C16: info@soundsystem.com.mt | D16: 356 21 25 55 00 | E16: Msida | F16: The sound system you need | The Sound System Malta | G16: yes | H16: yes
A17: wall mounted speakers | B17: Megatekk | C17: info@megatekk.mt
A18: Wall mounted speakers | B18: Audiophonic | C18: jc.audiophonic@gmail.com

Sheet Hardware
A1: item | B1: supplier | C1: email | D1: phone number | E1: location | F1: website | G1: physical store | H1: installation | I1: delivery | J1: local supply | K1: import
A2: Compact monitor bracket | B2: SCAN | C2: info@scanmalta.com | G2: yes | H2: yes | I2: yes | J2: yes | K2: yes
A3: Compact monitor bracket | B3: Klikk | C3: sales@klikk.com.mt | G3: yes | H3: yes | I3: yes | J3: yes | K3: yes
A4: Compact monitor bracket | B4: Game Breaker | C4: info@gamebreakermalta.com | G4: yes | H4: no | I4: yes | J4: yes | K4: yes
A5: Compact monitor bracket | B5: AtoZ | C5: marketing@atoz.com.mt | G5: yes | H5: yes | I5: yes | J5: yes | K5: yes
A6: Compact monitor bracket | B6: Xpert | C6: sales@xpert.mt | G6: yes | H6: no | I6: yes | J6: yes | K6: yes
A7: Compact monitor bracket | B7: Computer Bargains | C7: info@computerbargainsmalta.com | G7: yes | H7: no | I7: yes | J7: yes | K7: yes
A8: Compact monitor bracket | B8: HomeMate | C8: customercare@homemate.com.mt | G8: yes | H8: yes | I8: yes | J8: yes | K8: yes
A9: Compact monitor bracket | B9: MaltaZon | C9: info@maltazon.com | G9: yes | H9: no | I9: yes | J9: yes | K9: yes
A10: Compact monitor bracket | B10: Forestals | C10: info@forestals.com | G10: yes | H10: yes | I10: yes | J10: yes | K10: yes
A11: Compact monitor bracket | B11: Top Choice | C11: info@topchoice.com.mt | G11: yes | H11: yes | I11: yes | J11: yes | K11: yes
A12: Compact monitor bracket | B12: Digital Zone | C12: info@digitalzone.com.mt | G12: yes | H12: no | I12: yes | J12: yes | K12: yes
A13: Compact monitor bracket | B13: Intercomp | C13: infosales@intercomp.com.mt | G13: yes | H13: yes | I13: yes | J13: yes | K13: yes
... A18: Compact monitor bracket | B18: The Notebook Center | C18: info@thenotebookcentre.com.mt | G18: yes | H18: no | I18: yes | J18: yes | K18: yes

Sheet Laser
A1: item | B1: supplier | C1: email | D1: phone number | E1: location | F1: website | G1: physical store | H1: delivery | I1: local supply | J1: import
A2: laser | B2: WJA Distributor | C2: info@wjadistributors.com | D2: 21809426 | E2: Dejma Road, Tarxien | F2: https://www.wjadistributors.com/product/bosch-cross-line-laser-advancedlevel-360/ | G2: yes | H2: yes | I2: yes | J2: no

Sheet Surveyors
A1: item | B1: supplier | C1: email | D1: phone number | E1: location | F1: website | G1: notes
A2: surveyor | B2: GeoMatix | C2: info@surveyingmalta.com | D2: 27440103 / 77440103 | E2: 8, Triq il-Laring, Attard, ATD 2531 Malta | F2: Geomatix Surveying | G2: Does land surveying, 3D scanning and drone surveying
A3: surveyor | B3: CM Surveying | C3: chris@cmsurveying.com.mt | D3: 99057464 | E3: No. 2, Triq Papa Piju XII, Birkirkara, Malta. | F3: https://www.cmsurveying.com/ | G3: They also offer courses
A4: surveyor | B4: Matsurv & Associates Ltd | C4: info@matsurv.eu | D4: 9949 5407 | E4: 89, Suite 1, ATL Business Centre, Triq Il-Kanun, Santa Venera, Malta | F4: https://www.facebook.com/matsurv/ | G4: Topographic surveys, 3D laser scanning,...
A5: surveyor | B5: NC Surveying | C5: ncsurveying23@gmail.com | D5: 7713 1010 | E5: NC Surveying 1 Joelle Triq Dun Guzepp Demicoli , Ghaxaq, Malta
A6: surveyor | B6: Alan Micallef Surveying Services | C6: alan@micallefsurveying.com | D6: 7970 7750 | E6: Alan Micallef Surveying Services 67 Flat 1 Triq Vince Dimech , Zurrieq, Malta ZRQ 2402 | F6: https://www.facebook.com/profile.php?id=100063536049877&utm_source=Yellow&utm_medium=Yellow-Website&utm_campaign=Landing-Page
A7: surveyor | B7: AR Surveying | C7: arsurveyingmalta@gmail.com | D7: 7941 1384 | E7: AR Surveying Triq it-Tahhan , B’Kara, Malta
A8: surveyor | B8: Atlas Surveying | C8: info@atlas-surveying.com | D8: 9998 7584 | E8: 182 Triq Bormla Paola, PLA 1905, MT, | F8: https://atlas-surveying.com/?utm_source=Yellow&utm_medium=Yellow-Website&utm_campaign=Landing-Page
A9: surveyor | B9: Impact Design | C9: impact.design.18@gmail.com | D9: 7904 9031 | E9: IMPACT design 56 Triq il-Vittmi tal-Gwerra Swatar , B’Kara, Malta
A10: surveyor | B10: Peter P Caruana | C10: lms@onvol.net | D10: 9949 6777 | E10: Peter P Caruana Shamrock Triq ta’ Giorni , San Giljan, Malta STJ 1615
A11: surveyor | B11: D&A Surveying | C11: surveying.da@gmail.com | D11: 9902 2336 | F11: https://www.checkyourtraders.com/listing/__trashed-19?fromCat=property-surveyor-surveying
A12: surveyor | B12: EllulSRV | C12: ellulsrv@gmail.com | D12: 9999 5037
A13: surveyor | B13: Malta Surveys (Shonnery Spiteri) | C13: maltasurveys.rs@gmail.com | D13: 9929 5479
A14: surveyor | B14: PSS DNA (Christopher Cassar) | C14: chris@pss-dna.com

Sheet Car Scrapping
A1: item | B1: name | C1: email | D1: phone number | E1: location | F1: website
A2: Car scrapping | B2: Tar-Robba Recycling Centre Ltd. | C2: johnghigo53@gmail.com | D2: 21683558, 99457162, 99493311 | E2: Limits of Kirkop
A3: Car scrapping | B3: Fredu Auto Parts | C3: freduautoparts@melita.com | D3: 27492222, 99490220 | E3: Plot, 6/7, Nassab Street, Qormi
A4: Car scrapping | B4: Gasparell Baling Plant Ltd. | C4: gasparell.b@gmail.com | D4: 21651475, 99495236 | E4: Ħal Far Ind Estate, Birzebbuga
A5: Car scrapping | B5: ELA Ltd. | C5: criszu75@gmail.com | D5: 21896023, 99495035, 99477294 | E5: 31, Wied Ghammieq Road Kalkara
A6: Car scrapping | B6: Auto Check Ltd. | C6: repairs@mile-end.mt | D6: 21444441, 79444441 | E6: 19/20/47, Triq l-Inginerija ma’Triq l-Iskola Teknika, Mriehel, Birkirkara
A7: Car scrapping | B7: DDE Attard | C7: info@ddeattard.com | D7: 21667857, 79442804 | E7: Scrap Lane, Valletta Road, Luqa, LQA 1764
A8: Car scrapping | B8: Roc-A-Go Services Ltd | C8: rocagoltd@gmail.com | D8: 21697766 | E8: Triq Tal-Barrani, Zejtun
A11: PROCEDURE WITH TM
A12: TM will only de-register and scrap a vehicle if the owner presents a certificate of desctruction issued by an approved desctruction facility.
A13: The authorised desctruction facility will issue a Certificate of Destruction. The certificate must be presented to TM during the scrapping process.
A15: AFTER the vehicle is taken to the treatment facility, the registered owner must call personally at the offices of TM and present the following documents:
A16: 1. Logbook
A17: 2. Registration number plate
A18: 3. Circulation license disc
A19: 4. Application form VEH13
A20: 5. Vehicle desctruction certificate
A22: CALL THE ABOVE AND ASK THEM TO EXPLAIN WHAT THE PROCESS IS AND HOW IT WORKS SO WE GET MORE INFO

Sheet Sills
A1: item | B1: supplier | C1: email | D1: phone number | E1: location | F1: website
A2: window sills | B2: design hub Store Malta | C2: info@designhubmalta.com.mt | D2: 99441703 | E2: 59 triq Domenico Cachia ,Birkirkara BKR 4019 ,MALTA | F2: designhubstores.com
A3: window sills | B3: Soll Malta | C3: info@soll.mt | D3: 21234567 | E3: triq il-Kalkara , Marsa , Malta | F3: soll.mt
A4: window sills | B4: Rabat marbles | C4: info@rabatmarbles.com | D4: 21456789 | E4: triq-il-Kbira , Rabat ,Malta | F4: rabatmarbles.com
A5: window sills | B5: Lawrence Fenech Ltd | C5: info@lawrencefenech.com | D5: 21345678 | E5: triq il-Labour ,Birkirkara, Malta | F5: lawrencefenech.com
A6: window sills | B6: AM Projects Malta | C6: info@pvc.com.mt | D6: 21654321 | E6: triq il-Ferrovija, Ħamrun, Malta | F6: pvc.com.mt
A7: window sills | B7: Finestral Malta | C7: info@finestralmalta.com | D7: 21468789 | E7: Triq il-Kostituzzjoni, Mosta, Malta | F7: finestralmalta.com
A8: window sills | B8: Building Materials Supplies Ltd(BMS Malta ) | C8: bmsltdmalta@gmail.com | D8: 21466668 | E8: Mdina Road, Qormi QRM 9011, Malta | F8: bms-malta.com
A9: window sills | B9: Graham Aluminium & Sons Ltd | C9: info@grahamaluminium.com | D9: 99994120 | E9: Mdina Road, Qormi QRM 9011, Malta | F9: grahamaluminium.com
A10: window sills | B10: Meli Bugeja Ltd | C10: info@melibugeja.com.mt | D10: 21444348 | E10: Triq il-Mithna,Qormi | F10: meliobugeja.com.mt
A11: window sills | B11: window World International | C11: info@windowworldinternational.net | D11: 2347 2994 | E11: Zircon Suites, Triq ta' Zejfa, Mosta, Malta | F11: windowworld.eu
A12: window sills | B12: Wilga Stores | C12: wilgastores@gmail.com | D12: 21897912 | E12: Wilga Street, Luqa LQA 1530, Malta | F12: wilgastores.com
A13: window sills | B13: Nicholas aluminium | C13: info@nicholas.mt | D13: 21464761 | E13: 33,Angelo A,Melilli ,HAz Zebugg ZBG 2802 | F13: nicholas.mt
A14: window sills | B14: Dingli Aluminium | C14: info@dinglialuminium.com | D14: 99472191 | E14: triq Anthony John Coleiro , hAL Qormi | F14: dinglialuminium.com
A15: window sills | B15: Schembri Marbles | C15: schembrimarbles@yahoo.com | D15: 21678608 | E15: Triq Dwardu Buttigieg ,Hal Ghaxaq,Malta GXQ 1253 | F15: findit.com.mt
A16: window sills | B16: Attard Bros | C16: info@attardbros.com
A17: window sills | B17: R Lautier | C17: info@rlautier.com
A18: window sills | B18: Floors of Stone | C18: sales@floorsofstone.com.mt
A19: window sills | B19: Desana Marbles | C19: info@desanamarbles.com
A20: window sills | B20: Cini Marbles | C20: info@cinimarbles.com
A21: window sills | B21: Seamless | C21: sales@seamless.com.mt
A22: window sills | B22: AMA Architectural Surfaces | C22: info@amaasurfaces.com
A23: window sills | B23: RGP Marbleware | C23: portellirennie@hotmail.com
A24: window sills | B24: Tiles and Marble | C24: tilesandmarbleinfo@gmail.com
A25: window sills | B25: Helmann Vella | C25: info@halmannvella.com
B26: Quality Stone Malta | C26: info@qualitystonemalta.com
B27: Marble Innovation | C27: sales@marbleinnovation.com
B28: C. Grech Marbles | D28: 9977 0099
B29: Show Tiles and More | C29: frankvassallo22@gmail.com
B30: Keith Bugeja Marble Works | C30: keithbugeja@hotmail.com

Sheet Waterproofing
A1: item | B1: supplier | C1: email | D1: phone number | E1: location | F1: website | G1: physical store | H1: installation | I1: delivery | J1: local supply | K1: import
A2: Waterproofing | B2: The Resin & Membrane Centre | C2: info@theresincentre.com | D2: 2747 7647 | E2: 264, Old Railway Track Santa Venera | F2: https://theresincentre.com/contact-us/ | G2: yes | H2: yes | I2: yes | J2: no | K2: yes
A3: Waterproofing | B3: Kenda Waterproofing | C3: kwaterproofing@melita.com | D3: 7972 9967 | E3: 24, Triq Indri Micallef,Luqa, Malta | F3: https://www.kendawaterproofing.com/contactV3.html# | G3: no | H3: yes | I3: yes | J3: yes | K3: no
A4: Waterproofing | B4: AG Waterproofing Services | C4: alexgrech.waterproofing@gmail.com | D4: 99 879 221 | E4: 2, Triq tal-Habaq, Luqa, Malta | F4: https://www.agwaterproofingmalta.com/ | G4: no | H4: yes | I4: yes
A5: Waterproofing | B5: CP Waterproofing | C5: colin@cpwaterproofing.com | D5: 99 445 181 | E5: Garage No 3, Pjazza l-Eroj,Swatar B'Kara BKR 4250 | F5: https://www.cpwaterproofing.com/ | G5: no | H5: yes | I5: yes | J5: yes | K5: no
A6: Waterproofing | B6: Air Solutions | C6: airsolutions@ezee.mt | D6: 7777 5495 | E6: 58, Donato del Piano Street, Zurrieq,ZRQ 2240 | F6: https://www.airsolutionslimited.com/ | G6: no | H6: yes | I6: yes | J6: yes | K6: no
A7: Waterproofing | B7: TN Waterproofing Services Ltd | C7: tnwaterproof@gmail.com | D7: 99 495 864 | E7: Cherry Blossom Triq Lorenzo Manche’, Attard, ATD 2906 | G7: no | H7: yes | I7: yes | J7: yes | K7: no
A8: Waterproofing | B8: Maximum Waterproofing | C8: danielschembri71@gmail.com | D8: 99 474 204 | E8: 102 Block A Flat 2 Triq Lapsi, Siggiewi | F8: https://www.fb.com/maximumwaterproofingmalta/ | G8: no | H8: yes | I8: yes | J8: yes | K8: no
A9: Waterproofing | B9: De Valtech | C9: info@devalier.com.mt | D9: 2149 1111 | E9: The Old Factory, San Gwakkin Str, Zone 3, Central Business District, Mriehel, B’kara, CBD 3030, Malta | F9: https://www.dv.mt/de-valtech-category/waterproofing/ | G9: yes | H9: yes | I9: yes | J9: no | K9: yes
A10: Waterproofing | B10: WP ltd | C10: wp.ltd123@gmail.com | D10: 99 445 527 | E10: WP Ltd Marcelle Triq ix-Xitwa , Qormi, Malta QRM 5234 | F10: https://www.wpmalta.com/?utm_source=Yellow&utm_medium=Yellow-Website&utm_campaign=Landing-Page | G10: no | H10: yes | I10: yes | J10: yes | K10: no
A11: Waterproofing | B11: 389 co Ltd | C11: info@389.com.mt | D11: 21 445 152 | E11: Three eight nine Co ltd (389 co Ltd) 22, 26 Triq Dun Xand Cortis , B’Kara, Malta BKR 1531 | G11: yes | H11: yes | I11: yes | J11: no | K11: yes
A12: Waterproofing | B12: C & Plastering | C12: clintsaliba3@gmail.com | D12: 79 256 240 | E12: C & R Plastering Trejqet il-Barrieri , Zurrieq, Malta ZRQ 3602 | F12: https://www.yellow.com.mt/c-r-plastering/waterproofing-contractors/ | G12: yes | H12: yes | I12: yes | J12: yes | K12: no
A13: Waterproofing | B13: Mr Lee Waterproofing | C13: mrleewaterproofing26@gmail.com | D13: 7700 3333 | F13: https://www.facebook.com/mrleewaterproofing/ | G13: no | H13: yes | I13: yes | J13: yes | K13: no
A14: Waterproofing | B14: Kibitec | C14: contact@kibitec.com | D14: 7777 1522 | F14: https://kibitec.com/waterproof-membrane-malta/ | G14: yes | H14: yes | I14: yes | J14: no | K14: yes
A15: Waterproofing | B15: Azzopardi Waterproofing | C15: azzopardiwp@gmail.com | D15: 9949 2745 | E15: Azzopardi Waterproofing Ltd 67 Triq il-Belt Valletta , Attard, Malta ATD 9056 | F15: https://www.yellow.com.mt/azzopardi-waterproofing-ltd_waterproofing-contractors+attard/ | G15: no | H15: yes | I15: yes | J15: yes | K15: no
A16: Waterproofing | B16: CHR Home Improvements | C16: caruana.chris@hotmail.com | D16: 7947 7777 | E16: CHR home improvements Triq Mikielang Sapiano , Luqa, Malta LQA 1803 | F16: https://www.facebook.com/CHR.home.improvements/?utm_source=Yellow&utm_medium=Yellow-Website&utm_campaign=Landing-Page | G16: no | H16: yes | I16: yes | J16: yes | K16: no
A17: Waterproofing | B17: Coverite Waterproofing | C17: jasonmartin777@hotmail.com | D17: 79 003 897 | E17: Coverite Waterproofing 3 Pretty Lodge Pjazza San Leonardu , Mosta, Malta MST 1061 | F17: https://www.yellow.com.mt/coverite-waterproofing_waterproofing-contractors+mosta/ | G17: no | H17: yes | I17: yes | J17: yes | K17: no
A18: Waterproofing | B18: D & G Waterproofing Membrane | C18: jurgendalli@gmail.com | D18: 99 498 925 | G18: no | H18: yes | I18: yes | J18: yes | K18: no
A19: Waterproofing | B19: JM Vassallo Vibro Steel Ltd | C19: sales@jmvibro.com | G19: yes | H19: yes | I19: yes | J19: no | K19: yes
A20: Waterproofing | B20: Andew Vassallo | C20: info@andrewvassallo.com | G20: yes | H20: yes | I20: yes | J20: no | K20: yes
A21: Waterproofing | B21: Norob Installations | C21: norob@onvol.net | G21: yes | H21: yes | I21: yes | J21: yes | K21: yes
A22: Waterproofing | B22: Forever Waterproofing | C22: forever.waterproofing@gmail.com | G22: no | H22: yes | I22: yes | J22: yes | K22: no
A23: Waterproofing | B23: L.C Waterproofing | C23: ludvic1979@gmail.com | G23: no | H23: yes | I23: yes | J23: yes | K23: no
A24: Waterproofing | B24: Martin's Waterproofing | C24: vmhome@go.net.mt | G24: no | H24: yes | I24: yes | J24: yes | K24: no
A25: Waterproofing | B25: Matuel Waterproofing | C25: matuelwaterproofing@gmail.com | G25: no | H25: yes | I25: yes | J25: yes | K25: no
A26: Waterproofing | B26: MP Liquid Membrane | C26: michael.portelli81@gmail.com | G26: no | H26: yes | I26: yes | J26: yes | K26: no
A27: Waterproofing | B27: Thermaseal | C27: admin@thermasealmalta.com | G27: no | H27: yes | I27: yes | J27: no | K27: yes
A28: Waterproofing | B28: Rosman Waterproofing | C28: rosmanwaterproofing@hotmail.com | G28: no | H28: yes | I28: yes | J28: yes | K28: no
A29: Waterproofing | B29: Joseph Stivala | C29: jostiv@live.com | G29: no | H29: yes | I29: yes | J29: yes | K29: no
A30: Waterproofing | B30: BCF Solutions | C30: bcf_solutions@outlook.com | G30: no | H30: yes | I30: yes | J30: yes | K30: no
A31: Waterproofing | B31: OIJ - Leak Detection and Maintenance | C31: oijwatermaintenance@gmail.com | G31: no | H31: yes | I31: yes | J31: yes | K31: no
A32: Waterproofing

Sheet Surface finishes
A1: item | B1: supplier | C1: email | D1: phone number | E1: location | F1: website

Sheet Terrazzo Slabs
A1: item | B1: supplier | C1: email | D1: phone number | E1: location | F1: website | G1: physical store | H1: intallation | I1: delivery | J1: local supply | K1: import
A2: Terrazzo Slab | B2: Carra.design | C2: c.demirkiran@carradesign.com | D2: 7712 2494 | F2: https://www.facebook.com/p/Carradesign-100086413076922/ | G2: no | H2: yes | I2: yes | J2: yes | K2: no
A3: Terrazzo Slab | B3: Absolute | C3: info@absolute.com.mt | D3: 2141 7596 | F3: https://www.absolute.com.mt/terrazzo/ | G3: yes | H3: yes | I3: yes | J3: yes | K3: no
A4: Terrazzo | B4: Helmann Vella | C4: info@halmannvella.com | D4: 2143 3636 | F4: https://www.halmannvella.com/ | G4: yes | H4: yes | I4: yes | J4: yes | K4: yes
A5: Terrazzo | B5: Desana Marbles | C5: info@desanamarbles.com | D5: 2145 1350 | F5: https://www.desanamarbles.com/materials/terrazzo | G5: yes | H5: yes | I5: yes | J5: yes | K5: yes
B6: Marble Innovation | C6: sales@marbleinnovation.com | F6: https://www.marbleinnovation.com/contact | G6: yes | H6: yes | I6: yes | J6: yes | K6: yes
B7: Pitre Bathrooms | C7: info@jpitre.com | D7: 21463335 | F7: https://www.pitrebathrooms.com/contact-us | G7: yes | H7: no | I7: yes | J7: yes | K7: no
B8: Iperceramica | C8: msida@iperceramica.mt | G8: yes | H8: no | I8: yes | J8: no | K8: yes
B9: Rado Flooring | C9: info@radosystems.eu | F9: https://www.facebook.com/radoflooring/ | G9: no | H9: yes | I9: yes | J9: yes | K9: no
B10: Cordina | C10: steve@cordina.eu | F10: https://www.facebook.com/cordinamt/ | G10: no | H10: yes | I10: yes | J10: yes | K10: no
B11: MRCD | C11: info@mrcd.com.mt | F11: https://www.mrcd.com.mt/en/home.htm | G11: yes | H11: no | I11: yes | J11: no | K11: yes
B12: CP Marbles | C12: cpcamilleripatrick@gmail.com | F12: https://www.facebook.com/profile.php?id=100054506707941 | G12: yes | H12: yes | I12: yes | J12: yes | K12: yes
B13: Seamless Surfaces | C13: sales@seamless.com.mt | F13: https://www.facebook.com/seamlessmalta/ | G13: yes | H13: yes | I13: yes | J13: yes | K13: yes
C14: sales@floorsofstone.com.mt
C15: info@cgaleamarble.com
C16: info@chicliving.com.mt
C17: info@distincthomes.com.mt
C18: info@bfmarbles.com
C19: info@soll.mt

Sheet Washing Machines
A1: item | B1: supplier | C1: email | D1: phone number | E1: location | F1: website | G1: physical store | H1: installation | I1: delivery | J1: local supply | K1: import
A2: washing machines | B2: Flamingo malta | C2: info@flamingo.com.mt | D2: 21443333 | E2: Mrieħel, Malta | F2: flamingo.com.mt | G2: yes | H2: yes | I2: yes | J2: yes | K2: yes
A3: washing machines | B3: WashingMachinesMalta | C3: info@washingmachinesmalta.com | D3: 2732 0796 | E3: Distribution Warehouse Center, Qormi, Malta | F3: washingmachinesmalta.com | G3: no | H3: yes | I3: yes | J3: yes | K3: yes
A4: washing machines | B4: Top Choice | C4: info@topchoice.com.mt | D4: 2123 4567 | E4: Il-Ħamrun y San Pawl il-Baħar, Malta | F4: topchoice.com.mt | G4: yes | H4: yes | I4: yes | J4: yes | K4: yes
A5: washing machines | B5: Petroni Ltd. | C5: info@petroni.com.mt | D5: 2133 2233 | E5: Msida, Malta | F5: petroni.com.mt | G5: yes | H5: yes | I5: yes | J5: yes | K5: yes
A6: washing machines | B6: Teckline Discount Store | C6: info@teckline.com.mt | D6: 2124 5678 | E6: Il-Ħamrun, Malta | F6: teckline.com.mt | G6: yes | H6: yes | I6: yes | J6: yes | K6: yes
A7: washing machines | B7: . Sound Machine | C7: info@soundmachine.com.mt | D7: 2149 7111 | E7: Psaila Street, Birkirkara, Malta | F7: soundmachine.com.mt | G7: yes | H7: yes | I7: yes | J7: yes | K7: yes
A8: washing machines | B8: KCL Home Centre | C8: info@kcl.com.mt | D8: 2149 3285 / | E8: 22, Triq Sant' Elija, Birkirkara, Fleur-De-Lys, Malta BKR 4942 | F8: www.kcl.com.m | G8: yes | H8: yes | I8: yes | J8: yes | K8: yes
A9: washing machines | B9: JS Household | C9: info@jshousehold.com | D9: 2169 1334 | E9: 71, Triq Il-Buqexrem, Il-Fgura, Malta | F9: jshousehold.com | G9: yes | H9: yes | I9: yes | J9: yes | K9: yes
A10: washing machines | B10: Hotpoint Malta | C10: info@hotpointmalta.com | D10: 2343 6345 | E10: Valley Road, Birkirkara BKR9010, Malta | F10: hotpointmalta.com | G10: yes | H10: yes | I10: yes | J10: yes | K10: yes
A11: washing machines | B11: Lava.mt ( | C11: info@lava.mt | D11: -------------------- | E11: Zachary House, Marsa Industrial Estate, Marsa MRS 3000, Malta | F11: lava.mt | G11: no | H11: yes | I11: yes | J11: yes | K11: yes
A12: washing machines | B12: Crosscraft | C12: info@crosscraft.com.mt | D12: 2180 5805 | E12: Mriehel Bypass, Qormi, Malta | F12: crosscraft.com.mt | G12: yes | H12: yes | I12: yes | J12: yes | K12: yes
A13: washing machines | B13: Audio Malta | C13: info@audiomalta.com | D13: 2138 2876 | E13: 26C Triq Lispiera, Swieqi, Malta | F13: audiomalta.com | G13: yes | H13: no | I13: yes | J13: yes | K13: yes
A14: washing machines | B14: ElectroFix Malta | C14: info@electrofix.com.mt | D14: 2144 5555 | E14: Triq il-Kanun, Qormi, Malta | F14: https://www.electrofixgroup.com/ | G14: yes | H14: no | I14: yes | J14: yes | K14: yes
... A24: washing machines | B24: Freddie's Household | C24: freddies@onvol.net | D24: 2143 2863 | E24: Eucharistic Congress Road, Mosta, Malta | F24: ________ | G24: yes | H24: yes | I24: yes | J24: yes | K24: yes

Sheet Tumble Dryer
A1: item | B1: supplier | C1: email | D1: phone number | E1: location | F1: website | G1: physical store | H1: installation | I1: delivery | J1: local supply | K1: import
A2: Tumble Dryer | B2: Ventura General Gas Ltd | C2: adriangrech@venturamalta.com | D2: 21 677 798 | E2: BLB 021 Qasam Industrijali, Bulebel , Zejtun, Malta ZTN 3000 | F2: www.venturamalta.com | G2: yes | H2: yes | I2: yes | J2: yes | K2: yes
A3: Tumble Dryer | B3: Forestals | C3: info@forestals.com | D3: 2549 3000 | E3: Mrieħel Bypass, Birkirkara, Malta | F3: forestals.com | G3: yes | H3: yes | I3: yes | J3: yes | K3: yes
A4: Tumble Dryer | B4: AtoZ Electronics | C4: info@atoz.com.mt | D4: 2133 6600 | E4: Valley Road, Msida, Malta | F4: atoz.com.mt | G4: yes | H4: yes | I4: yes | J4: yes | K4: yes
A5: Tumble Dryer | B5: Crosscraft | C5: info@crosscraft.com.mt | D5: 2180 5805 | E5: Mriehel Bypass, Qormi, Malta | F5: crosscraft.com.mt | G5: yes | H5: yes | I5: yes | J5: yes | K5: yes
A6: Tumble Dryer | B6: Homemate | C6: customercare@homemate.com.mt | D6: 2326 2000 | E6: Mriehel | F6: https://www.homemate.com.mt/product/midea-free-standing-tumble-dryer-white-10kg-a-class | G6: yes | H6: no | I6: yes | J6: yes | K6: yes
A7: Tumble Dryer | B7: Hotpoint Malta | C7: info@hotpointmalta.com | D7: 2343 6345 | E7: Valley Road, Birkirkara BKR9010, Malta | F7: hotpointmalta.com | G7: yes | H7: yes | I7: yes | J7: yes | K7: yes
A8: Tumble Dryer | B8: KCL Home Centre | C8: info@kcl.com.mt | D8: 2149 3285 / | E8: 22, Triq Sant' Elija, Birkirkara, Fleur-De-Lys, Malta BKR 4942 | F8: www.kcl.com.m | G8: yes | H8: yes | I8: yes | J8: yes | K8: yes
A9: Tumble Dryer | B9: Sound Machine | C9: info@soundmachine.com.mt | D9: 2149 7111 | E9: Psaila Street, Birkirkara, Malta | F9: soundmachine.com.mt | G9: yes | H9: yes | I9: yes | J9: yes | K9: yes
A10: Tumble Dryer | B10: Petroni Ltd. | C10: info@petroni.com.mt | D10: 2133 2233 | E10: Msida, Malta | F10: petroni.com.mt | G10: yes | H10: yes | I10: yes | J10: yes | K10: yes
A11: Tumble Dryer | B11: Top Choice | C11: info@topchoice.com.mt | D11: 2123 4567 | E11: Il-Ħamrun y San Pawl il-Baħar, Malta | F11: topchoice.com.mt | G11: yes | H11: yes | I11: yes | J11: yes | K11: yes
A12: Tumble Dryer | B12: Flamingo malta | C12: info@flamingo.com.mt | D12: 21443333 | E12: Mrieħel, Malta | F12: flamingo.com.mt | G12: yes | H12: yes | I12: yes | J12: yes | K12: yes
A13: Tumble Dryer | B13: Vitel Home | C13: info@vitelmalta.com | D13: 21377172 | E13: Triq R. Caruana Dingli San Gwann, SGN 1035 Malta. | F13: https://vitelmalta.com/shop/domestic-appliances/laundry-appliances/tumble-dryers/keen-tumble-dryer-10kg-dhb1053ba/ | G13: yes | H13: yes | I13: yes | J13: yes | K13: yes
A14: Tumble Dryer | B14: Triple A | C14: info@triplea.mt | D14: 21257346 | E14: Triple A Luqa 1, St. Thomas Street,, Ħal Luqa LQA 9031 | F14: https://triplea.mt/contactus | G14: yes | H14: yes | I14: yes | J14: yes | K14: yes
A15: Tumble Dryer | B15: Paulson | C15: paulsonmalta@gmail.com | D15: 2166 3329 | E15: Paulson Home & Hi-Fi Centre, Bir Deheb Road, Zejtun, Malta | F15: https://www.paulson.com.mt/en/shop/webshop/683/concorde-10kg-tumble-dryer---condenser | G15: yes | H15: yes | I15: yes | J15: yes | K15: yes
A16: Tumble Dryer | B16: ProChimps | C16: info@prochimps.com | D16: 9978 5765 | E16: Santa Venera, Canon Road, Malta | F16: https://prochimps.com/collections/tumble-dryer | G16: yes | H16: yes | I16: yes | J16: yes | K16: yes
A17: Tumble Dryer | B17: Right Deal | G17: yes | H17: yes | I17: yes | J17: yes | K17: yes
A18: Tumble Dryer | B18: Paulson | G18: yes | H18: yes | I18: yes | J18: yes | K18: yes

Sheet Gypsum
A1: item | B1: supplier | C1: email | D1: phone number | E1: location | F1: website | G1: physical store | H1: installation | I1: delivery | J1: local supply | K1: import
A2: gypsum | B2: Summit Importers & Distributors | C2: sales@summit.com.mt | D2: 2141 1206 | E2: Xwieki Road, Triq Tal-Balal, Tal-Balal, Iklin, IKL 9013, Malta | F2: www.summit.com.mt | G2: yes | H2: no | I2: yes | J2: no | K2: yes
A3: gypsum | B3: CA Gypsum | C3: cagypsum@onvol.net | D3: 2741 8713 | E3: 107, Triq L-Istadju, Gzira, GZR 1301, Malta | F3: www.cagypsummalta.com | G3: no | H3: yes | I3: yes | J3: yes | K3: no
A4: gypsum | B4: D Gypsum and Lights | C4: dgypsumandlights@gmail.com | D4: 2705 2100 | E4: Triq Hal Tarxien, Il-Gudja, Malta | F4: www.dgypsumworks.com | G4: no | H4: yes | I4: yes | J4: yes | K4: no
A5: gypsum | B5: Grant's Gypsum Work | C5: grantgypsumwork@gmail.com | D5: 7945 0373 | E5: 13, Triq Ignazio Saverio Mifsud, Birkirkara, BKR1017, Malta | F5: www.grantsgypsumwork.com | G5: no | H5: yes | I5: yes | J5: yes | K5: no
A6: gypsum | B6: Galea & Tonna Gypsum Works | C6: gplusgypsum@gmail.com | D6: 9980 4706 | E6: 43, Triq Qrajten, Tal-Pieta', Malta | F6: --------------------- | G6: no | H6: yes | I6: yes | J6: yes | K6: no
A7: gypsum | B7: Buffa Malta | C7: buffamalta@t4bservices.com | D7: 2148 5629 | E7: Valletta Road, Qormi (frente a Maltapost), Malta | F7: --------------------- | G7: yes | H7: no | I7: yes | J7: no | K7: yes
A8: gypsum | B8: P J Gypsum Works | C8: pjgypsumworks@gmail.com | D8: 9982 6705 | E8: 94, Emmant, Triq Salvu Aquilina, Mosta, MST 3162, Malta | F8: www.pjgypsumworks.com | G8: no | H8: yes | I8: yes | J8: yes | K8: no
A9: gypsum | B9: Pierre Chircop Gypsum Works | C9: pchircop76@gmail.com | D9: 7944 8833 | E9: Marsaxlokk, Malta | F9: www.summit.com.mt | G9: no | H9: yes | I9: yes | J9: yes | K9: no
A10: gypsum | B10: Grima Interiors | C10: grimainteriors@hotmail.com | D10: 9988 8272 / | E10: Triq Luret Cutajar, Ħaż-Żebbuġ ZBG 273, Malta | F10: www.grimainteriors.com | G10: no | H10: yes | I10: yes | J10: yes | K10: no
A11: gypsum | B11: Donovan Plastering | C11: donovanplastermalta@gmail.com | D11: 7727 0833 | E11: 49 Triq Spadaro, Ħaż-Żabbar, Malta | F11: www.donovan-plastering.com | G11: no | H11: yes | I11: yes | J11: yes | K11: no
A12: gypsum | B12: JCR Imports Ltd | C12: jattard@jcrimports.com.mt | D12: 2144 2466 | E12: Triq In-Negozju, Mrieħel, Birkirkara BKR 3000, Malta | F12: www.jcrimports.com.mt | G12: yes | H12: no | I12: yes | J12: no | K12: yes
... A15: gypsum | B15: Mediterranean Building Finishes Ltd | C15: info@mbfmalta.com | D15: 2137 4454 | E15: Riviera Court/2, Triq Forrest, San Ġiljan, Malta | F15: www.mbfmalta.com | G15: no | H15: yes | I15: yes | J15: yes | K15: no
A16: Gypsum | B16: GRF Malta | C16: info@grfmalta.com | D16: 21377378 | E16: 117 Triq L-Assemblea Nazzjonali, San Gwann SGN 3034, Malta | F16: https://grfmalta.com/ | G16: no | H16: yes | I16: yes | J16: yes | K16: no
A17: Gypsum | B17: O&M Gypsum | C17: oandmgypsum.com@gmail.com | D17: 2149 2920 | E17: 69, Triq John Borg, Birkirkara, Malta BKR 1284 | F17: https://www.findit.com.mt/en/directory/listings/441/oandampm-gypsum-malta.htm | G17: no | H17: yes | I17: yes | J17: yes | K17: no
A18: Gypsum | B18: Perfectum | C18: Info@perfectum.mt | D18: 9921 5215 | E18: Valletta, Malta | F18: https://www.facebook.com/perfectummt/ | G18: no | H18: yes | I18: yes | J18: yes | K18: no
A19: Gypsum | B19: GAD Finishings | C19: alex@gad.com.mt | D19: 9947 2226 | E19: 21, Triq Gellewza Sewda, Midland Park, D7 Burmarrad Road, Burmarrad LO Naxxar Malta | F19: https://www.gad.com.mt/ | G19: no | H19: yes | I19: yes | J19: yes | K19: no
A20: Gypsum | B20: Xuereb Instalations Ltd | C20: xil@xuerebinstall.com | D20: 99492278 | E20: Xuereb Installations Ltd. Tal-Hlas Road, Qormi QRM 5011. Malta | F20: https://xuerebinstall.com/ | G20: no | H20: yes | I20: yes | J20: yes | K20: no
A21: Gypsum | B21: JG Gypsum | C21: josephgiordano54@gmail.com | D21: 79939898 | E21: Hal Mula Street, Garage number 5. | F21: https://josephgiordano54.wixsite.com/josephgiordano | G21: no | H21: yes | I21: yes | J21: yes | K21: no
A22: Cement Boards | B22: Meli Bugeja | C22: info@melibugeja.com.mt | D22: 7908 7476 | F22: melibugeja.com.mt | G22: yes | H22: no | I22: yes | J22: no | K22: yes
A23: Gypsum | B23: Deo's Interiors | C23: lukeattard89@gmail.com | D23: 9988 7158 | F23: https://www.facebook.com/profile.php?id=61560664902130 | G23: no | H23: yes | I23: yes | J23: yes | K23: no

Sheet Cubicle Partitions
A1: item | B1: supplier | C1: email | D1: phone number | E1: location | F1: website | G1: other
A2: partition | B2: CRC Group | C2: marketing@crcmalta.com | D2: 7741 9400 | F2: https://www.crcmalta.com/shop/category/partitions-cubicles-for-showers-or-w-cs-656
A3: partition | B3: Quality Postform | C3: qualitypostform@gmail.com | D3: 2123 8054 | F3: https://www.qualitypostform.com/en/products/products/21/algonquin-anti-vandal-cubicles
A4: partition | B4: ProBuild | C4: sales@probuildmalta.com | D4: 7741 9500 | F4: https://www.probuildmalta.com/
A5: partition | B5: BSL Lifestyles | C5: sales@bsl-lifestyles.com | F5: https://bsl-lifestyles.com/product-category/partitions-panels/?offset=4
A6: partition | B6: Da Valier | C6: info@devalier.com.mt | F6: https://www.dv.mt/showroom-category/office-partitions/
A7: partition | B7: Xuereb Installations | C7: xil@xuerebinstall.com | F7: https://xuerebinstall.com/our-service/demountable-partitions/
A8: partition | B8: Trends | C8: info@trendsltdmalta.com | F8: https://www.trendsltdmalta.com/products/commercial-bathrooms/cubicles/
A9: partition | B9: Dimech Enterprises | C9: sales@dimech-ent.com | F9: https://www.dimech-ent.com/
B10: Sham Decorations | D10: 9914 8332
B11: Shaker | C11: sales@shaker.com.mt
B12: Jialifu (CHINA) | C12: sales@jialifucn.com | F12: https://www.jialifucn.com/compact-laminate-toilet-partitions/

Sheet Site Clearance
A1: item | B1: supplier | C1: email | D1: phone number | E1: location | F1: website
A2: Tile remover/torba, Carting away of materials | B2: Fardell Home Maintenance | C2: fardellhonda@gmail.com | D2: 9968 5377 | E2: 111-113 Hompesch Road, Fgura | F2: https://fardellhonda.wixsite.com/fardellmaintenance
A3: Carting away | B3: Vella Brothers & Sons | C3: info@vellabrothersandsons.com | D3: 2145 5674 / 7945 5674 | E3: TA' DMIEREK QUARRY c/o Maghlaq Quarry - Panoramic Road, Qrendi | F3: https://vellabrothersandsons.com/index.html

Sheet Industrial Shelving
A1: item | B1: supplier | C1: email | D1: phone number | E1: location | F1: website | G1: physical store | H1: installation | I1: delivery | J1: local supply | K1: import
A2: industrial shelving | B2: Ennegi Enterprises Ltd | C2: sales@ennegiltd.com | D2: 2146 3517 | E2: 237, Triq Hal Qormi, Marsa, MRS 9045, Malta | F2: www.ennegiltd.com | G2: yes | H2: yes | I2: yes | J2: no | K2: yes
A3: industrial shelving | B3: Storage Systems Ltd | C3: storagesys@vol.net.mt | D3: 2148 8450 | E3: KW12, Zona Industrijali Ta' Kordin, Coradino, Paola, Malta | F3: www.storagesystems.com.mt | G3: yes | H3: yes | I3: yes | J3: no | K3: yes
A4: industrial shelving | B4: Caravel Ltd | C4: dario@caravelmalta.com | D4: 2134 0289 | E4: ‘Raycop’, Plot 13/15, Sqaq iz-Ziemel, Handaq, Qormi QRM-4003, Malta | F4: www.caravelmalta.com | G4: yes | H4: yes | I4: yes | J4: no | K4: yes
A5: industrial shelving | B5: AGP Systems Ltd | C5: info@agps.com.mt | D5: 2279 2123 | E5: Zamco Buildings, Triq Il-Mithna, Hal Qormi, QRM 3103, Malta | F5: www.agps.com.mt | G5: yes | H5: yes | I5: yes | J5: no | K5: yes
A6: industrial shelving | B6: T4B Services Ltd | C6: info@t4bservices.com | D6: 2123 7555 | E6: Canter Business Centre, Triq Patri Felicjan Bilocca, Il-Marsa, Malta | F6: www.t4bservices.com | G6: yes | H6: yes | I6: yes | J6: no | K6: yes
A7: industrial shelving | B7: ALFEN Displays | C7: alfen@maltanet.net | D7: 2122 5721 | E7: 96, Triq Il-Kbira San Guzepp, Il-Hamrun, Malta | F7: www.alfendisplays.com | G7: yes | H7: yes | I7: yes | J7: no | K7: yes
A8: industrial shelving | B8: UDS Limited (Upward Door Systems Ltd) | C8: uds@maltanet.net | D8: 2156 4456 | E8: Factory C, Triq L-Industrija, Ix-Xewkija (Gozo) XWK 3000, Malta | F8: www.udsmalta.com | G8: yes | H8: yes | I8: yes | J8: no | K8: yes
A9: industrial shelving | B9: 360 Retail Supplies Ltd | C9: info@360rs.com.mt | D9: 2713 9608 | E9: 360 Business Center, Mdina Road, Ħaż-Żebbuġ, ZBG 9014, Malta | F9: www.360retailsupplies.com | G9: yes | H9: yes | I9: yes | J9: no | K9: yes
A10: industrial shelving | B10: deValtech Co Ltd | C10: info@devaltech.com | D10: 7942 5055 | E10: de Valtech Building, San Gwakkin Street, Zone 3, Central Businees District, Mriehel CBD 3030 Birkirkara, Malta | F10: https://www.dv.mt/de-valtech/ | G10: yes | H10: yes | I10: yes | J10: no | K10: yes
A11: industrial shelving | B11: de Valier | C11: info@devalier.com.mt | D11: 21491111 | E11: The Old Factory, San Gwakkin str, Mriehel,Central Business District Birkirkara CBD, 3030 | F11: https://www.dv.mt/ | G11: yes | H11: yes | I11: yes | J11: no | K11: yes
A12: industrial shelving | B12: Metalock Malta Ltd | C12: info@metalock.com.mt | D12: 9968 5778 | E12: The Hillock - Block North C 8, Triq Il-Qolla S-Safra, Marsalforn, MFN 1405, Gozo | F12: metalock.com.mt | G12: yes | H12: yes | I12: yes | J12: no | K12: yes
A13: industrial shelving | B13: Ramilene Office Supplies Ltd | C13: info@ramilenemalta.com | D13: 2133 4716 | E13: 50/51, Triq It-Torri, Birkirkara, Is-Swatar, Malta BKR 4011 | F13: https://ramilenemalta.com/ | G13: yes | H13: yes | I13: yes | J13: no | K13: yes
A14: industrial shelving | B14: Intervisions Ltd | C14: info@intervisions.com.mt | D14: 2143 8925 | E14: Hard Rocks Industrial Park, Triq Burmarrad, Naxxar, Malta NXR 6345 | F14: www.intervisions.com.mt | G14: yes | H14: yes | I14: yes | J14: no | K14: yes
A15: industrial shelving | B15: Petrolea Ltd | C15: info@petroleamalta.com | D15: 2123 4501 | E15: Valley Road, Msida, Malta | F15: www.petroleamalta.com | G15: yes | H15: no | I15: yes | J15: no | K15: yes
A16: industrial shelving | B16: SC Engineering | C16: sales@scengineering.com.mt | D16: 21693621 / 99498659 | E16: 322, Qasam Industrijali Ta' Hal Luqa Hal Luqa, Malta | F16: https://www.scengineering.com.mt/ | G16: yes | H16: yes | I16: yes | J16: no | K16: yes

Sheet multysensory room
A1: Multisensory room
A2: item | B2: supplier | C2: email | D2: phone number | E2: location | F2: website | G2: physical store | H2: installation | I2: delivery | J2: local supply | K2: import
A3: Fiber Optic Lighting | B3: Unicare Ltd | C3: info@unicare.com.mt | D3: +356 2144 5544 | E3: Birkirkara, Malta | F3: unicare.com.mt | G3: yes | H3: yes | I3: yes | J3: no | K3: yes
A4: Sensory Cushions | B4: Edusell Malta | C4: info@edusell.com.mt | D4: +356 2189 4712 | E4: Hamrun, Malta | F4: edusell.com.mt | G4: yes | H4: no | I4: yes | J4: no | K4: yes
A5: multi sensory equipment and furniture | B5: noriva ltd | C5: info@noriva.com.mt | D5: 21413112 | E5: mosta ,malta | F5: www.noriva.com.mt | G5: yes | H5: yes | I5: yes | J5: no | K5: yes
A6: multi sensory equipment and furniture | B6: AIM enterprises ltd | C6: info@aim.com.mt | D6: 21802828 | E6: 54 telghet rahal gdid,PAOLA,MALTA,PLA 1706 | F6: www.facebook.com/AimEnterprisesLtd | G6: yes | H6: yes | I6: yes | J6: no | K6: yes
A7: multi sensory equipment and furniture | B7: TJ novelty | C7: info@tjnovelty.com | D7: 356 2733 3444 | E7: triq Dun Karm Schembri,Mosta MST 2440-MALTA | F7: www.tjnovelty.com | G7: yes | H7: no | I7: yes | J7: no | K7: yes

Sheet Bathroom
A1: item | B1: supplier | C1: email | D1: phone number | E1: location | F1: website
A2: tiles | B2: Satarino Tiles | C2: info@satarino.com | D2: +356 2149 1249 | E2: 122, Msida Valley Road, B'kara, BKR 9024 | F2: www.satariano.com
A3: tiles | B3: Deluxe Bathrooms | C3: deluxebathroomsmanagement@gmail.com | D3: 21 560 388; 79 902 613; 99 307 711 | E3: Triq Benghazi, Ghajnsielem-Gozo, GSM 1624 | F3: www.deluxe-bathrooms.com
A4: tiles | B4: Newline Living Concepts | C4: newlineliving@gmail.com | D4: 21 563 966 | E4: Triq Papa Gwanni Pawlu II, Victoria-Gozo, Gozo VCT 9046 | F4: www.newline.com.mt
A5: tiles | B5: Newline Living Concept | C5: newlineliving@gmail.com | D5: 21 563 966 | E5: Triq Papa Gwanni Pawlu ll, Victoria-Gozo, Gozo VCT 9046 | F5: www.newline.com.mt
A6: tiles | B6: Pitre' Bathrooms | C6: info@jpitre.com | D6: 21463335 | E6: Mdina Road, Qormi, QRM 9011, Malta | F6: www.pitrebathrooms.com
A7: tiles | B7: Banju Boutique | C7: info@banjuboutique.com | D7: 2011 7900 | E7: Paola Outlet Arcade Street, Paola PLA1212 | F7: www.banjuboutique.com
A8: tiles | B8: Bridgepoint Ltd | C8: sales@bridgepoint.com.mt | D8: 27 922 222 | E8: No 3, Triq Ferdinand Inglott, Attard ATD 3134 | F8: www.bridgepoint.com
A9: tiles | B9: Gozo Baths Ceramics | C9: gozobaths@gmail.com | D9: 9993 2230 | E9: Triq Dun Karm, Birkirkara, Malta | F9: https://www.facebook.com/p/Gozo-Baths-Ceramics-100063540523723/
A10: tiles | B10: Alex Mercieca Bathroom Centre Limited | C10: info@alexmercieca.com | D10: +365 2169 5438; +356 2167 2049; +365 7940 2553 | E10: 25th November Avenue, Zejtun, ZTN2019 | F10: www.alexmercieca.com
A11: tiles | B11: D Floorings Parquet and more | C11: dfloorings@gmail.com | D11: 27 445 533 | E11: Vjal il-Helsen, Zebbug, Malta | F11: www.dfloorings.com
A12: tiles | B12: Faenza | C12: faenzabathroomsmalta@gmail.com | D12: 79 218 080 | E12: 7 Triq I-Erba' Qaddisin | F12: www.faenzabathrooms.com
A13: tiles | B13: SBM Marble & Granite | C13: simonbonnicimarble@gmail.com | D13: 99 470 302 | E13: 5 Triq Profs Carmelo Coleiro Tal-Handaq, Qormi, Malta QRM 4000 | F13: www.sbmmarble.com
A14: tiles | B14: A F Ellis Ltd | C14: mail@afellis.com.tm | D14: 21 556 021 | E14: Triq il-Taflija Qasam Industrijali, Xewkija-Gozo, Gozo XWK 3000 | F14: www.afellis.com.mt
A15: tiles | B15: NSN TILES AND CERAMICS | C15: naasan.co@gmail.com | D15: 21 805 839 ; 99 707 639 | E15: 226, Triq Alfred Cachia Zammit, Zejtun, Malta | F15: www.nsntilesandceramics.com
A16: tiles | B16: Vella Falzon | C16: info@vellafalzon.com / aaquilina@vellafalzon.com | D16: 2144 5165 | E16: 13, Triq il-Furnar Qormi QRM 3504, Malta | F16: www.wvellafalzon.com
A17: tiles | B17: Vellmann | C17: info@vellmann.com | D17: 21424990 | E17: Pantar Road Hal Lija LJA, 2023 | F17: www.vellmann.com
A18: tiles | B18: Magri Bathrooms | C18: info@magribathrooms.com | D18: 2148 6883 ; 9949 8840 | E18: Triq il-Kanun, al Qormi, Malta | F18: www.magribathrooms.com
A19: tiles | B19: JCR Imports Limited | C19: info@jcrimports | D19: 2144 2466 | E19: Zone 3, Triq In-Negozju Central Business District Birkirkara CBD 3010 | F19: wwwjcrimports.com.mt
A20: tiles | B20: Falzon's Bathroom | C20: info@falzons.com | D20: 2148 2860; 2148 5536; 2149 5485 | E20: Falzon's Bathroom & Ceramics, Triq il-Kummerc, Qormi, Malta | F20: www.falzons.com
A21: tiles | B21: Malta DIY | C21: _____ | D21: 20341569 | E21: 160, Mdina Road, Zebbug ZBG9015 | F21: www.maltadiy.com
A22: tiles | B22: The Tile | C22: info@the-tile.com | D22: 21 371 891 | E22: Triq Bella Vista, San Gwann, Malta SGN 2690 | F22: www.the-tile.com
A23: tiles | B23: Bathroom Design | C23: info@bathroomdesign.com.mt | D23: 21 441 328 | E23: 356 Naxxar Road, B'Kara, BKR 9040, Malta | F23: www.bathroomdesign.com.mt
A24: tiles | B24: Malta Tile Centre | C24: info@tilewarehousemalta.com | D24: 9933 0274 | E24: Triq iI-Qoton, Santa Lucija, Malta | F24: www.facebook.com/tilewarehousemalta/
A25: tiles | B25: The Tub | C25: sales@thetubmalta.com | D25: 21448499 ; 79522969 | E25: 313A, Triq il-Barrieri, St Venera | F25: www.thetub.com
A26: tiles | B26: MRCD Ltd | C26: info@mrcd.com.mt | D26: 21 468770 | E26: Karmenu Camilleri Street, Qormi, QRM46 | F26: www.mrcd.com.mt
A27: tiles | B27: Carini Stores Ltd. | C27: sales@carinibathrooms.com | D27: 21 449 641; 21 440 202 | E27: 435 St. Joseph High Road, St. Venera, Malta | F27: www.carinibathrooms.com
A28: tiles | B28: Waterart Concepts | C28: info@waterartconcepts.com | D28: 2278 2000 | E28: Mill Street, Qormi QRM 3102, Malta | F28: www.waterartconcepts.com
A29: tiles | B29: JYSK | C29: jysk@jysk.com.mt | D29: 2713 7364 | E29: Triq II-Mosta, Lija, Malta | F29: www.jysk.com.mt
A30: tiles | B30: BC Bathrooms | C30: bc.bathrooms@gmail.com | D30: 2749 5590 | E30: Triq Dun Karm, B'Kara Bypass, Birkirkara BKR 2940 | F30: www.bc-bathrooms.com
A31: tiles | B31: Absolute bathrooms | C31: info@absolute.com.mt | D31: +356 2141 7596 | E31: Triq Pantar, Hal Lija | F31: www.absolute.com.mt
A32: tiles | B32: B&M | C32: info@bmsupplies.com | D32: 2144 0710 | E32: Triq Dun Karm, Kirkirkara, BKR 9035 | F32: www.bmsupplies.com
A33: tiles | B33: C. Fino + Sons | C33: info@fino.com.mt | D33: +356 2549 3000 | E33: Triq I-Imdina, Zone 4, Meriehel/Central Business District CBD 2010, Malta | F33: www.fino.com.mt
... A68: sink | B68: Firm B Pullicino | C68: info@fbpmalta.com | D68: 2167 6627 | E68: 139, Bajada Street ZBR 3011 Zabbar, Malta | F68: fbpmalta.com
A69: sink | B69: Ultra Taps
A71: bath | B71: Deluxe Bathrooms | C71: deluxebathroomsmanagement@gmail.com | D71: 21 560 388; 79 902 613; 99 307 711 | E71: Triq Benghazi, Ghajnsielem-Gozo, GSM 1624 | F71: www.deluxe-bathrooms.com
A72: bath | B72: E Grech Cristal Bath Ltd | C72: info@egrechcristalbath.com | D72: 21 483 216 | E72: Triq Salvu Psaila, B'Kara, Matla BKR 9076 | F72: www.egrechcristalbath.com
A73: bath | B73: Alfred Hili & Co Ltd | C73: sales@alfredhili.com | D73: 27 234 527 | E73: 17 Triq Guze' Galea Qormi, Malta QRM 2106 | F73: www.alfredhili.com
A74: bath | B74: Halmann Vella Ltd | C74: info@hallmannvella.com | D74: 21 433 636 | E74: The Factory Triq il-Mosta, Lija, Malta LJA 9016 | F74: www.halmannvella.com
A75: bath | B75: Bugeja Marbles | C75: bugejamarbles@gmail.com | D75: 21 448 012 | E75: Zone 3 Triq San Gwakkin Central Business District, B'kara, Malta CBD 3030 | F75: www.bugeja-marbles.com
A76: bath | B76: Custo Bathrooms | C76: custobathrooms@gmail.com | D76: 79 425 175 | E76: Triq Joe Sciberras, Hamrun, Malta HMR 1550 | F76: www.custobathrooms.com
A77: bath | B77: Alex Mercieca Bathroom Centre Limited | C77: info@alexmercieca.com | D77: +365 2169 5438; +356 2167 2049; +365 7940 2553 | E77: 25th November Avenue, Zejtun, ZTN2019 | F77: www.alexmercieca.com
A78: bath | B78: Faenza | C78: faenzabathroomsmalta@gmail.com | D78: 79 218 080 | E78: 7 Triq I-Erba' Qaddisin | F78: www.faenzabathrooms.com
A79: bath | B79: A F Ellis Ltd | C79: mail@afellis.com.tm | D79: 21 556 021 | E79: Triq il-Taflija Qasam Industrijali, Xewkija-Gozo, Gozo XWK 3000 | F79: www.afellis.com.mt
A80: bath | B80: Absolute bathrooms | C80: info@absolute.com.mt | D80: +356 2141 7596 | E80: Triq Pantar, Hal Lija | F80: www.absolute.com.mt
A81: bath | B81: Avante Bathrooms | C81: meli@avantebathrooms.com | D81: 21 472 095 | E81: 181 Triq Salvu Psaila, B'Kara, Malta BKR 9076 | F81: www.facebook.com/avantebathrooms/
A82: bath | B82: Banju Boutique Ltd | C82: info@banjuboutique.com | D82: 20 117 900 | E82: Triq I-Arkata, Paola, Malta PLA 1212 | F82: www.banjuboutique.com
... A95: bath | B95: Farell Bathrooms | C95: info@farellbathrooms.com | D95: 21 642 396 | E95: 115 Vjal iI-Blue Grotto, Zurrieq, Malta ZRQ 4015 | F95: www.farellbathrooms.com
A96: bath | B96: Hauz | C96: info@hauz.mt | D96: 79633615 | E96: 123 Triq Dun Karm Sant, Tarxien, Malta | F96: www.hauz.mt
A97: bath | B97: Iperceramica | C97: info@bayker.it | D97: 27 133 090 | E97: Triq iI-Wied ta' I-Imsida, Msida, Malta | F97: www.iperceramica.it
A98: bath | B98: Josies Bathroom Centre | C98: josies@josies.com.mt | D98: 21 410 685 | E98: Triq in-Naxxar, Lija, Malta | F98: www.facebook.com/Josies-Bathroom-Centre
A99: bath | B99: Keramit Bathroom Centre | C99: jovanpisani@keramitbathrooms.com | D99: 21 434 935 | E99: Naxxar, Malta NXR 6345 | F99: www.facebook.com/keramitbathrooms/
A100: bath | B100: M & S Bathroom Centre | C100: bugejamalcolm@gmail.com | D100: 21 573 499 | E100: 137 Triq Parades, San Pawl II-Bahar, Malta SPB 3430 | F100: ___
A101: bath | B101: Magri Bathroom Centre | C101: info@magribathrooms.com | D101: 21 486 883 | E101: Triq iI-Kanun, Qormi, Malta QRM 9039 | F101: www.magribathrooms.com
A102: bath | B102: Moda Bagno | C102: modabagnor@gmail.com | D102: 21 446 751 | E102: Zone 3 Triq I-Intornjatur, Zona Industrjali, Mriehel, B'Kara, Malta BKR 3000 | F102: www.facebook.com/ModaBagnoMalta
A103: bath | B103: Nuova Bagno | C103: michaelnuovobagno@gmail.com | D103: 21 802 845 | E103: M'Skala By Pass, Zabbar, Malta ZBR 9042 | F103: www.facebook.com/Nuovo-Bagno
A104: bath | B104: Property Services Ltd | C104: adrian@esclmalta.com | D104: 99 423 740 | E104: Triq San Bartolomew, Qormi, Malta | F104: www.propertyservicesltd.com
A105: bath | B105: S & S Bathrooms Ltd | C105: info@ssbathrooms.com | D105: 21 412 222 | E105: Triq il-Mosta, Lija, Malta LJA 9012 | F105: www.ssbathrooms.com
A106: bath | B106: Sogno Bagno Bathroom Centre | C106: jg375@maltanet.net | D106: 21 451 032 | E106: 120 Triq il-Kullegg, Rabat, Malta RBT 1408 | F106: www.facebook.com/SognoBagno/
A107: bath | B107: The Tub | C107: sales@thetubmalta.com | D107: 79522966 | E107: Misrah il-Barrieri, Sta Venera, Malta | F107: www.thetubmalta.com
A108: bath | B108: Vella Falzon Home | C108: info@vellafalzon.com | D108: 21 445 165 | E108: Triq il-Wied ta'Imsida, Msida, Malta MSD 9022 | F108: www.vellafalzon.com
A109: bath | B109: Vellmann Ltd | C109: info@vellmann.com | D109: 21 424 990 | E109: Pantar Estate Triq Pantar | F109: www.facebook.com/Vellmann/
A110: bath | B110: VIVO Bathrooms & Ceramics Ltd | C110: info@vivo.com.mt | D110: 20 932 932 | E110: 9 Triq Geronimo Abos, Iklin, Malta IKL 1022 | F110: www.vivo.com.mt
A112: toilet | B112: Deluxe Bathrooms | C112: deluxebathroomsmanagement@gmail.com | D112: 21 560 388; 79 902 613; 99 307 711 | E112: Triq Benghazi, Ghajnsielem-Gozo, GSM 1624 | F112: www.deluxe-bathrooms.com
A113: toilet | B113: E Grech Cristal Bath Ltd | C113: info@egrechcristalbath.com | D113: 21 483 216 | E113: Triq Salvu Psaila, B'Kara, Matla BKR 9076 | F113: www.egrechcristalbath.com
A114: toilet | B114: Alex Mercieca Bathroom Centre Limited | C114: info@alexmercieca.com | D114: +365 2169 5438; +356 2167 2049; +365 7940 2553 | E114: 25th November Avenue, Zejtun, ZTN2019 | F114: www.alexmercieca.com
A115: toilet | B115: A F Ellis Ltd | C115: mail@afellis.com.tm | D115: 21 556 021 | E115: Triq il-Taflija Qasam Industrijali, Xewkija-Gozo, Gozo XWK 3000 | F115: www.afellis.com.mt
A116: toilet | B116: Avante Bathrooms | C116: meli@avantebathrooms.com | D116: 21 472 095 | E116: 181 Triq Salvu Psaila, B'Kara, Malta BKR 9076 | F116: www.facebook.com/avantebathrooms/
A117: toilet | B117: Banju Boutique Ltd | C117: info@banjuboutique.com | D117: 20 117 900 | E117: Triq I-Arkata, Paola, Malta PLA 1212 | F117: www.banjuboutique.com
A118: toilet | B118: Bathroom Design Ltd | C118: info@bathroomdesign.com.mt | D118: 21 441 328 | E118: 358 Triq in-Naxxar, B'Kara, Malta BKR 9040 | F118: www.bathroomdesign.com.mt
A119: toilet | B119: BC Bathrooms | C119: bc.bathrooms@gmail.com | D119: 27 495 590 | E119: Triq Dun Karm B'Kara By Pass, B'Kara, Malta BKR 2940 | F119: www.bc-bathrooms.com
A120: toilet | B120: C Grech Marbles Ltd | C120: cgrarbles@gmail.com | D120: 21 420 538 | E120: 11 Triq I-Imdina, Attard, Malta ATD 9036 | F120: www.cgremarbles.com.mt
... A144: shower | B144: BridgePoint | C144: sales@bridgepoint.com.mt | D144: 2792 2222 | E144: 3, Triq Ferdinandu Inglott, Ħ'Attard | F144: https://www.bridgepointmalta.com/
A145: Accessories | B145: MRCD | C145: info@mrcd.com.mt | D145: 21468770 | E145: MRCD Building, Karmenu Camilleri Street, Qormi, QRM4631 | F145: https://www.mrcd.com.mt/en/home.htm
B147: BMS

Sheet Jacuzzi
A1: item | B1: supplier | C1: email | D1: phone number | E1: location | F1: website
A2: Spa | B2: Deluxe Bathrooms | C2: deluxebathroomsmanagement@gmail.com | D2: 21 560 388; 79 902 613; 99 307 711 | E2: Triq Benghazi, Ghajnsielem-Gozo, GSM 1624 | F2: www.deluxe-bathrooms.com
A3: Spa | B3: Newline Living Concepts | C3: newlineliving@gmail.com | D3: 21 563 966 | E3: Triq Papa Gwanni Pawlu II, Victoria-Gozo, Gozo VCT 9046 | F3: www.newline.com.mt
A4: Spa | B4: Pitre' Bathrooms | C4: info@jpitre.com | D4: 21463335 | E4: Mdina Road, Qormi, QRM 9011, Malta | F4: www.pitrebathrooms.com
A5: Spa | B5: Banju Boutique | C5: info@banjuboutique.com | D5: 2011 7900 | E5: Paola Outlet Arcade Street, Paola PLA1212 | F5: www.banjuboutique.com
A6: Spa | B6: Bridgepoint Ltd | C6: sales@bridgepoint.com.mt | D6: 27 922 222 | E6: No 3, Triq Ferdinand Inglott, Attard ATD 3134 | F6: www.bridgepoint.com
A7: Spa | B7: Gozo Baths Ceramics | C7: gozobaths@gmail.com | D7: 9993 2230 | E7: Triq Dun Karm, Birkirkara, Malta | F7: https://www.facebook.com/p/Gozo-Baths-Ceramics-100063540523723/
A8: Spa | B8: Alex Mercieca Bathroom Centre Limited | C8: info@alexmercieca.com | D8: +365 2169 5438; +356 2167 2049; +365 7940 2553 | E8: 25th November Avenue, Zejtun, ZTN2019 | F8: www.alexmercieca.com
A9: Spa | B9: Faenza | C9: faenzabathroomsmalta@gmail.com | D9: 79 218 080 | E9: 7 Triq I-Erba' Qaddisin | F9: www.faenzabathrooms.com
A10: Spa | B10: A F Ellis Ltd | C10: mail@afellis.com.tm | D10: 21 556 021 | E10: Triq il-Taflija Qasam Industrijali, Xewkija-Gozo, Gozo XWK 3000 | F10: www.afellis.com.mt
A11: Spa | B11: Vella Falzon | C11: info@vellafalzon.com | D11: 2144 5165 | E11: 13, Triq il-Furnar Qormi QRM 3504, Malta | F11: www.wvellafalzon.com
A12: Spa | B12: Vellmann | C12: info@vellmann.com | D12: 21424990 | E12: Pantar Road Hal Lija LJA, 2023 | F12: www.vellmann.com
A13: Spa | B13: Magri Bathrooms | C13: info@magribathrooms.com | D13: 2148 6883 ; 9949 8840 | E13: Triq il-Kanun, al Qormi, Malta | F13: www.magribathrooms.com
A14: Spa | B14: Falzon's Bathroom | C14: info@falzons.com | D14: 2148 2860; 2148 5536; 2149 5485 | E14: Falzon's Bathroom & Ceramics, Triq il-Kummerc, Qormi, Malta | F14: www.falzons.com
A15: Spa | B15: Malta DIY | C15: sales@maltadiy.com | D15: 20341569 | E15: 160, Mdina Road, Zebbug ZBG9015 | F15: www.maltadiy.com
A16: Spa | B16: The Tile | C16: info@the-tile.com | D16: 21 371 891 | E16: Triq Bella Vista, San Gwann, Malta SGN 2690 | F16: www.the-tile.com
A17: Spa | B17: Bathroom Design | C17: info@bathroomdesign.com.mt | D17: 21 441 328 | E17: 356 Naxxar Road, B'Kara, BKR 9040, Malta | F17: www.bathroomdesign.com.mt
A18: Spa | B18: The Tub | C18: sales@thetubmalta.com | D18: 21448499 ; 79522969 | E18: 313A, Triq il-Barrieri, St Venera | F18: www.thetub.com
A19: Spa | B19: Carini Stores Ltd. | C19: sales@carinibathrooms.com | D19: 21 449 641; 21 440 202 | E19: 435 St. Joseph High Road, St. Venera, Malta | F19: www.carinibathrooms.com
A20: Spa | B20: Waterart Concepts | C20: info@waterartconcepts.com | D20: 2278 2000 | E20: Mill Street, Qormi QRM 3102, Malta | F20: www.waterartconcepts.com
A21: Spa | B21: BC Bathrooms | C21: bc.bathrooms@gmail.com | D21: 2749 5590 | E21: Triq Dun Karm, B'Kara Bypass, Birkirkara BKR 2940 | F21: www.bc-bathrooms.com
A22: Spa | B22: B&M | C22: info@bmsupplies.com | D22: 2144 0710 | E22: Triq Dun Karm, Kirkirkara, BKR 9035 | F22: www.bmsupplies.com
A23: Spa | B23: Vellmann Ltd | C23: info@vellmann.com | D23: 21 424 990 | E23: Pantar Estate Triq Pantar | F23: www.facebook.com/Vellmann/
B24: Dolphin Pools | C24: info@dolphinpools.com.mt
B25: Home Decor | C25: mail@afellis.com.mt
B26: Chris Imgarr Pools | C26: pools@muscatpools.com
B27: RC Pool Services | C27: rodneycolombo@gmail.com
B28: Splash Store | C28: info@splashstoremalta.com
B29: Crystal Pools | C29: info@crystalpools.com.mt
B30: Faenza | C30: faenzabathroomsmalta@gmail.com
B31: HomeTrends | C31: shop@hometrends.com.mt
B32: Casafini | C32: sales@casafini.com.mt
B33: BigMat | C33: info@bigmatmalta.com
B34: Malta Hot Tub Store
B35: The Great Outdoors Malta | C35: info@thegreatoutdoorsmalta.com

Sheet Bedroom
A1: Bedroom
A2: item | B2: supplier | C2: email | D2: phone number | E2: location | F2: website
A3: bed | B3: EuroIm JSM | C3: sales@euroimjsm.com | D3: 21415553 | E3: 2, Industrial Estate Mdina Road Attard, ATD3000 | F3: https://www.euroimjsm.com/
A4: bed | B4: style interni | C4: info@styleinterni.com | D4: 2149 6473 | E4: 260 Old Railway Track, Santa Venera SVR 9019 | F4: https://styleinterni.com/
A5: bed | B5: Homistic Homes | C5: homistic@yahoo.com | D5: 7904 9970 | E5: 22/23 Triq hal mula Haz-zebbug ZBG | F5: https://www.homisticrooms.com/
A6: bed | B6: Foam & Leather Bedding & Home | C6: foam.leather@gmail.com | D6: 21 232 159 ; 27232159 | E6: 836, 838 Triq il-Kbira San Guzepp, Hamrun, Malta HMR 1018 | F6: www.foamandleather.com
A7: bed | B7: C B R | C7: cbrltd1@go.net.mt | D7: 21 661 317 | E7: Triq Hal Tarxien, Luqa, Malta LQA 1814 | F7: www.cbrltd.com
A8: bed | B8: Furniture & Hardware Gozo Ltd | C8: lawrenceagalea@yahoo.com | D8: 21 551 500 | E8: City Pearl Shopping Arcades Triq Fortunato Mizzi, Victoria-Gozo, Gozo VCT 2571 | F8: _____
A9: bed | B9: Hastens | C9: marketing@form.com.mt | D9: 21 445 607 | E9: Triq il-Wied ta' I-Imsida, Msida, Malta MSD 9023 | F9: www.facebook.com/4mHome
A10: bed | B10: PoweHouse | C10: sales@powerhousemalta.eu | D10: 2742 4632 | E10: 13 Censu Bugeja, L-Iklin BZN 1170 | F10: www.powerhousemalta.eu
A11: bed | B11: KREA | C11: info@krea.com.mt | D11: 21 463 501 | E11: Triq I-Imdina, Qormi, Malta QRM 9011 | F11: www.krea.com.mt
A12: bed | B12: JYSK | C12: jysk@jysk.com.mt | D12: 27 137 364 | E12: Triq il-Mosta, Lija, Malta LIJA 9012 | F12: www.jysk.com.mt
A13: bed | B13: Dino Fino Home & Contract | C13: info@dinofino.com | D13: 21 240 100 | E13: Triq il-Wied Ta' L-Imsida, B'Kara, Malta BKR 9025 | F13: www.dinofino.com
A14: bed | B14: Mattres Collection | C14: help@mattresscollection.com.mt | D14: 21 461 961 | E14: Mdina Road Zebbug, Malta | F14: www.mattresscollection.com.mt
A15: bed | B15: Royalty Bedding | C15: info@royaltybedding.com | D15: 21 449 253 | E15: Zone 5, Central Business District Triq il-Kummerc Qormi, CBD 5050 | F15: www.royaltybedding.com
... A17: bed | B17: Dreams Malta | C17: info@dreamsmalta.com | D17: 7977 1054 | E17: GB Building Triq il-Watar, Ta' Xbiex XBX1301 Malta | F17: www.dreamsmalta.com
A18: bed | B18: Morfeus Malta | C18: estevan@morfeus.com.mt | D18: 27995234 | E18: Triq San Pawl tal-Qliegha, MST9096 Mosta, Malta | F18: www.morfeus.com.mt
A19: bed | B19: Oxford House | C19: info@oxfordhouse.com.mt | D19: 25464000 | E19: Triq L-mdina, Zone 2, Central Business District, Birkirkara CBD 2010, Malta | F19: www.oxfordhouse.com.mt
A20: bed | B20: OK Home | C20: info@okhome.com.mt | D20: 2143 4747 | E20: Pantar Road, Lija, Malta | F20: www.okhome.com.mt
A21: bed | B21: The Atrium | C21: contactus@theatrium.com.mt | D21: 2549 5000 | E21: Giovanni Felice Street, Zone 3, Central Business District, Birkirkara CBD 3120 | F21: www.theatrium.com.mt
A22: bed | B22: C. Fino & Sons Ltd | C22: info@fino.com.mt | D22: 2549 3000 | E22: Triq I-Imdina, Zone 4, Mriehel/Central Business District CBD 4010, Malta | F22: www.fino.com.mt
A23: bed | B23: Homemate | C23: mosta@homemate.com.mt | D23: 2326 2700 | E23: Vjal 25 ta' Novembru, Tal-Barrani, Zejtun | F23: www.homemate.com.mt
A24: bed | B24: Vitafoam | C24: info@vitafoammalta.com | D24: 2148 4992 | E24: Galeas, San Gwann | F24: www.vitafoammalta.com
A25: bed | B25: Sylvia Bazaar | C25: sales@sylviabazaar.com | D25: 21 666 488 | E25: Triq A Caligari Zabbar Malta ZBR 2806 | F25: www.sylviabazaar.com
A26: bed | B26: Omajco Bedding | C26: sales@omajco.net | D26: 2164 2343 | E26: San Gwann Nexxar Road | F26: www.omajcobedding.com
A27: bed | B27: Boris Arcidicano | C27: ______ | D27: 2133 3638 ; 2133 3639 | E27: 233 Tower Road, Sliema SLM 1601 | F27: www.borisarcidiacono.com
A28: bed | B28: Wellbeing Bedding Ltd | C28: help@wellbeingbedding.com | D28: 2131 6678 | E28: 5/6 Msida Valley Road Birkirkara BKR 9022 Malta | F28: www.wellbeingbedding.com
A29: bed | B29: Channel Trade Marketing | C29: info@ctmliving.com | D29: 21417967 ; 79300135 | E29: 5/7 Triq Censu Bugeja, L-Iklin | F29: www.ctmliving.com
A30: bed | B30: Perer Camilleri & Sons | C30: info@pcs.com.mt | D30: 2122 0258 ; 2123 4453 | E30: 31, Cross Road, Marsa MRS 1548, Malta | F30: www.pcs.com.mt
A31: bed | B31: Malta Design | C31: sales@malta-design.com | D31: 77105385 | E31: Malta Design 33 Triq l-Oleandru , San Giljan, Malta | F31: https://www.malta-design.com
A32: bed | B32: ProMan Interiors | C32: info@promaninteriors.com | D32: 2131 0334 | E32: Proman Interiors, 115, Valley Road, B'Kara. BKR 9022. Malta. | F32: https://www.promaninteriors.com/
A33: bed | B33: DARI | C33: info@dari.mt | D33: 21 890 459
A34: bed | B34: FairDeal Furniture | C34: info@fairdealfurniture.com.mt
A35: bed | B35: Homes by BDI | C35: info@bdi.com.mt
A36: bed | B36: Bo Concept | C36: info@boconcept.com.mt
A38: closet | B38: Brands International Ltd | C38: info@brands.com.mt | D38: 20 959 595 | E38: Triq tal-Balal, San Gwann, Malta SGN 9016 | F38: www.brands.com.mt
A39: closet | B39: R Living | C39: stephen@rliving.com.mt | D39: 21 499 699 | E39: Dawert I-Imriehel, Qormi, Malta QRM 9052 | F39: www.rliving.com.mt
A40: closet | B40: Kubek | C40: info@kubekgroup.com | D40: 21 658 358 | E40: HF 5A Qasam Industrijali, Hal Far, B'Bugia, Malta BBG 3000 | F40: www.kubekgroup.com
A41: closet | B41: Abela Norbert Joiners | C41: abelanorbertjoiners@gmail.com | D41: 21 523 853 | E41: 59 Triq in-Nahal, Mellieha, Malta MLH 2166 | F41: https://www.facebook.com/people/Abela-Norbert-Joiners/100057636902110/
A42: closet | B42: Bed And Sofa | C42: info@antoniocaruso.it | D42: 77 773 085 | E42: 119 Triq il-Kappillan Mifsud, Sta Venera, Malta | F42: https://www.facebook.com/photo/?fbid=518605750070651&set=a.518605710070655
A43: closet | B43: Bed&Sofa | C43: bedandsofamalta@gmail.com | D43: 77755520 | E43: 57 Naxxar road, San Gwann sgn 9032, Malta | F43: https://bedsofa.mypos.site/en
A44: closet | B44: Casafini | C44: sales@casafini.com.mt | D44: 2766 6622 | E44: 146, Balzan Valley, Hal Balzan, Malta | F44: https://www.instagram.com/casafini_malta/?hl=en
A45: closet | B45: Cascone Home | C45: info@casconehome.com | D45: 27 555 525 | E45: Triq il-Wied Ta' L-Imsida, B'Kara, Malta BKR 9022 | F45: www.casconehome.com
A46: closet | B46: Cieffe Joinery | C46: cieffejoinery@fsh.com.mt | D46: 21 658 152 | E46: Triq Hal Far, B'Budia, Malta | F46: www.cieffeprojects.com.mt
A47: closet | B47: Construct Furniture Co Ltd | C47: info@constructfurniture.com.mt | D47: 21 220 610 | E47: 40 Qasam Industrijali, Luqa, Malta LQA 3000 | F47: www.constructfurniture.com.mt
A48: closet | B48: Domal | C48: sales@domal.mt | D48: 21 482 662 | E48: 192 Triq in-Naxxar, B'Kara, Malta BKR 9044 | F48: www.domal.com.mt
A49: closet | B49: Eric Kuster | C49: rachel@erickuster.com | D49: 20 106 917 | E49: Triq Wied Ghomor, San Giljan, Malta STJ 2040 | F49: www.erickuster.com
A50: closet | B50: Estea | C50: gaspare@esteamt.com | D50: 21 449 499 | E50: Monpalau Building Triq it-Torri, Msida, Malta | F50: www.esteamt.com
A51: closet | B51: Fillmore Furniture | C51: agius65@hotmail.com | D51: 21 249 763 | E51: 69 Triq Hal Qormi, Hamrun, Malta HMR 2183 | F51: _____
A52: closet | B52: Gozoarts Furnishings Ltd | C52: info@gozoarts.com.mt | D52: 21 563 364 | E52: Triq Gorg Borg Olivier, Vicotria-Gozo, Gozo VCT 2515 | F52: www.gozoarts.com.mt
A53: closet | B53: Form Ltd | C53: info@formltd.com | D53: 21 446 000 | E53: Triq il-Wied ta'lmsida, Msida, Malta MSD 9023 | F53: www.form.com.mt
A54: closet | B54: Immaginecasa Ltd | C54: info@immaginecasamalta.com | D54: 21 443 539 | E54: Triq il-Wied Ta' L'lmsida, B'Kara, Malta BKR 3000 | F54: www.imaginecasamalta.com
A55: closet | B55: JDS Furniture | C55: info@jdsfurniture.com | D55: 21 522 390 | E55: Triq il-Kbira, Mellieha, Malta MLH 2317 | F55: www.jdsfurniture.com
... A59: closet | B59: onepercent | C59: info@onepercent.com.mt | D59: 25 465 000 | E59: Triq il-Wied ta' I-Imsida, Msida, Malta MSD 9022 | F59: www.onepercent.com.mt
A60: closet | B60: Real Woodworks | C60: realwoodworks1@gmail.com | D60: 99892178 | E60: Binja San Guzepp Haddiem Triq Indri Psaila, Qormi Malta | F60: https://www.facebook.com/people/Real-woodworks/100057415459586/
A61: closet | B61: Rustica Home | C61: info@rusticahome.com.mt | D61: 21 238 520 | E61: 32 II-Moll tal-Hatab, Marsa, Malta MRS 1440 | F61: www.rusticahome.com.mt
A62: closet | B62: ProMan Interiors | C62: info@promaninteriors.com | D62: 2131 0334 | E62: Proman Interiors, 115, Valley Road, B'Kara. BKR 9022. Malta. | F62: https://www.promaninteriors.com/
A64: nightstand | B64: PoweHouse | C64: sales@powerhousemalta.eu | D64: 2742 4632 | E64: 13 Censu Bugeja, L-Iklin BZN 1170 | F64: www.powerhousemalta.eu
A65: nightstand | B65: The Atrium | C65: contactus@theatrium.com.mt | D65: 2549 5000 | E65: Giovanni Felice Street, Zone 3, Central Business District, Birkirkara CBD 3120 | F65: www.theatrium.com.mt
A66: nightstand | B66: Homemate | C66: mosta@homemate.com.mt | D66: 2326 2700 | E66: Vjal 25 ta' Novembru, Tal-Barrani, Zejtun | F66: www.homemate.com.mt
A67: nightstand | B67: JYSK | C67: jysk@jysk.com.mt | D67: 27 137 364 | E67: Triq il-Mosta, Lija, Malta LIJA 9012 | F67: www.jysk.com.mt
A68: nightstand | B68: OK Home | C68: info@okhome.com.mt | D68: 2143 4747 | E68: Pantar Road, Lija, Malta | F68: www.okhome.com.mt
A69: nightstand | B69: Karrari | C69: sales@karrari.shop | D69: 2799 5000 ; 9999 6755 | E69: 77 Commerce St, Birkirkara, CBD3010 | F69: www.karrari.shop
A70: nightstand | B70: C. Fino & Sons Ltd | C70: info@fino.com.mt | D70: 2549 3000 | E70: Triq I-Imdina, Zone 4, Mriehel/Central Business District CBD 4010, Malta | F70: www.fino.com.mt
A71: nightstand | B71: Orienta | C71: ______ | D71: 2144 5733 | E71: Triq L-Imdina, Zone 2, Central Business District, Birkirkara | F71: www.orienta.mt
A72: nightstand | B72: Newline Living Concept | C72: newlineliving@gmail.com | D72: 21 563 966 | E72: Triq Papa Gwanni Pawlu ll, Victoria-Gozo, Gozo VCT 9046 | F72: www.newline.com.mt
A73: nightstand | B73: Luxonas | C73: info@luxonas.com | D73: 21451718 ; 79288688 | E73: Triq L-Mdina, Haz-Zebbug, ZBG09018 | F73: www.luxonas.com
... A91: dresser | B91: Farrugia Group | C91: info@farrugiagroup.com | D91: 99 408 444 | E91: 61 St Liberata Triq Santa Liberata, Kalkara, Malta KKR 1612 | F91: www.fg.com.mt
A92: dresser | B92: Ferraracasa | C92: info@ferraramalta.com | D92: 21483614 | E92: Triq il-Wied, B'Kara, Malta | F92: www.ferraracasa.com.mt
A93: dresser | B93: Flamant Malta | C93: sales@flamant.com.mt | D93: 23 957 630 | E93: Pjazza Tigne' Tigne' Point, Slimea, Malta
A94: dresser | B94: Gozoarts Furnishings Ltd | C94: info@gozoarts.com.mt | D94: 21 563 364 | E94: Triq Gorg Borg Olivier, Victoria-Gozo, Gozo VCT 2515 | F94: www.gozoarts.com.mt
A95: dresser | B95: Granny Smith Dine Furniture & Home Interiors | C95: info@grannysmithshop.com | D95: 21 418 984 | E95: Triq San Pawl, Naxxar, Malta NXR 4016 | F95: www.facebook.com/grannysmithfurnitureandinteriors
A96: dresser | B96: J C R Furniture | C96: info@jcrfurniture.com | D96: 21 230 933 | E96: Triq il-Labour, Marsa, Malta MRS 9030 | F96: www.jcrfurniture.com
A97: dresser | B97: James Agius Woodworks Ltd | C97: info@jagiuswoodworks.com | D97: 79 369 176 | E97: 28 Qasam Industrijali, Luqa, Malta LQA 3000 | F97: www.jagiuswoodworks.com
A98: dresser | B98: JDS Furniture | C98: info@jdsfurniture.com | D98: 21 522 390 | E98: Triq il-Kbita, Mellieha, Malta | F98: www.jdsfurniture.com
A99: dresser | B99: JYSK | C99: jysk@jysk.com.mt | D99: 27 137 364 | E99: Triq il-Mosta, Lija, Malta LIJA 9012 | F99: www.jysk.com.mt
A100: dresser | B100: JTS Trading | C100: jurgen@jtstrading.com | D100: 99 446 951 | E100: Zone 5 Triq ll-Kummerc Central Business District, Qormi, Malta | F100: www.jtstrading.com
A101: dresser | B101: Muccio Mobili | C101: info@mucciomobili.it | D101: 99 643 810 | E101: 154 Triq il-Kappillan Mifsud, Sta Venera, Malta | F101: www.mucciomobili.it
A102: dresser | B102: Rags And Riches Buy & Sell | C102: ragsandrichesbuyandsell@gmail.com | D102: 79 593 666 | E102: Flat 9, Harmony Court Triq tal-Gardiel, M'Skala, Malta MSK 3807 | F102: https://www.facebook.com/p/Rags-and-Riches-Buy-and-Sell-100041339592117/
A103: dresser | B103: Richard Furniture | C103: seguna@onvol.net | D103: 21 224 103 | E103: 91 Triq il-Kbira San Guzepp, Hamrun, Malta HMR 1017 | F103: www.lepseg.wix.com/richard-furniture
A104: dresser | B104: Rondor | C104: ronaldmarmara@gmail.com | D104: 99 425 609 | E104: 210 Triq il-Ferrovija, Sta Venera, Malta SVR 9019 | F104: _____
A105: dresser | B105: Spaces | C105: info@spaces.com.mt | D105: 21 230 982 | E105: Triq il-Wied, B'Kara, Malta BKR 9021 | F105: www.spaces.com.mt
... A123: mattress | B123: Omajco Bedding | C123: sales@omajco.net | D123: 21 642 343 | E123: San Gwann | F123: www.omajcobedding.com
A124: mattress | B124: Oxford House | C124: info@oxfordhouse.com.mt

Sheet Kitchen
A1: g
A2: item | B2: supplier | C2: email | D2: phone number | E2: location | F2: website
A3: Kitchen counter | B3: Ferraracasa | C3: info@ferraramalta.com | D3: 21483614 | E3: Ferraracasa Warehouse Triq is-Salib ta l-Mriehel CBD3020 Birkirkara Malta | F3: https://www.ferraramalta.com/
A4: Kitchen counter | B4: style interni | C4: info@styleinterni.com | D4: 2149 6473 | E4: 260 Old Railway Track, Santa Venera SVR 9019 | F4: https://styleinterni.com/
A5: Kitchen counter | B5: Sghendo Woodworks | C5: info@sghendowoodworks.com | D5: 99 229 600; 99 406 580 | E5: Triq Mastru Gorg Cachia Tal-Handaq, Qormi, Malta WRM 4000 | F5: www.sghendo.com | H5: https://dari.mt/
A6: Kitchen counter | B6: Desana Marbles | C6: info@desanamarbles.com | D6: 21 451 350 | E6: Triq il-Buskett, Dingli, Malta DGL 2709 | F6: www.desanamarbles.com
A7: Kitchen counter | B7: Fairdeal Furniture | C7: info@fairdealfurniture.com.mt | D7: 27 282 828 | E7: Triq I-Imdina, Zebbug, Malta ZBG 4351 | F7: www.fairdealfurniture.com.mt
A8: Kitchen counter | B8: Art At Home | C8: artathomeltd@gmail.com | D8: 21 417 402 | E8: Triq I-Imdina, Attard, Malta ATD 9037 | F8: www.artathomemalta.com
A9: Kitchen counter | B9: Low Cost Furniture by Fairdeal | C9: arnold@lowcostfurniture.com.mt | D9: 27 227 771; 77 729 292 | E9: Triq I-Imdina, Zebbug, Malta | F9: www.lowcostfurniture.com.mt
A10: Kitchen counter | B10: FV Carpentry | C10: fran@fvcarpentry.com | D10: 79 041 733 | E10: 42 Triq ix-Xwieni Albert Town, Marsa, Malta | F10: www.fvcarpentry.com
A11: Kitchen counter | B11: Top Drawer Ltd | C11: topdrawer@topdrawermalta.com | D11: 21 410 903 | E11: Triq il-Kappar, Mosta, Malta MST 4003 | F11: https://www.facebook.com/people/Top-Drawer-Ltd/100057222588942/
A12: Kitchen counter | B12: Brands International Ltd | C12: info@brands.com.mt | D12: 20 959 595 | E12: Triq tal-Balal, San Gwann, Malta SGN 9016 | F12: www.brands.com.mt
A13: Kitchen counter | B13: Domestica Ltd | C13: igor@domestica.com.mt | D13: 77 447 610; 21 447 604 | E13: Triq il-Wied ta' I-Imsida, Msida, Malta MSD 9091 | F13: www.domestica.com.mt
A14: Kitchen counter | B14: Core | C14: info@core.com.mt | D14: 21 443 449 | E14: Triq Mannarino, B'Kara, Malta BKR 9085 | F14: www.core.com.mt
A15: Kitchen counter | B15: Dino Fino Home & Contract | C15: info@dinofino.com | D15: 21 240 100 | E15: Triq il-Wied Ta' L-Imsida, B'Kara, Malta BKR 9025 | F15: www.dinofino.com
A16: Kitchen counter | B16: Distinct Homes | C16: info@distincthomes.com.mt | D16: 21 551 234 | E16: Triq Papa Gwanni Pawlu ll, Victoria-Gozo, Gozo VCT 9046 | F16: www.distincthomes.com.mt
A17: Kitchen counter | B17: Grixti Mobili Ltd | C17: sales@grixtimobili.com | D17: 21 486 511 | E17: 1 Triq il-Kanun, Qormi, Malta QRM 9036 | F17: www.grixtimobili.com
... A25: Kitchen counter | B25: Oxford House | C25: info@oxfordhouse.com.mt | D25: 25 464 000 | E25: Triq L-Imdina, Zone 2, Central Business District, Birkirkara CBD 2010, Malta | F25: www.oxfordhouse.com.mt
A26: Kitchen counter | B26: Tree D (Jonathan Grech) | C26: info@treedfurniture.com | D26: 79445674 | F26: https://www.facebook.com/treedfurnituremalta?locale=nn_NO
A28: Kitchen cabinets | B28: Casaform Furniture | C28: casaform@onvol.net | D28: 21 447 266 | E28: T/G fi triq l-Imdina, Zebbug, Malta ZBG 5011 | F28: www.casaformfurniture.com
A29: Kitchen cabinets | B29: Ciantar Woodworks 3rd Generation Ltd | C29: jasoakwalnut@yahoo.com | D29: 21 672 432 | E29: Triq l-Isqof Buhagiar, Paola, Malta PLA 1111 | F29: www.ciantarwoodworks.com
A30: Kitchen cabinets | B30: Daniel Woodworks | C30: jasoakwalnut@yahoo.com | D30: 21 667 106 | E30: 86 Triq Vallettaa, Luqa, Malta LQA 1762 | F30: www.danielwoodworksmalta.com
A31: Kitchen cabinets | B31: JYSK | C31: jysk@jysk.com.mt | D31: 27 137 364 | E31: Triq il-Mosta, Lija, Malta LIJA 9012 | F31: www.jysk.com.mt
A32: Kitchen cabinets | B32: Richard Furniture | C32: seguna@onvol.net | D32: 21 224 103 | E32: 91 Triq il-Kbira San Guzepp, Hamrun, Malta HMR 1017 | F32: www.lepseg.wix.com/richard-furniture
A33: Kitchen cabinets | B33: Rustica Home | C33: info@rusticahome.com.mt | D33: 21 238 520 | E33: 32 ll-Moll tal-Hatab, Marsa, Malta MRS 1440 | F33: www.rusticahome.com.mt/site/
A34: Kitchen cabinets | B34: Spaces | C34: info@spaces.com.mt | D34: 21 230 982 | E34: Triq il-Wied, B'Kara, Malta BKR 9021 | F34: www.spaces.com.mt
A35: Kitchen cabinets | B35: R Living | C35: stephen@rliving.com.mt | D35: 21 499 699 | E35: Dawert I-Imriehel, Qormi, Malta QRM 9052 | F35: www.rliving.com.mt
A36: Kitchen cabinets | B36: Tree D (Jonathan Grech) | C36: info@treedfurniture.com | D36: 79445674 | F36: https://www.facebook.com/treedfurnituremalta?locale=nn_NO
A37: Kitchen cabinets | B37: ProMan Interiors | C37: info@promaninteriors.com | D37: 2131 0334 / 9943 1232 | E37: Proman Interiors, 115, Valley Road, B'Kara. BKR 9022. Malta | F37: https://www.promaninteriors.com/
A39: Kitchen islands | B39: Desana Marbles | C39: info@desanamarbles.com | D39: 21 451 350 | E39: Triq il-Buskett, Dingli, Malta DGL 2709 | F39: www.desanamarbles.com
A40: Kitchen islands | B40: Fairdeal Furniture | C40: info@fairdealfurniture.com.mt | D40: 27 282 828 | E40: Triq I-Imdina, Zebbug, Malta ZBG 4351 | F40: www.fairdealfurniture.com.mt
A41: Kitchen islands | B41: Brands International Ltd | C41: info@brands.com.mt | D41: 20 959 595 | E41: Triq tal-Balal, San Gwann, Malta SGN 9016 | F41: www.brands.com.mt
A42: Kitchen islands | B42: FV Carpentry | C42: fran@fvcarpentry.com | D42: 79 041 733 | E42: 42 Triq ix-Xwieni Albert Town, Marsa, Malta | F42: www.fvcarpentry.com
A43: Kitchen islands | B43: Top Drawer Ltd | C43: topdrawer@topdrawermalta.com | D43: 21 410 903 | E43: Triq il-Kappar, Mosta, Malta MST 4003 | F43: https://www.facebook.com/people/Top-Drawer-Ltd/100057222588942/
A44: Kitchen islands | B44: Domestica Ltd | C44: igor@domestica.com.mt | D44: 77 447 610; 21 447 604 | E44: Triq il-Wied ta' I-Imsida, Msida, Malta MSD 9091 | F44: www.domestica.com.mt
A45: Kitchen islands | B45: Dino Fino Home & Contract | C45: info@dinofino.com | D45: 21 240 100 | E45: Triq il-Wied Ta' L-Imsida, B'Kara, Malta BKR 9025 | F45: www.dinofino.com
A46: Kitchen islands | B46: Grixti Mobili Ltd | C46: sales@grixtimobili.com | D46: 21 486 511 | E46: 1 Triq il-Kanun, Qormi, Malta QRM 9036 | F46: www.grixtimobili.com
A47: Kitchen islands | B47: Kubek | C47: info@kubekgroup.com | D47: 21 658 358 | E47: HF 5A Qasam Industrijali, Hal Far, B'Bugia, Malta BBG 3000 | F47: www.kubekgroup.com
A48: Kitchen islands | B48: Petroni Ltd | C48: info@petroni.com.mt | D48: 21 447 763 | E48: Triq il-Wied ta' I-Imsida, Msida, Malta MSD 9022 | F48: www.petroni.com.mt
A49: Kitchen islands | B49: Tree D (Jonathan Grech) | C49: info@treedfurniture.com | D49: 79445674 | F49: https://www.facebook.com/treedfurnituremalta?locale=nn_NO
A51: Dining chair | B51: Renova Co Ltd | C51: info@renovamalta.com ; bjornzammit@gmail.com | D51: 21 448 174 | E51: Factory M 10, Zone 4 Triq ll-Furnara Central Business District | F51: www.renovamalta.com
A52: Dining chair | B52: Mercieca Chairs & Tables Hire | C52: mchire4@gmail.com | D52: 79 591 793 | E52: Casa Santa Rita Triq Santa Marta, Victoria-Gozo, Gozo VCT 2552 | F52: www.merciecaeventsuppliers.com
A53: Dining chair | B53: Silvio's Chairs | C53: silviochairs@gmail.com | D53: 99 454 333 | E53: 25 Triq il-Kataniz, Zebbug, Malta ZBG 2831 | F53: www.silvioschairs.com
A54: Dining chair | B54: Farrugia Group | C54: info@farrugiagroup.com | D54: 99 408 444 | E54: 61 St Liberata Triq Santa Liberata, Kalkara, Malta KKR 1612 | F54: www.fg.com.mt
A55: Dining chair | B55: M F Company Ltd | C55: office.mfcoltd@gmail.com | D55: 21 242 494 | E55: 184, 186 Triq Qormi, Marsa, Malta MRS 9044 | F55: www.facebook.com/mfcompanyltd
A56: Dining chair | B56: JYSK | C56: jysk@jysk.com.mt | D56: 27 137 364 | E56: Triq il-Mosta, Lija, Malta LIJA 9012 | F56: www.jysk.com.mt
A57: Dining chair | B57: Oxford House | C57: info@oxfordhouse.com.mt | D57: 25 464 000 | E57: Triq L-Imdina, Zone 2, Central Business District, Birkirkara CBD 2010, Malta | F57: www.oxfordhouse.com.mt
A58: Dining chair | B58: PoweHouse | C58: sales@powerhousemalta.eu | D58: 2742 4632 | E58: 13 Censu Bugeja, L-Iklin BZN 1170 | F58: www.powerhousemalta.eu
A59: Dining chair | B59: Dino Fino Home & Contract | C59: info@dinofino.com | D59: 21 240 100 | E59: Triq il-Wied Ta' L-Imsida, B'Kara, Malta BKR 9025 | F59: www.dinofino.com
A60: Dining chair | B60: Home by BDI | C60: info@bdi.com.mt | D60: 2149 1727; 2149 1722 | E60: 1, Triq Pietru Felici, Qormi, Malta | F60: www.homesbybdi.com
A61: Dining chair | B61: Maltashopper | C61: sales@maltashopper.com | D61: 20334532 | E61: 162 Cannon Road, Santa Venera, SVR 9034, Malta | F61: www.maltashopper.com
A62: Dining chair | B62: ABRA | C62: info@abra.com.mt | D62: 2141 7821; 7999 9330 | E62: ABRA, Triq L-Imdina ATTARD, ATD 9037 | F62: www.abra.com.mt
A63: Dining chair | B63: Fino | C63: info@fino.com.mt | D63: 2549 3000 | E63: Fino Buildings, Triq l-Imdina, Zone 4, Mriehel/Central Business District CBD 4010, Malta | F63: https://fino.com.mt/
A65: Kitchen storage | B65: Petrolea | C65: info@petroleamalta.com ; sales@petroleamalta.com | D65: 21 444 478 | E65: Triq I-Isof Labini, B'Kara, Malta BKR 1275 | F65: www.patroleamalta.com
A67: Dining table | B67: Fairdeal Furniture | C67: info@fairdealfurniture.com.mt | D67: 27 282 828 | E67: Triq I-Imdina, Zebbug, Malta ZBG 4351 | F67: www.fairdealfurniture.com.mt
A68: Dining table | B68: Newline Living Concept | C68: newlineliving@gmail.com | D68: 21 563 966 | E68: Triq Papa Gwanni Pawlu ll, Victoria-Gozo, Gozo VCT 9046 | F68: www.newline.com.mt
A69: Dining table | B69: Brands International Ltd | C69: info@brands.com.mt | D69: 20 959 595 | E69: Triq tal-Balal, San Gwann, Malta SGN 9016 | F69: www.brands.com.mt
A70: Dining table | B70: Top Drawer Ltd | C70: topdrawer@topdrawermalta.com | D70: 21 410 903 | E70: Triq il-Kappar, Mosta, Malta MST 4003 | F70: https://www.facebook.com/people/Top-Drawer-Ltd/100057222588942/
A71: Dining table | B71: BoConcept | C71: info@boconcept.com.mt | D71: 21 378 011; 20 959 595 | E71: Triq tal-Balal, San Gwann, Malta SGN 9016 | F71: www.boconcept.com/en-mt/
A72: Dining table | B72: Index Furniture | C72: info@indexmalta.com | D72: 21 806 878 | E72: Tip Top Bldgs Triq Haz-Zabbar | F72: www.indexmalta.com
A73: Dining table | B73: Malta Design | C73: sales@malta-design.com | D73: 77 105 385 | E73: 33 Triq l-Oleandru, San Giljan, Malta | F73: www.malta-design.com
A74: Dining table | B74: R Living | C74: stephen@rliving.com.mt | D74: 21 499 699 | E74: Dawert I-Imriehel, Qormi, Malta QRM 9052 | F74: www.rliving.com.mt
A75: Dining table | B75: Fava Woodworks Co Ltd | C75: fava@maltanet.net | D75: 99 835 390 | E75: KW 17b Qasam Industrijali, Kordin, Paola, Malta PLA 3000 | F75: www.facebook.com/woodworksfava/
... A100: Dining table | B100: Tornello Arredamenti | C100: info@tornelli.net | D100: 99 100 356 | E100: 197 Triq I-Imdina, Qormi, Malta QRM 9012 | F100: www.tornelloarredamenti.it
A101: Dining table | B101: Tree D (Jonathan Grech) | C101: info@treedfurniture.com | D101: 79445674 | F101: https://www.facebook.com/treedfurnituremalta?locale=nn_NO
A103: Fridge | B103: Ventura General Gas Ltd | C103: www.vanturamalta.com | D103: 21 677 798 / 21 225 608 / 21 240 938 | E103: BLB 021 Qasam Industrijali, Bulebel, Zejtun, Malta ZTN 3000 | F103: www.venturamalta.com
A104: Fridge | B104: Petroni Ltd | C104: info@petroni.com.mt | D104: 21 447 763 | E104: Triq il-Wied ta' I-Imsida, Msida, Malta MSD 9022 | F104: www.petroni.com.mt
A105: Fridge | B105: Soundsmart | C105: info@soundsmart.com.mt | D105: 21 430 569 / 79 454 867 | E105: Triq il-Kostituzzjoni, Mosta, Malta MST 9050 | F105: www.soundsmart.com.mt
A106: Fridge | B106: KCL Home Centre | C106: info@kcl.com.mt | D106: 21 493 285 | E106: 22, Triq Sant' Elija, B'Kara, Malta BKR 2064 | F106: www.kcl.com.mt
A107: Fridge | B107: Tablets & More | C107: tabletsandmoreelectronics@yahoo.com | D107: 27 366 601 | E107: 12 Triq il-Hammieri, Qormi, Malta | F107: www.tabletsandmoreelectronics.com
A108: Fridge | B108: Akkwist | C108: camrugun@hotmail.com | D108: 27 898 230 | E108: 18 Wesghat il-Knisja tan-Nattivita, Bormla, Malta BML 1650 | F108: www.facebook.com/akkwist
A109: Fridge | B109: Ta' Gulinu | C109: tagulinu@onvol.net | D109: 21 454 379 | E109: 10 Misrah I' Isle Adam, Rabat, Malta RBT 1169 | F109: https://www.facebook.com/TaGulinu/info?tab=page%5Cuinfo
A110: Fridge | B110: Triple A | C110: etv@etvhomeline.com | D110: 21 237 601 | E110: Triq San Tumas, Luqa, Malta LQA 9031 | F110: www.triplealuqa.com
A111: Fridge | B111: Right Deal Ltd | C111: rightdealcosp@onvol.net | D111: 21 800 638 | E111: Misrah Gavino Gulia, Bormla | F111: www.rightdealmalta.com
A112: Fridge | B112: Top Choice | C112: info@topchoice.com.mt | D112: 23 342 000 | E112: 280 Triq il-Kbira San Guzepp, Hamrun | F112: www.topchoice.com.mt
A113: Fridge | B113: Futura Home Appliances | C113: futurahomeappliances@gmail.com | D113: 21 377 181 | E113: 220 Triq in-Naxxar, San Gwann, Malta SGN 9030 | F113: https://www.facebook.com/futurahomeappliances/
A114: Fridge | B114: Centro Casalinga | C114: sales@jjscerri.com | D114: 21 250 980 | E114: Triq il-Kappillan Mifsud, Sta Venera | F114: www.centrocasalinga.com
... A193: Kitchen | B193: Joinwell | C193: info@joinwellfxb.com | D193: 2278 2000 | E193: JoinwellFXB, Triq il-Mithna, Central Business District, Qormi, CBD 5090 | F193: https://joinwell.com.mt/contact-us/
A194: Kitchen | B194: The Atrium | C194: contactus@theatrium.com.mt | D194: 2549 5000 | F194: https://www.theatrium.com.mt/contact-us
A195: Kitchen | B195: Form | C195: infodesk@form.com.mt | D195: 2144 6000 | E195: Triq Il-Wied Ta’ L-Imsida, L-Imsida | F195: https://form.com.mt/contact-us/
A196: Kitchen | B196: C. Fino & Sons | C196: info@fino.com.mt | D196: 2549 3000 | F196: https://fino.com.mt/
A197: Kitchen | B197: Scavolini | C197: info@scavolini.mt | D197: 2546 5000 | E197: Birkirkara by-pass, Birkirkara, Malta, BKR 9037 Links | F197: https://scavolini.mt/
A198: Kitchen | B198: Carmelo Delia | C198: info@carmelodelia.com | D198: 2147 2882 | E198: Valley Road, Birkirkara | F198: https://www.carmelodelia.com/contact

Sheet Wall Panels
A1: item | B1: supplier | C1: email | D1: phone number | E1: location | F1: website
A2: Wall Panels | B2: Nine Yards | C2: info@nineyards.com.mt | D2: 79421666 | E2: No.1, Triq Daniel Sammut, Lija, c/w Triq l-Gherusija, Balzan | F2: https://www.nineyards.com.mt/
A3: Wall Panels | B3: Mega Home | C3: info@megahome.mt | D3: 9997 5737 | E3: Triq Il-Vitorja, Ħal Qormi QRM 2504 | F3: https://megahome.mt/product/3d-wall-panels/
A4: Wall Panels | B4: BF Marbles | C4: info@bfmarbles.com | D4: 7724 4377 | E4: 40, Balzan Valley Road, Balzan BZN 1407 - Malta | F4: https://www.bfmarbles.com/#
A5: Wall Panels | B5: Quality Wall Panels | D5: 7903 0403 | F5: https://www.facebook.com/profile.php?id=61561349402968
A6: Wall Panels | B6: Vicali Interiors | C6: info@vicalinteriors.com | D6: 99499925 | E6: 84, Qormi Road, Hamrun | F6: https://www.vicalinteriors.com/
A7: 3D Wall Panels | B7: Malta DIY | C7: sales@maltadiy.com | D7: 20341569 | F7: https://maltadiy.com/product-category/floors-walls/walls/3d-wall-panels/?utm_source=chatgpt.com
A8: 3D Wall Panels | B8: Big Mat | C8: info@bigmatmalta.com | D8: 7950 8457 | E8: Industrial Zone, ATD 4000 Ta' Qali | F8: https://bigmatmalta.com/collections/wall-panels?utm_source=chatgpt.com
A9: 3D Wall Panels | B9: de Valier | C9: info@devalier.com.mt | D9: 21491111 | F9: https://www.dv.mt/showroom-category/3d-panels/
A10: 3D Wall Panels | B10: Gypsum Works Malta | C10: info@aptc.com.mt | D10: 7989 5238 | F10: https://www.gypsumworksmalta.com/store/c14/Panels
A11: Wall Panels | B11: Panels Hub Malta | C11: sales@panelshubmalta.com | D11: 7955 7968 | F11: https://panelshubmalta.com/flexible-panels/
A12: 3D Wall Panels | B12: AP Homes Malta | C12: info@aphomes.com.mt | D12: 7979 2083 | F12: http://www.aphomesmalta.com/store/c3/PVC_panels.html#/
A13: 3D Wall Panels | B13: Homemate | C13: customercare@homemate.com.mt | D13: 2326 2000 | F13: https://www.homemate.com.mt/product-category/feature-wall-planks
A14: 3D Wall Panels | B14: Evolve | C14: info@rsgroup.com.mt | D14: 2180 5486 | E14: Mdina Road, Zebbug, Malta, ZBG 9019 | F14: https://www.evolve.com.mt/products/wall-decor-malta/#3dwalls
A15: Corrugated Sheet | B15: MultiTrade | C15: sales@multitrademalta.com | D15: 21460195 | F15: https://www.multitrademalta.com/product-tag/corrugated-sheet/?utm_source=chatgpt.com
A16: Wall Panels | B16: KS Projects | C16: info@ksprojects.mt | D16: 7903 1199 | F16: https://www.facebook.com/profile.php?id=100091956755959
A17: Wall Panels | B17: The Atrium | C17: contactus@theatrium.com.mt | F17: https://www.theatrium.com.mt/search-site-results?nostock=0&search=panel

Sheet Office
A1: item | B1: supplier | C1: email | D1: phone number | E1: location | F1: website | G1: other | H1: Price
A2: Office Furniture | B2: Ramilene Office Supplies Ltd | C2: info@ramilenemalta.com | D2: 2133 4716 | E2: Ramilene Office Supplies Ltd 50/51 Ramilene Building Triq it-Torri, Swatar – B’Kara BKR 4011, Malta | F2: https://ramilenemalta.com/ | G2: sales@ramilenemalta.com
A3: Office Furniture | B3: de Valier | C3: info@devalier.com.mt | D3: 2149 1111 | E3: The Old Factory, San Gwakkin str, Mriehel,Central Business District Birkirkara CBD, 3030 | F3: www.dv.mt
A4: Office Furniture | B4: Malta Design | C4: sales@malta-design.com | D4: 77105385 | E4: Malta Design 33 Triq l-Oleandru , San Giljan, Malta | F4: www.malta-design.com
A5: Office Furniture | B5: Brands International | C5: info@brands.com.mt | D5: 2095 9595 | E5: Triq tal-Balal, San Gwann, Malta | F5: https://www.brands.com.mt/
A6: Office Furniture | B6: MaltaDIY | C6: sales@maltadiy.com | D6: 2034 1569 | E6: Baldacchino Building B, Triq Il-Belt Valletta, Zurrieq | F6: https://maltadiy.com/product-category/lights-and-tech/lights/
A7: Office Furniture | B7: Ferrara Casa | C7: info@ferraramalta.com | D7: 21483614 | E7: Ferraracasa Warehouse Triq is-Salib ta l-Mriehel CBD3020 Birkirkara Malta | F7: https://www.ferraramalta.com/
A8: Office Furniture | B8: Office Line Malta | C8: info@officelinemalta.com | D8: 2133 4401 | E8: Anthony Valletta Street, Swatar | F8: https://www.officelinemalta.com/
A9: Office Furniture | B9: Link Projects | C9: info@linkprojects.com.mt | D9: 2133 4145 | E9: 70, Ta' Xbiex Seafront , Msida, Malta | F9: https://linkprojects.com.mt/
A10: Office Furniture | B10: Vivendo | C10: info@vivendo.mt | D10: 2277 3000 | E10: Mdina Road, Qormi, QRM 9011, Malta | F10: https://vivendo.mt/
A11: Round Table | B11: IKEA | F11: https://www.ikea.com/it/it/p/mariedamm-tavolo-grigio-scuro-50441510/ | G11: 105cm Diameter | H11: 200EUR
A12: Tables | B12: SATARIANO | C12: info@satariano.com | D12: 21492149 | E12: 122, Valley Road Birkirkara, BKR 9024 | F12: https://satariano.com/products/room/tables/ | H12: Up on Reqquest
A13: Round Table | F13: https://www.megastore.com.mt/en_MT/p/MITTZON-Conference-table%2C-round-walnut-veneerblack%2C-120x75-cm/2145800 | G13: 120cm Diameter | H13: 240EUR
A14: Round Table, GLASS | B14: The Atrium | C14: contactus@theatrium.com.mt | D14: 2549 5000 | E14: Central Business District, Giovanni Felice Street - Zone 3, Birkirkara CBD 3120, Malta | F14: https://www.theatrium.com.mt/dining/dining-tables/atmosphera-ostras-dining-table-diameter-120cm-glass/Item?c=528741 | G14: 120cm Diameter | H14: 202EUR
A15: Round Table | B15: The Atrium | F15: https://www.theatrium.com.mt/dining/dining-tables/roxby-dining-table-black-oak-105cm/Item?c=267474 | G15: 105cm Diameter | H15: 275EUR
A16: Round Table, GLASS | B16: The Atrium | F16: https://www.theatrium.com.mt/dining/dining-tables/heaven-round-dining-table-with-clear-tempered-glass-top-and-thick-black-metal-legs/Item?c=512388 | G16: 120cm Diameter | H16: 365EUR
A17: Round Table | B17: Mega Store | F17: https://www.megastore.com.mt/en_MT/p/VIHALS-Table%2C-whitewhite%2C-107-cm/2237008 | G17: 107cm Diameter | H17: 101EUR

Sheet Office Tables
B2: Supplier | F2: Type | H2: Description | L2: Price | N2: Link
B3: The Atrium | F3: Round, 4 Legs | H3: 120cm Diameter, Glass Top | L3: 202EUR | N3: https://www.theatrium.com.mt/dining/dining-tables/atmosphera-ostras-dining-table-diameter-120cm-glass/Item?c=528741
B4: The Atrium | F4: Round, 4 Legs | H4: 120cm Diameter, Glass Top | L4: 375EUR | N4: https://www.theatrium.com.mt/dining/dining-tables/heaven-round-dining-table-with-clear-tempered-glass-top-and-thick-black-metal-legs/Item?c=512388
B5: The Atrium | F5: Round, 4 Legs | H5: 105cm Diameter, Black Vinyl | L5: 275EUR | N5: https://www.theatrium.com.mt/dining/dining-tables/roxby-dining-table-black-oak-105cm/Item?c=267474
B6: Mega Store | F6: Round, 4 Legs | H6: 107cm Diameter, White Vinyl | L6: 101EUR | N6: https://www.megastore.com.mt/en_MT/p/VIHALS-Table%2C-whitewhite%2C-107-cm/2237008
B7: Mega Store | F7: Round, 4 Legs | H7: 120cm Diameter, Walnut Veneer | L7: 237EUR | N7: https://www.megastore.com.mt/en_MT/p/MITTZON-Conference-table%2C-round-walnut-veneerblack%2C-120x75-cm/2145800
B8: The Atrium | F8: Round, 4 Legs | H8: 105cm Diameter, Light Oak Veneer | L8: 280EUR | N8: https://www.theatrium.com.mt/dining/dining-tables/roxby-dining-table-light-oak-top-black-legs-105cm/Item?c=267475
B9: The Atrium | F9: Round, 1 Leg | H9: 110cm Diameter, White Plastic | L9: 260EUR | N9: https://www.theatrium.com.mt/dining/dining-tables/ibiza-round-table-110cm-diameter-white/Item?c=510667
B10: OK Home | F10: Round, 1 Leg | H10: 110cm Diameter, Black Veneer | L10: 390EUR | N10: https://www.okhome.com.mt/products/matt+table/
B11: Kave Home | F11: Round, 4 Legs | H11: 120cm Diameter, White Vinyl | L11: 440EUR | N11: https://kavehome.mt/products/argo-round-table-in-white-melamine-and-steel-legs-with-black-finish-o-120-cm?variant=48354606219497

Sheet Living Room
A1: item | B1: supplier | C1: email | D1: phone number | E1: location | F1: website | G1: other
A2: Living Room | B2: Malta Design | C2: sales@malta-design.com | D2: 77105385 | E2: Malta Design 33 Triq l-Oleandru , San Giljan, Malta | F2: www.malta-design.com
A3: Living Room | B3: Joinwell | C3: info@joinwell.com.mt | D3: 2278 2000 | E3: JoinwellFXB, Triq il-Mithna, Central Business District, Qormi, CBD 5090 | F3: https://joinwell.com.mt/
A4: Living Room | B4: Brands International | C4: info@brands.com.mt | D4: 2095 9595 | E4: Triq tal-Balal, San Gwann, Malta | F4: https://www.brands.com.mt/
A5: Living Room | B5: ProMan Interiors | C5: info@promaninteriors.com | D5: 2131 0334 | E5: Proman Interiors, 115, Valley Road, B'Kara. BKR 9022. Malta. | F5: https://www.promaninteriors.com/
A6: Living Room | B6: Fino | C6: info@fino.com.mt | D6: 2549 3000 | E6: Fino Buildings, Triq l-Imdina, Zone 4, Mriehel/Central Business District CBD 4010, Malta | F6: https://fino.com.mt/
A7: Living Room | B7: Power House | C7: sales@powerhousemalta.eu | D7: 2742 4632 | E7: Power House, 13, Censu Bugeja Street, Birkirkara, Malta | F7: https://www.powerhousemalta.eu/
A8: Living Room | B8: FairDeal Furniture | C8: info@fairdealfurniture.com.mt | D8: 2728 2828 | E8: Fairdeal Furniture Malta LTD Mdina Road Zebbug, Malta | F8: https://fairdealfurniture.com.mt/
A9: Living Room | B9: Domesica | C9: info@domestica.com.mt | D9: 2144 7604 | E9: Domestica Complex, Level 1, Valley Road Msida, MSD 9091, Malta | F9: https://domestica.com.mt/
A10: Living Room | B10: OnePercent | C10: info@onepercent.com.mt | D10: 2546 5000 | E10: Valley Road Msida MSD 9022 | F10: https://onepercent.com.mt/
A11: Living Room | B11: Distinct Homes | C11: info@distincthomes.com.mt | D11: 2155 1234 | E11: Mdina Road, Attard | F11: https://distincthomes.com.mt/
A12: Living Room | B12: Index Furniture | C12: info@indexmalta.com | D12: 21806878 | E12: 159, Tip Top Buildings, St Thomas Street, Fgura, FGR1605 | F12: https://indexmalta.com/
A13: Living Room | B13: OK Home | C13: info@okhome.com.mt | D13: 2143 4747 | E13: OK Home, Pantar Road, Lija, Malta | F13: https://www.okhome.com.mt/
A14: Living Room | B14: The Atrium | C14: contactus@theatrium.com.mt | D14: 2549 5000 | E14: The Atrium, Giovanni Felice Street, Zone 3, Central Business District, Birkirkara CBD 3120 | F14: https://www.theatrium.com.mt/living
A15: Living Room | B15: Homemate | C15: customercare@homemate.com.mt | D15: 2326 2000 | E15: Homemate Mriehel | F15: https://www.homemate.com.mt/
A16: Living Room | B16: form | C16: infodesk@form.com.mt | D16: 2144 6000 | E16: Triq il-Wied Ta' L-Imsida, L-Imsida | F16: https://form.com.mt/living/
A17: Living Room | B17: Oxford House | C17: service@oxfordhouse.com.mt | D17: 2546 4543 | E17: Triq L-Imdina, Zone 2, Central Business District, Birkirkara CBD 2010, Malta | F17: https://oxfordhouse.com.mt/
A18: Living Room | B18: JYSK | C18: jysk@jysk.com.mt | D18: 27137364 | E18: Triq-Il Mosta, Lija, Malta | F18: https://jysk.com.mt/
A19: Living Room | B19: Homes by BDI | C19: info@bdi.com.mt | D19: 2149 1727 | E19: BDI, 1, Triq Pietru Felici, Qormi, Malta | F19: https://www.homesbybdi.com/en/home
A20: Living Room | B20: Dari | C20: info@dari.mt | D20: 2189 0459 | E20: Industrial Estate Ħandaq Qormi, QRM 4000, Malta | F20: https://dari.mt/living-rooms/
A21: Living Room | B21: Satariano | C21: info@satariano.com | D21: 2149 2149 | E21: 122, Msida Valley Road B’kara BKR 9024 | F21: https://satariano.com/
A22: Living Room | B22: Karrari | C22: sales@karrari.shop | D22: 2799 5000 | E22: Karrari (Showroom), Avenue 77, Commerce Street, Central Business District, , Birkirkara, Malta | F22: https://karrari.shop/
A23: Living Room | B23: Dino Fino | C23: info@dinofino.com | D23: 2124 0100 | E23: Dino Fino Home + Contract, Msida, Valley Road, Birkirkara, Birkirkara, Malta | F23: https://dinofino.com/
A24: Living Room | B24: Borge Group | C24: info@borgegroup.com | D24: 99148891 | F24: https://borgegroup.com/
A25: Living Room | B25: Bond's | C25: info@bondsmalta.com | D25: 2143 6407 | E25: Bond’s Limited Mdina Road, Attard, ATD 9039 | F25: https://www.bondsmalta.com/
A26: Living Room | B26: Immagine Casa | C26: info@immaginecasamalta.com | D26: 2144 0862 | E26: Valley Road, Birkirkara, Malta. | F26: https://www.immaginecasamalta.com/living-2/
A27: Living Room | B27: FerraraCasa | C27: info@ferraramalta.com | D27: 21483614 | E27: Ferraracasa Warehouse Triq is-Salib ta l-Mriehel CBD3020 Birkirkara Malta | F27: https://www.ferraramalta.com/
A28: Living Room | B28: Construct Furniture | C28: info@constructfurniture.com.mt | D28: 2122 0310 | E28: 40, Industrial Estate, Luqa LQA 3000, Malta | F28: https://constructfurniture.com.mt/contact-us/
A29: Living Room | B29: MaltaShopper.com | C29: sales@maltashopper.com | D29: 20334532 | E29: 162 Cannon Road, Santa Venera, SVR 9034, Malta | F29: https://maltashopper.com/
A30: Living Room | B30: Orienta | C30: info@orienta.com.mt | D30: 2144 5733 | E30: Triq L-Imdina, Zone 2 Central Business District, Birkirkara CBD 2010, Malta | F30: https://orienta.mt/
A31: Living Room | B31: Azeta | C31: info@azeta.com.mt | D31: 27482536 | E31: Azeta Limited 354 Cannon Road, St Venera SVR9033 Malta | F31: https://azeta.com.mt/pages/contact | G31: Also: dorianne@azeta.com.mt OR 77043376
A32: Living Room | B32: Daniel Woodworks | C32: danwoodworks@yahoo.co.uk | D32: 7940 7622 | E32: 86 Triq Valletta Hal Luqa Malta LQA 1762 | F32: https://www.danielwoodworksmalta.com/en/home.htm
A33: Living Room | B33: MaltaDIY | C33: sales@maltadiy.com | D33: 2034 1569 | E33: Baldacchino Building B, Triq Il-Belt Valletta, Zurrieq | F33: https://maltadiy.com/product-category/lights-and-tech/lights/
A34: Living Room | B34: Homistic Homes | C34: homistic@yahoo.com | D34: 7904 9970 | E34: 22/23 Triq hal mula Haz-zebbug ZBG | F34: https://www.homisticrooms.com/
A35: Living Room | B35: style interni | C35: info@styleinterni.com | D35: 2149 6473 | E35: 260 Old Railway Track, Santa Venera SVR 9019 | F35: https://styleinterni.com/
A36: Living Room | B36: Arko | C36: info@arkomalta.com | D36: 77972449 | E36: Triq is-Salib Ta' l-Imriehel Business District Mriehel | F36: https://www.arkomalta.com/
A37: Living Room | B37: Luks Furniture | C37: info@luksfurniture.com | D37: 2766 1083 | E37: Luks Furniture, Triq L-Imdina, Attard | F37: https://luksfurniture.com/
A38: Living Room | B38: EuroIm JSM | C38: sales@euroimjsm.com | D38: 21415553 | E38: 2, Industrial Estate Mdina Road Attard, ATD3000 | F38: https://www.euroimjsm.com/
A39: Living Room | B39: Luxonas | C39: info@luxonas.com | D39: 21451718 | E39: Triq L-Mdina, Haz-Zebbug, ZBG09018 | F39: https://luxonas.com/
A40: Living Room | B40: Lingonberries | C40: sales@lingonberries.eu | D40: 2788 3788 | E40: 27 Triq Wignacourt, Birkirkara | F40: https://www.lingonberries.mt/
A41: Living Room | B41: BoConcept | C41: info@boconcept.com.mt | F41: https://www.boconcept.com/en-mt/
A42: Living Room | B42: Loft | C42: info@loft.com.mt
A43: Living Room | B43: Gauci Woods | C43: pdgl1969@gmail.com
A44: Living Room | B44: Newline Living Concept | C44: newlineliving@gmail.com

Sheet Storage Units
A1: item | B1: supplier | C1: email | D1: phone number | E1: location | F1: website | G1: other
A2: Custom Furniture/Storage Unit | B2: PM Hobby | C2: sales@pmhobby.com.mt
A3: Custom Furniture/Storage Unit | B3: Design Hub | C3: info@designhubmalta.com.mt
A4: Custom Furniture/Storage Unit | B4: De Valier | C4: customer@devalier.com.mt
A5: Custom Furniture/Storage Unit | B5: Def Furniture | C5: info@deffurniture.com
A6: Custom Furniture/Storage Unit | B6: Construct Furniture | C6: info@constructfurniture.com.mt
A7: Custom Furniture/Storage Unit | B7: JCR Furniture | C7: info@jcrfurniture.com
A8: Custom Furniture/Storage Unit | B8: Custom Workshop Malta | C8: thecustomworkshop@gmail.com
A9: Custom Furniture/Storage Unit | B9: Amets Furniture | C9: info@ametsfurniture.com
A10: Custom Furniture/Storage Unit | B10: Turnkey Services Malta | C10: info@ts-malta.com
A11: Custom Furniture/Storage Unit | B11: JDS Furniture | C11: info@jdsfurniture.com
A12: Custom Furniture/Storage Unit | B12: Ciantar Woodworks | C12: jasoakwalnut@yahoo.com
A13: Custom Furniture/Storage Unit | B13: C&M Woodworks | C13: candmww@gmail.com
... A16: Custom Furniture/Storage Unit | B16: Kasarreda | C16: kasa.arreda@gmail.com
B17: Lupa | C17: info@lupa.mt
B18: Dari | C18: info@dari.mt
B19: Trends | C19: info@trendsltdmalta.com
B20: Saliba Woodworks | C20: chrissaliba295@gmail.com
B21: Paul Target | C21: info@paultarget.com
B22: Fairdeal Furniture | C22: info@fairdealfurniture.com.mt
B23: Ferraracasa | C23: info@ferraramalta.com
B24: Dino Fino | C24: info@dinofino.com
B25: Mon Lung Woodworks | C25: monlung@onvol.net

Sheet Custom Furniture
A1: item | B1: supplier | C1: email | D1: pohone number | E1: location | F1: website

Sheet Garden 
A1: Garden
A2: item | B2: supplier | C2: email | D2: phone number | E2: location | F2: website
A3: Garden chair | B3: Brands International Ltd | C3: info@brands.com.mt | D3: 20 959 595 | E3: Triq tal-Balal, San Gwann | F3: www.brands.com.mt
A4: Garden chair | B4: OK Home | C4: info@okhome.com.mt | D4: 21 434 747 | E4: Triq Pantar, Lija | F4: www.okhome.com.mt
A5: Garden chair | B5: Protrade Decor | C5: protrade@protrademalta.com | D5: 21 485 203 | E5: Zone 5 Triq Is-Sebh Central Business District, Qormi | F5: https://www.facebook.com/@protrademalta/
A6: Garden chair | B6: Dino Fino Home & Contract | C6: info@dinofino.com | D6: 21 240 100 | E6: Triq il-Wied Ta' L-Imsida, B'Kara, Malta BKR 9025 | F6: www.dinofino.com
A7: Garden chair | B7: camilleriparismode | C7: you@camilleriparismode.com | D7: 2010 2030 | E7: 54 Triq Santa Katerina, Rabat | F7: www.camilleriparismode.com
A8: Garden chair | B8: Patrolea | C8: sales@patroleamalta.com | D8: 21 234 501 | E8: Triq il-Wied ta' I-Imsida, Msida | F8: www.patroleamalta.com
A9: Garden chair | B9: JYSK | C9: jysk@jysk.com.mt | D9: 27 137 364 | E9: Triq il-Mosta, Lija, Malta LIJA 9012 | F9: www.jysk.com.mt
A10: Garden chair | B10: G D L Trading & Services Ltd | C10: peter@gdl.com.mt | D10: 2123 5415 | E10: 70 Triq is-Salib tal-Marsa | F10: https://www.facebook.com/maltawarehousesale/
A11: Garden chair | B11: The Atrium | C11: contactus@theatrium.com.mt | D11: 2549 5000 | E11: Giovanni Felice Street, Zone 3, Central Business District, Birkirkara CBD 3120 | F11: www.theatrium.com.mt
A12: Garden chair | B12: Piscopo Gardens Ltd | C12: info@piscopogardens.com | D12: 2158 6755 | E12: Triq Toni Camilleri, Burmarrad | F12: www.piscopogardens.com
A13: Garden chair | B13: Malta Design | C13: https://www.malta-design.com/en/1652-chairs-and-tables | D13: 2144 5800 | E13: Birkirkara | F13: www.malta-design.com
... A84: Plants | B84: Derek Garden Centre | C84: sales@derekmalta.com / flowershop@derekmalta.com | D84: 2144 9754 | E84: 71 Canon Road, Qormi | F84: www.derekmalta.com
A85: Landscaping | B85: Garland Malta | C85: projects@garlandmalta.com | D85: 9969 0258 | F85: https://www.garlandmalta.com/
A86: Garden | B86: All Seasons Home and Garden | C86: customercare@allseasons.mt | F86: https://www.allseasons.mt/

Sheet Outdoor Furniture
A1: item | B1: supplier | C1: email | D1: phone number | E1: location | F1: website
A2: Furniture | B2: Malta Design | C2: sales@malta-design.com | D2: 7710 5385 | E2: Malta Design 33 Triq l-Oleandru , San Giljan, Malta | F2: www.malta-design.com
A3: Furniture | B3: Pitre Home | C3: home@jpitre.com | D3: 2746 3330 | E3: Pitre Home Ltd, Mdina Road, Qormi | F3: https://pitreonline.com/
A4: Furniture | B4: Brands International | C4: info@brands.com.mt | D4: 2095 9595 | E4: Triq tal-Balal, San Gwann, Malta | F4: https://www.brands.com.mt/
A5: Furniture | B5: Fino | C5: info@fino.com.mt | D5: 2549 3000 | E5: Fino Buildings, Triq l-Imdina, Zone 4, Mriehel/Central Business District CBD 4010, Malta | F5: https://fino.com.mt/
A6: Furniture | B6: Style Interni | C6: info@styleinterni.com | D6: 2149 6473 | E6: 260 Old Railway Track, Santa Venera SVR 9019 | F6: https://styleinterni.com/
A7: Furniture | B7: All Seasons Home and Garden | C7: customercare@allseasons.mt | F7: https://www.allseasons.mt/
A15: NOTE: Look up items which are permitted in the Outdoor Catering Area such as tables, chairs, heaters, planters, and serving stations. Excluding shading equipment/structures

Sheet Wallpapers
A1: item | B1: supplier | C1: email | D1: pohone number | E1: location | F1: website
A2: Wallpaper | B2: style interni | C2: info@styleinterni.com | D2: 2149 6473 | E2: 260 Old Railway Track, Santa Venera SVR 9019 | F2: https://styleinterni.com/
A3: Wallpapers | B3: Spot On Lighting | C3: info@spotonmalta.com | D3: 2166 8880 | E3: 102 Palm Street, PLA1414 Paola MALTA. | F3: https://spotonmalta.com/
A4: Wallpapers | B4: Mega Home | C4: info@megahome.mt | D4: 9997 5737 | E4: Triq Il-Vitorja, Ħal Qormi QRM 2504 | F4: https://megahome.mt/
A5: Wallpapers | B5: BF Marbles | C5: info@bfmarbles.com | D5: 7724 4377 | F5: https://www.bfmarbles.com/#
A6: Wallpapers | B6: Lingonberries | C6: sales@lingonberries.eu | D6: 2788 3788 | E6: 27 Triq Wignacourt, Birkirkara | F6: https://www.lingonberries.mt/
A7: Wallpapers | B7: Big Ben Interiors | C7: info@bigbeninteriors.com.mt | D7: 2144 7347 | E7: Naxxar Road, Birkirkara, Malta, BKR 9045 | F7: https://bigbeninteriors.com.mt/

Sheet Trimwork
A1: item | B1: supplier | C1: email | D1: pohone number | E1: location | F1: website
A2: Mouldings | B2: Mega Home | C2: info@megahome.mt | D2: 9997 5737 | E2: Triq Il-Vitorja, Ħal Qormi QRM 2504 | F2: https://megahome.mt/
A3: Mouldings | B3: BF Marbles | C3: info@bfmarbles.com | D3: 7724 4377 | F3: https://www.bfmarbles.com/#
A4: Skirting | B4: SOLL | C4: info@soll.mt | D4: 79628055 | E4: B1, Midland Enterprise Park Burmarrad Road, Naxxar, Malta | F4: https://soll.mt/
A5: Skirting | B5: Quality Wall Panels | D5: 7903 0403 | F5: https://www.facebook.com/profile.php?id=61561349402968
G15: ADD | H15: https://noble.mt/moulding-and-wall-panelling/

Sheet House Decor
A1: item | B1: supplier | C1: email | D1: phone number | E1: location | F1: website
A2: Decor | B2: MaltaDIY | C2: sales@maltadiy.com | D2: 2034 1569 | E2: Baldacchino Building B, Triq Il-Belt Valletta, Zurrieq | F2: https://maltadiy.com/product-category/lights-and-tech/lights/
A3: Decor | B3: style interni | C3: info@styleinterni.com | D3: 2149 6473 | E3: 260 Old Railway Track, Santa Venera SVR 9019 | F3: https://styleinterni.com/
A4: Decor | B4: Ferrara Casa | C4: info@ferraramalta.com | D4: 21483614 | E4: Ferraracasa Warehouse Triq is-Salib ta l-Mriehel CBD3020 Birkirkara Malta | F4: https://www.ferraramalta.com/
A5: Artistic and Creative Finishes | B5: Veneziano Creazioni | C5: venezianocreazioni@gmail.com | D5: 9990 6485 | E5: Mosta, Malta | F5: https://www.facebook.com/venezianocreazioni/?locale=it_IT
A6: Clocks | B6: Mega Home | C6: info@megahome.mt | D6: 9997 5737 | E6: Triq Il-Vitorja, Ħal Qormi QRM 2504 | F6: https://megahome.mt/
A7: Frames and Pictures | B7: Luxonas | C7: info@luxonas.com | D7: 21451718 | E7: Triq L-Mdina, Haz-Zebbug, ZBG09018 | F7: https://luxonas.com/
A8: Decor | B8: Lingonberries | C8: sales@lingonberries.eu | D8: 2788 3788 | E8: 27 Triq Wignacourt, Birkirkara | F8: https://www.lingonberries.mt/

Sheet Business Cards
A1: item | B1: supplier | C1: email | D1: phone number | E1: location | F1: website
A2: Business Cards | B2: Turbo Signs | C2: turbosigns@outlook.com | D2: 79271448 | E2: Parades Street, St Paul's Bay | F2: https://www.turbosignsmalta.com/

Sheet Laundry room
A1: Laundry room
A2: item | B2: supplier | C2: email | D2: phone number | E2: location | F2: website
A3: Washing machine | B3: Ventura General Gas Ltd | C3: www.vanturamalta.com | D3: 21 677 798 / 21 225 608 / 21 240 938 | E3: BLB 021 Qasam Industrijali, Bulebel, Zejtun, Malta ZTN 3000 | F3: www.venturamalta.com
A4: Washing machine | B4: Petroni Ltd | C4: info@petroni.com.mt | D4: 21 447 763 | E4: Triq il-Wied ta' I-Imsida, Msida, Malta MSD 9022 | F4: www.petroni.com.mt
A5: Washing machine | B5: Soundsmart | C5: info@soundsmart.com.mt | D5: 21 430 569 / 79 454 867 | E5: Triq il-Kostituzzjoni, Mosta, Malta MST 9050 | F5: www.soundsmart.com.mt
A6: Washing machine | B6: KCL Home Centre | C6: info@kcl.com.mt | D6: 21 493 285 | E6: 22, Triq Sant' Elija, B'Kara, Malta BKR 2064 | F6: www.kcl.com.mt
A7: Washing machine | B7: Futura Home Appliances | C7: futurahomeappliances@gmail.com | D7: 21 377 181 | E7: 220 Triq in-Naxxar, San Gwann, Malta SGN 9030 | F7: https://www.facebook.com/futurahomeappliances/
A8: Washing machine | B8: Tablets & More | C8: tabletsandmoreelectronics@yahoo.com | D8: 27 366 601 | E8: 12 Triq il-Hammieri, Qormi, Malta | F8: www.tabletsandmoreelectronics.com
A9: Washing machine | B9: Akkwist | C9: camrugun@hotmail.com | D9: 27 898 230 | E9: 18 Wesghat il-Knisja tan-Nattivita, Bormla, Malta BML 1650 | F9: www.facebook.com/akkwist
A10: Washing machine | B10: Ta' Gulinu | C10: tagulinu@onvol.net | D10: 21 454 379 | E10: 10 Misrah I' Isle Adam, Rabat, Malta RBT 1169 | F10: https://www.facebook.com/TaGulinu/info?tab=page%5Cuinfo
A11: Washing machine | B11: Triple A | C11: etv@etvhomeline.com | D11: 21 237 601 | E11: Triq San Tumas, Luqa, Malta LQA 9031 | F11: www.triplealuqa.com
A12: Washing machine | B12: Bakers Point | C12: bakerspoint1@gmail.com | D12: 21 464 646 | E12: Triq it-Tabib Nikol Zammit, Siggiewi, Malta SHW 3075 | F12: _______
A13: Washing machine | B13: Cath's Home | C13: caths@melita.com | D13: 27 453 200 | E13: Triq il-Gzira, Malta GZR 1312 | F13: www.facebook.com/cathshome
... A55: Dryer machine | B55: X-Treme Technologies | C55: x.treme@onvol.net | D55: 21 553 611 | E55: Triq Gorg Borg Olivier, Victoria-Gozo, Gozo VCT 2514 | F55: www.xtmalta.com

Sheet Window Films
A1: item | B1: supplier | C1: email | D1: phone number | E1: location | F1: website
A2: UV Films | B2: SolarTech | C2: solartechmalta@gmail.com | D2: 2147 2000 | E2: 12, SolarTech, Triq il-Masgar Qormi, QRM 3217, Malta | F2: https://solartech.com.mt/
A3: UV Films | B3: Recowatt | C3: info@recowatt.com | D3: 2166 0546 | E3: Triq L-Imdina, Ħaż-Żebbuġ ZBG 9019, Malta | F3: https://recowatt.com/
A4: UV Films | B4: Sign World Malta | C4: info@signworldmalta.com | D4: 9947 1937 | E4: Triq il-Frangiskani, L-Imsida MSD 1120, Malta | F4: https://signworldmalta.com/
A5: Custom Frosted Window Film | B5: Polidano Press | C5: ppl@pplmalta.com | D5: 2122 7888 | E5: 112 Industrial Estate , Ħal Luqa, Malta | F5: https://www.pplmalta.com/
A6: UV Films | B6: Turbo Signs | C6: turbosigns@outlook.com | D6: 79271448 | E6: Parades Street, St Paul's Bay | F6: https://www.turbosignsmalta.com/
A7: UV Films | B7: Just LTD Malta | C7: info@justltdmalta.com | D7: 99490109 | E7: 194, Luqa Briffa Street, Gzira GZR1504, Malta | F7: https://justltdmalta.com/home.html
A8: UV Films | B8: Zaffarese | C8: admin@zaffarese.com | D8: 2148 4305 | E8: CCG Building, Triq 3 Ta’ Settembru 1798 Zone 3, Central Business District, Birkirkara CBD 3100 Malta | F8: https://zaffarese.com/
A9: UV Films | B9: GRF Contractor Studio | C9: info@grfmalta.com | D9: 21377378 | E9: 117 Triq L-Assemblea Nazzjonali, San Gwann SGN 3034, Malta | F9: https://grfmalta.com/
A10: UV Films | B10: Opaque | C10: contact@opaque.mt | D10: 7979 2552 | F10: https://www.opaquemalta.com/

Sheet Blinds
A1: item | B1: supplier | C1: email | D1: phone number | E1: location | F1: website
A2: blinds | B2: Blinds & More | C2: sales@blindsandmore.com.mt | D2: 2787 8700 | E2: 41 Triq in-Naxxar, San Ġwann, Malta SGN 9030 | F2: www.blindsandmore.com.mt
A3: blinds | B3: Sunlock Window Blinds | C3: info@sunlockblinds.com | D3: 2122 2083 | E3: Triq l-Imdina, Żebbuġ, ZBG 9016, Malta | F3: sunlockblinds.com
A4: blinds | B4: Gozo Vertical Blinds & Shades Ltd | C4: info@gozoverticals.com | F4: https://www.gozoverticals.com/
A5: blinds | B5: MG Home Interiors | C5: mghomeinteriorsltd@gmail.com | D5: 2142 0540 / 9988 3988 | E5: MG Home Interiors Ltd, 2 Triq San Tumas, Ħal Luqa | F5: https://mghomeinteriors.com/#services
A6: blinds | B6: Nigel Dimech | C6: info@nigeldimech.com | D6: 7943 4443 / 2143 4443 | E6: KKW 721, Corradino Industrial Estate Paola, PLA 3000, Malta | F6: https://nigeldimech.com/
A7: blinds | B7: Blinds4All | C7: sales@blinds4all.mt | D7: 7777 4083 | F7: https://www.facebook.com/blinds4allmalta
A8: blinds | B8: Kuluri Malta | C8: kulurimalta@gmail.com | D8: 79437704 | F8: https://www.kulurimalta.com/
A9: blinds | B9: Homemate | C9: customercare@homemate.com.mt | D9: 2326 2000 | E9: Mriehel, Malta | F9: https://www.homemate.com.mt/
A10: blinds | B10: BD blinds | C10: info@bdblinds.mt | D10: 2169 2885 | E10: Industrial Estate Bulebel, Zejtun ZTN 3000 Malta | F10: https://bdblinds.mt/
A11: blinds | B11: JYSK | C11: jysk@jysk.com.mt | D11: 27137364 | E11: Triq-Il Mosta, Lija, Malta | F11: https://jysk.com.mt/
A12: blinds | B12: latenda | C12: hello@latenda.com.mt | D12: 99357300 | F12: https://latenda.com.mt/
A13: blinds | B13: yourblinds | C13: info@yourblindsmalta.com | D13: 9987 5265 | E13: 58, Daddy’s Court Flat 1, Triq Il-Pitkali, Attard | F13: https://yourblindsmalta.com/
A14: blinds | B14: The Atrium | C14: contactus@theatrium.com.mt | D14: 2549 5000 | E14: The Atrium, Giovanni Felice Street, Zone 3, Central Business District, Birkirkara CBD 3120 | F14: https://www.theatrium.com.mt/living
A15: blinds | B15: Vicali Interiors | C15: info@vicalinteriors.com | D15: 99499925 | E15: 84, Qormi Road, Hamrun | F15: https://www.vicalinteriors.com/
A16: blinds | B16: Mega Store | C16: shop@megastore.com.mt | D16: 2141 6753 | E16: Warehouse No. 25, Hard Rocks Industrial Park, Burmarrad Road, Naxxar, Malta | F16: https://www.megastore.com.mt/
A17: blinds | B17: Big Ben Interiors | C17: info@bigbeninteriors.com.mt | D17: 2144 7347 | E17: Naxxar Road, Birkirkara, Malta, BKR 9045 | F17: https://bigbeninteriors.com.mt/
A18: blinds | B18: HML Workshop | C18: info@hml.com.mt | D18: 2148 5215 | E18: HML Workshop, Cannon Road Qormi | F18: https://www.hml.com.mt/
A19: blinds | B19: Dimech Enterprises | C19: sales@dimech-ent.com | D19: 2132 0433 | E19: Dimech Enterprises Ltd Centre Point, Triq Valletta Luqa Malta LQA 1762 | F19: https://www.dimech-ent.com/
A20: blinds | B20: NBlinds | C20: nblindsmalta@gmail.com | D20: 7774 5619 | E20: 219, Sanctuary Street, Zabbar, Malta | F20: https://www.facebook.com/nblindsmalta/?utm_source=chatgpt.com
A21: blinds | B21: Mi Casa Solutions | C21: micasasolutions3@gmail.com | D21: 7900 9947 | E21: 156 Triq Ganu, Birkirkara, Malta | F21: https://micasasolutions.eu/
A22: blinds | B22: David Interiors | C22: info@davidinteriors.com | D22: 2144 3859 | E22: David Interiors, 161, St. Edwards Street, Qormi | F22: https://www.davidinteriors.com/en/home.htm
A23: blinds | B23: Direct Developments | C23: sales@pvcmalta.com | D23: 2138 2595 | E23: L, 52 Triq Il- Muzika, Iklin IKL 1091 | F23: https://www.pvcmalta.com/en/home.htm
A24: blinds | B24: Zebra Blinds Malta | C24: zebrablindsmalta@gmail.com | D24: 9996 0623 | F24: https://zebrablindsmalta.com/
A25: blinds | B25: Malta DIY | C25: sales@maltadiy.com | D25: 2034 1569 | F25: https://maltadiy.com/
A26: blinds | B26: JB Stores | C26: info@jbstores.com | D26: 2331 4206 | E26: JB Stores, JB House, Iklin Road, Iklin | F26: https://jbstoresonline.com/
A27: blinds | B27: Budget Blinds | C27: infobudgetblindsmalta@gmail.com | D27: 99476622 | E27: Triq-il Bufura l-Hamra, Mosta | F27: https://budgetblinds.mt/
B28: Royalty Screen and Blinds | C28: info@royaltyscreens.com | D28: 2347 2994 | E28: Zircon Suites Triq ta' Zejfa,Mosta, Malta. | F28: https://www.royaltyscreens.com/contact-us

Sheet Systems 
A1: Systems
A2: item | B2: supplier | C2: email | D2: phone number | E2: location | F2: website
A3: Fire alarms | B3: J Grima & Co Ltd | C3: info@jgrima.com | D3: 21 445 533 | E3: 130, Triq Salvu Psaila, B'Kara | F3: www.jgrima.com
A4: Fire alarms | B4: Antifire Safety & Security Ltd | C4: info@antifire.com.mt | D4: 79 300 112 / 99 300 112 | E4: Triq il-Belt Valetta, Qormi | F4: www.antifire.com.mt
A5: Fire alarms | B5: A E C O Telecom & Security Systems | C5: info@aeco.com.mt | D5: 21 318 181 | E5: 10 Triq Amabile Sisner, Fgura | F5: www.aeco.com.mt
A6: Fire alarms | B6: P D Security Installations | C6: info@pdsecuritymalta.com | D6: 79 819 905 | E6: 25 Triq il-Bennej, Mosta | F6: https://www.facebook.com/pdsec.malta?utm_source=Yellow&utm_medium=Yellow-Website&utm_campaign=Landing-Page#
A7: Fire alarms | B7: Soteria Ltd | C7: info@soteria.com.mt | D7: 21 227 746 | E7: Dawert Hal Ghaxaq | F7: www.soteria.com.mt
A8: Fire alarms | B8: Elektro Services | C8: info@elektroservices.com.mt | D8: 79050568 | E8: 347 Triq D’Argens, Il-Gżira | F8: https://elektroservices.com.mt/
A10: CCTV | B10: Securtek Limited | C10: info@security.com.mt | D10: 22 484 623 | E10: 9 Triq in-Narcis, San Gwann | F10: www.securtek.com/home
A11: CCTV | B11: J Grima & Co Ltd | C11: info@jgrima.com | D11: 21 445 533 | E11: 130, Triq Salvu Psaila, B'Kara | F11: www.jgrima.com
A12: CCTV | B12: P D Security Installations | C12: info@pdsecuritymalta.com | D12: 79 819 905 | E12: 25 Triq il-Bennej, Mosta | F12: https://www.facebook.com/pdsec.malta?utm_source=Yellow&utm_medium=Yellow-Website&utm_campaign=Landing-Page#
A13: CCTV | B13: Antifire Safety & Security Ltd | C13: info@antifire.com.mt | D13: 79 300 112 / 99 300 112 | E13: Triq il-Belt Valetta, Qormi | F13: www.antifire.com.mt
A14: CCTV | B14: A E C O Telecom & Security Systems | C14: info@aeco.com.mt | D14: 21 318 181 | E14: 10 Triq Amabile Sisner, Fgura | F14: www.aeco.com.mt
A15: CCTV | B15: Alarm Tech | C15: info@alarmtechmalta.com | D15: 21 490 758 | E15: Sub 901 Triq F S Caruana Qasam Industrijali, San Gwann | F15: www.alarmtechmalta.com
A16: CCTV | B16: CB Security | C16: info@cbsecuritymalta.com | D16: 79 996 119 | E16: 40 Triq il-Konvoj Ta' Santa Marija, Mqabba | F16: www.cbsecuritymalta.com
A17: CCTV | B17: CCTV Solutions | C17: darren@d-tech.mt | D17: 79 444 378 | E17: 258 Triq is-Sur, Fgura | F17: _________
A18: CCTV | B18: Correct Terminations Ltd | C18: jmallia@vol.net.mt | D18: 99 420 739 | E18: Triq Felicia Abela, Zejtun | F18: _________
A19: CCTV | B19: Craud Security | C19: craudsecurity@gmail.com | D19: 77 570 570 | E19: 168 Triq Bajada, Zabbar | F19: https://www.facebook.com/p/Craud-Security-100083313423806/
A20: CCTV | B20: Dedicated Micros Ltd | C20: sales@dmicros.com.mt | D20: 21 483 673 | E20: BLB 017 Qasam Industijali, Bulebel, Zejtun | F20: www.dedicatedmicros.com
A21: CCTV | B21: Dar Services Ltd | C21: info@darservicesmalta.com | D21: 21 668 022 | E21: Triq il-Belt Valletta, Luqa | F21: www.darservicesmalta.com
... A35: CCTV | B35: Universal Micro Security | C35: umsmalta@gmail.com | D35: 99 446 089 | E35: Garage 4 Triq Edgar Ferro, Pieta' | F35: www.universalmicrosecurity.com
A36: CCTV | B36: Elektro Services | C36: info@elektroservices.com.mt | D36: 79050568 | E36: 347 Triq D’Argens, Il-Gżira | F36: https://elektroservices.com.mt/
A37: CCTV | B37: SML | C37: info@sml.com.mt | D37: 2124 9707 | E37: Blu Building, Qormi Road, Luqa | F37: http://www.intercoms.com.mt/
A38: CCTV | B38: Alberta | C38: info@alberta.com.mt | D38: 2144 3538 | E38: Triq San Gwakkin, Zone 3, Central Business District, Birkirkara, CBD 3030, Malta | F38: https://www.alberta.com.mt/products-and-services/cctv-systems-for-your-home/
A39: CCTV | B39: Focal Tech Malta | C39: info@focaltechmalta.com | D39: 27605017 | E39: Focal Tech Malta Triq Alfredo Cachia Zammit. Zejtun, Malta | F39: https://www.focaltechmalta.com/solutions/safire-smart-cctv/
A40: CCTV | B40: Masco | C40: info@masco.com.mt | D40: 2143 4400 | E40: Masco House, Valletta Road, Mosta | F40: https://masco.com.mt/contact-us/
A41: CCTV | B41: SecureVision | C41: info@securevision.com.mt | D41: 21444398 | E41: Securevision, W.S Gauci Limited, Wignacourt Street, Birkirkara, BKR 4714, Malta | F41: https://securevision.com.mt/sv/product-category/security/cctv/
A42: CCTV | B42: Firetech | C42: info@firetech.com.mt | D42: 2278 5200 | E42: Zone 5, Central Business District, 99 Triq il-Mitħna, Qormi CBD 5090 | F42: https://www.firetech.com.mt/about-us
A43: CCTV | B43: SecuRich | C43: info@securichmalta.com | D43: 2146 3618 | E43: Securich Co Ltd 121, Mdina Road, Zebbug | F43: https://www.securichmalta.com/en/services/services/5/cctv-cameras.htm
A44: CCTV | B44: Cobra | C44: kevin@cobrainstallations.com | D44: 9949 8033 | F44: https://cobrainstallations.com/
A45: CCTV | B45: CZ SmartTech | C45: info@czsmarttech.com | D45: 79793611 | F45: https://www.czsmarttech.com/
A47: Pv panels | B47: AQS ENERGY | C47: sales@aqsmed.com | D47: 79 376 112 / 20 102 121 / 79 390 636 | E47: 9 Triq F S Caruana, B'Kara | F47: www.aqsmed.com
A48: Pv panels | B48: Alternative Technologies Ltd | C48: info@alternativetechnologies.com.mt | D48: 21 380 309 | E48: 1 triq Dun Guzepp Xerri, San Giljan | F48: www.alternativetechnologies.com.mt
A49: Pv panels | B49: Solar Solutions Ltd | C49: info@solarsolutions.com.mt | D49: 21 424 750 | E49: 2, 3 Triq tal-Balal Tax-Xwieki, Gharghur | F49: www.solarsolutions.com.mt
A50: Pv panels | B50: CallejaFormosa Energy Saving | C50: info@callejaformosaenergysaving.com | D50: 99 486 132 | E50: Paradise Triq Fra Baskal, Zebbug-Gozo | F50: www.callejaformosaenergysaving.com
A51: Pv panels | B51: CD Power Solutions Co Ltd | C51: info@powersolutions.com.mt | D51: 21 480 500 | E51: Ciancio House, Zone 5 Triq ll-Kanun Central Business District, Qormi | F51: www.powersolutions.com.mt
A52: Pv panels | B52: CFL Group Engineering Malta Ltd | C52: cflgroupmalta@gmail.com | D52: 27 349 054 | E52: 39 Triq il-Kwartin, Swieqi | F52: www.cflgroupmalta.com
A53: Pv panels | B53: CS Technical Services | C53: josephspiteri.cs@gmail.com | D53: 99 292 730 | E53: 133 CSTS Ltd Triq il-Koppla, Fgura | F53: www.csts-malta.com
A54: Pv panels | B54: Electrofix Group | C54: sales@electrofixgroup.com | D54: 21 675 353 | E54: Triq il-Burdnara, Qormi | F54: www.electrofixgroup.com
A55: Pv panels | B55: Gozo Solar Energy | C55: gozo.solar@gmail.com | D55: 79 602 611 | E55: Summer Set House Triq Dun Karlu Zimech Nadur-Gozo | F55: https://www.facebook.com/p/Gozo-Solar-Energy-Solar-Panels-and-Solar-Water-Heaters-100057213680113/
A56: Pv panels | B56: JLC energy - home | C56: jlcenergyhome@gmail.com | D56: 79 404 890 | E56: 220 Triq Alfredo Cachia Zammit, Zejtun | F56: https://www.facebook.com/people/JLC-energy-home/100063454366944/?fref=ts%3Futm_source%3DYellow&utm_medium=Yellow-Website&utm_campaign=Landing-Page#
A57: Pv panels | B57: Luxury Living Technologies Limited | C57: info@llt.com.mt | D57: 20 996 609 | E57: Green Business Comples Triq il-Hofor, Qormi | F57: www.llt.com.mt
A58: Pv panels | B58: Power Plus Trading Limited | C58: info@powerplusltd.com | D58: 27 167 167 | E58: 20, Triq Pietru Xuereb, Pieta' | F58: www.powerplus.com
... A60: Pv panels | B60: Virtue Solaris | C60: info@virtuesolaris.com | D60: 99 880 528 | E60: Sagra Famiglia Building Triq Mro Giorgio Zarb, Qormi | F60: www.virtuesolaris.com

Sheet Water tank
A1: item | B1: supplier | C1: email | D1: phone number | E1: location | F1: website
A2: water tank | B2: Idroplast Manufacturing Ltd | C2: info@idroplastmalta.com | D2: 6 2165 0127 | E2: Factory MRA014, Qasam Industrijali, Marsa, Malta | F2: www.idroplastmalta.com
A3: water tank | B3: KHS Malta | C3: info@khsmalta.com | D3: 2169 3446 | E3: 54, Castaldi Street, Żabbar ZBR1453, Malta | F3: www.khsmalta.com
A4: water tank | B4: Micallef Fibreglass Works | C4: info@micalleffibreglassworks.com | D4: 2157 0332 | E4: 7, Sun Down Yard, Triq il-Burmarrad, Naxxar, Malta NXR 6345 | F4: www.micalleffibreglassworks.com
A5: water tank | B5: Framegrip Ltd | C5: james@framegrip.com | D5: 2141 9788 | E5: Triq Il-Mosta, Hal Lija, Malta LJA 9010 | F5: www.framegrip.com
A6: water tank | B6: JWT Caruana | C6: info@jwtcaruana.com | D6: 9946 0050 | E6: Caruana Farm, Triq it-Tnax Ta' Mejju, Żebbuġ, ZBG 1281, Malta | F6: www.jwtcaruana.com
A7: water tank | B7: The Hardware Store | C7: thehardwarestoremalta@gmail.com | D7: 77 203 556 | E7: 31 Triq il-Witja , Tarxien, Malta TXN 2296 | F7: www.thehardwarestoremalta.com/
A8: water tank | B8: Richie's Ironmongery | C8: rironmongomery@onvol.net | D8: 27 422 892 | E8: 222, 224 Vjal il-Wiehed U Ghoxrin Ta’ Settembru , Naxxar, Malta NXR 1012 | F8: www.richiesironmongerymalta.com
A9: water tank | B9: Old Key Ironmongery | C9: deguara24@gmail.com | D9: 27 312 222 | E9: Triq il-Klin , Iklin, Malta IKL 1032 | F9: www.facebook.com/1675915686031114
A10: water tank | B10: W Cardona Trading | C10: wcardonatrading@gmail.com | D10: 99 477 271 | E10: 242 Triq l-Imdina , Qormi, Malta QRM 9014 | F10: www.wcardonatrading.com/
A11: water tank | B11: Cauchi Joseph Ironmongery | C11: jcironmongomery@mail.com | D11: 21 222 737 | E11: 9 Triq Dun Nerik Cordina Perez , Hamrun, Malta HMR 2101 | F11: www.jcironmongery.com
A12: water tank | B12: Alldecor Hardware Supplies | C12: alldecor@maltanet.net | D12: 21 332 640 | E12: 166 Triq il-Kullegg L-Antik , Sliema, Malta SLM 1373 | F12: -----------
A13: water tank | B13: The Ironmonger | C13: kevinbartololtd@gmail.com | D13: 27 002 218 | E13: 16 Triq Sant’ Antnin , M’Skala, Malta MSK 9058 | F13: -----------
A14: water tank | B14: AFS | C14: info@afs.com.mt | D14: 21417771 | E14: Triq L-Imdina, Ħ'Attard, Malta | F14: https://www.facebook.com/afsmalta/
A15: water tank | B15: Firm B Pullicino | C15: info@fbpmalta.com | D15: 2167 6627 | E15: 139, Bajada Street, Zabbar, Malta | F15: https://www.fbpmalta.com/
A16: water tank | B16: Midea | C16: sales@midea.mt | F16: https://midea.mt/contact/
A17: water tank | B17: Homemate | C17: customercare@homemate.com.mt
A18: water tank | B18: Tesy | C18: office@tesy.com
A19: water tank | B19: Top Choice | C19: info@topchoice.com.mt
A20: water tank | B20: Zenith
A21: water tank | B21: Atlantic | C21: info@atlanticwaterheaters.com.mt
A22: water tank | B22: Digital Zone | C22: info@digitalzone.com.mt
A23: water tank | B23: BigMat | C23: info@bigmatmalta.com
A24: water tank | B24: Thermex | C24: info@thermex.com.mt
A25: water tank | B25: Flamingo | C25: sales@flamingo.mt
A26: water tank | B26: BT Commerical | C26: info@btmalta.com
A27: water tank | B27: Carini | C27: sales@carinibathrooms.com
A28: water tank | B28: ProChimp | C28: info@prochimps.com
A29: water tank | B29: Tarcisio Caruana | C29: info@tarcisiocaruana.com
A30: water tank | B30: A to Z | C30: team-b2b@atoz.com.mt
A31: water tank | B31: Attard's Household Goods and Appliances | C31: info@attardsmalta.com
A32: water tank | B32: Divine Appliances | C32: info@divine.com.mt

Sheet STO
A1: item | B1: supplier | C1: phone number | D1: email | E1: location | F1: website
A2: STO Services | B2: MAKS Engineering | C2: 9950 0549 | D2: info@maksengmalta.com
A3: STO Services | B3: Marlon Mercieca | C3: 7931 1095 | D3: marlon1790@hotmail.com
A4: STO Services | B4: Retrofit | D4: info@retrofit.com.mt
A5: STO Services | B5: Architworks | C5: 9985 5109 | D5: info@architworks.com
A6: STO Services | B6: RDC Consultants | C6: 77 072 101 | D6: rdcmalta@gmail.com
A7: STO Services | B7: STO Services Malta | C7: 79092549 | D7: sitetechnicalofficermalta@gmail.com
A8: STO Services | B8: Perit Daniel Portelli | C8: 79973333 | D8: daniel@dpa.com.mt
A9: STO Services | B9: STO Services | C9: 7977 2255 | D9: info@stoservicesltd.com
A10: STO Services | B10: AI Engineering Solutions | C10: 7988 7194 | D10: iagius@aiesltd.com
A11: STO Services | B11: Aaron Abela | C11: 79051114 | D11: akarchistudio@gmail.com
A12: STO Services | B12: Adrian Formosa | C12: 99718489 | D12: adrian180690@gmail.com
A13: STO Services | B13: Adam Pace | C13: 79394677 | D13: ap@paceadam.com
A14: STO Services | B14: Alexander Sammut | C14: 99012340 | D14: alexander.sammut.16@gmail.com
A15: STO Services | B15: Antoine Brincat | D15: antoinebrincat.mlt@gmail.com
A16: STO Services | B16: Anthony Micallef | D16: antdormic@gmail.com
A17: STO Services | B17: Catherine Galea | D17: cg@techman.com.mt
A18: STO Services | B18: Christian Attard | D18: christian.attard@gmail.com
A19: STO Services | B19: Christian Fenech | D19: cfperit@gmail.com
A20: STO Services | B20: Claire Ghigo | D20: claireghigo@gmail.com
A21: STO Services | B21: Clayton Zammit | D21: clayton.zammit@yahoo.com
A22: STO Services | B22: Dario Esposito | D22: ingdarioespo@gmail.com
A23: STO Services | B23: ENWAR OULAIWI | D23: enwar27699@gmail.com
A24: STO Services | B24: George Cauchi | D24: gorgcauchi@gmail.com
A25: STO Services | B25: George Xuereb | D25: xuereb.george@gmail.com

Sheet MEP Services
A1: item | B1: supplier | C1: phone number | D1: email | E1: location | F1: website
A2: Consultancy | B2: A+ MEP Consultancy Services | C2: 99511239 | D2: aplusmep.ce@gmail.com | F2: https://www.facebook.com/profile.php?id=61571161208722

Sheet Lifts
A1: item | B1: supplier | C1: phone number | D1: email | E1: location | F1: website
A2: lift | B2: D&S Lifts (Maintenance) Ltd | C2: 2741 3490 • | D2: info@dslifts.com | E2: Vjal il‑Wieħed u Għoxrin ta' Settembru, Naxxar | F2: www.dslifts.com
A3: lift | B3: Groffe Elevator Services Ltd | C3: 2733 2198 | D3: groffelifts@gmail.com | E3: 5/3, Triq l‑Imsida, Gżira GZR 1401
A4: lift | B4: Apex Lifts | C4: 2145 0395 | D4: info@apexlifts.com.mt | E4: 14, Triq San Mikiel, Rabat RBT 2440 | F4: www.apexlifts.com.mt
A5: lift | B5: Etralia Limited | C5: 2180 7030 | D5: info@etralia.com | E5: 39, Triq San Ġakmu, Luqa LQA 1892 | F5: www.etralia.com
A6: lift | B6: Titan International Limited | C6: 2134 1697 | D6: info@titan.mizzi.com.mt | E6: The Lyric, Triq Antonio Bosio, L‑Imsida | F6: www.titan.com.mt
A7: lift | B7: Eni Lift Malta | C7: 9949 2362 | D7: eniliftmalta@gmail.com | E7: Triq San Filippu, Mġarr/M’najdra? | F7: www.eni-lift.com
A8: lift | B8: Air‑tro Services | C8: 9908 6442 | D8: air‑tro_service@outlook.com | E8: Triq il‑Gudja, Ħal Għaxaq
A9: lift | B9: Bertu Lifting Service | C9: 9922 9391 | D9: bertulifting@gmail.com | E9: Triq Piscopo Macedonia, San Pawl il‑Baħar | F9: www.bertulifting.com.mt
A10: lift | B10: High Rise Co Ltd | C10: 2145 5220 | D10: info@highriselifts.com | E10: Factory LQA 5/6/7, Luqa Industrial Estate | F10: www.highriselifts.com
A11: lift | B11: Panta Lesco Ltd | C11: 2381 2381 | D11: enquiries@pantalesco.com | E11: Panta House, Triq il‑Wied ta' l‑Imsida | F11: www.pantalesco.com
A12: lift | B12: Schindler Malta Ltd | C12: 2144 2914 | D12: info_malta@schindler.com | E12: 2, Triq Roger Debattista, Hamrun HMR 1271
A13: lift | B13: Eleva Lifts Co Ltd | C13: 2146 6866 | D13: sales@elevaliftsmalta.com | E13: Mdina Bastions Block A, Triq Michael Bonnici, Żebbuġ
A14: lift | B14: S.S Lifts Orona | C14: 2157 5392 | D14: info@sslifts.com | E14: S.S. Lifts Orona, 13, Triq it-Turisti Qawra, SPB1028 Malta | F14: https://sslifts.com/
A15: lift | B15: Vertibus | C15: 2248 7118 | D15: info.mt@otis.com | E15: MRA048D, Industrial Estate, Marsa, MRS3000, Malta | F15: https://vertibus.com/
A16: lift | B16: IGM Lifts | C16: 21 346 535 | D16: info@igmlifts.com | E16: I G M Lift Supplies & Services Triq Moroni , Sliema Malta SLM 1210 | F16: https://www.igmlifts.com/
A17: lift | B17: Lift Services | C17: 2125 2206 | D17: info@liftservices.com.mt | E17: Factory A25F, Marsa Industrial Estate, Malta | F17: https://liftservices.com.mt/
A18: lift | B18: Elevation | C18: 27413490 | D18: info@elevation.mt | E18: Elevation Ltd Upper A12 Midland Industrial Estate Triq Burmarrad Naxxar, NXR 6345 Malta | F18: https://elevation.mt/
A19: lift inspection & certification | B19: S&A Quality Assurance Ltd | C19: 2731 4593 | D19: info@qualitymalta.com | E19: Joedi Graziella Apartments, Triq l‑Iskola, Imśida

Sheet Flooring
A1: item | B1: supplier | C1: email | D1: phone number | E1: location | F1: website
A2: Installers | B2: Maduma Home Interiors | C2: info@madumahomeinteriors.com | D2: 2144 1611 / 7777 4240 | E2: 12, Triq il-Parroċċa SVR 1262 Santa Venera | F2: https://www.madumahomeinteriors.com/
A3: Installers | B3: Brands International | C3: info@brands.com.mt | D3: 2095 9595 | E3: Triq tal-Balal, San Gwann, Malta | F3: https://www.brands.com.mt/
A4: Installers | B4: Tutto Parquet | C4: tuttoparquetmalta@gmail.com | D4: 2144 7379 | E4: 10, Triq Dun Karm Birkirkara, Malta | F4: https://tuttoparquetmalta.com/index.html
A5: Flooring | B5: Vivendo | C5: info@vivendo.mt | D5: 2277 3000 | E5: Mdina Road, Qormi, QRM 9011, Malta | F5: https://vivendo.mt/
B7: Rubber Flooring - 389 Co Ltd

Sheet Tilers
A1: ITEM | B1: SUPPLIER | C1: EMAIL | D1: PHONE NUMBER | E1: LOCATION | F1: WEBSITE
A2: TILERS | B2: Brian Tile Cutting and Skirting | C2: bgalea11@gmail.com | D2: 99 421 140 | E2: Triq John Michael Testa Tal-Handaq , Qormi, Malta QRM 4000 | F2: --------------
A3: TILERS | B3: C M K A (Chris Zammit) | C3: cmkazammit@gmail.com | D3: 79 478 840 | E3: 19 Garage Katarina Triq Santa Klementina , Zurrieq, Malta ZRQ 2510 | F3: --------------
A4: TILERS | B4: Ceramic Cutting Services Ltd | C4: info@skirting.com.mt | D4: 99 822 287 | E4: Private Road, Garage 4, 5 & 6 Triq l-Irham , Qormi, Malta | F4: --------------
A5: TILERS | B5: Edward Debono | C5: gabjean@gmail.com | D5: 99 860 593 | E5: 6 Montana Triq il-Qamh , Mellieha, Malta MLH 1761 | F5: --------------
A6: TILERS | B6: Aljanid GROUP | C6: jamal82aljanid82@gmail.com | D6: 99 099 033 | E6: 13 Helen Flat 3 Triq Joe Sciberras , Hamrun, Malta HMR 1550 | F6: --------------
A7: TILERS | B7: Azzopardi Bros | C7: tonytilelayer@hotmail.com | D7: 99 496 072 | E7: 12 Windrush T/G fi triq it-Turretta , Dingli, Malta DGL 1731 | F7: --------------
A8: TILERS | B8: Busuttil Ivan Tile Layer | C8: ivan.busu@hotmail.com | D8: 79 859 114 | E8: Trejqet il-Beatu Dun Gorg Preca , Pembroke, Malta PBK 1460 | F8: www.facebook.com/865035916866720 Suggest update
A9: TILERS | B9: Charles Grech (Ic-Cippi) | C9: charliegrech65@gmail.com | D9: 99 476 679 | E9: 22 April May Triq Gorg Borg , Qormi, Malta QRM 1943 | F9: --------------
A10: TILERS | B10: Damir Sujak | C10: damirsujak77@gmail.com | D10: 77 803 904 | E10: 35 Trilogy, Flt 1 Triq Ganni Bonnici , Zebbug, Malta ZBG 2507 | F10: --------------
A11: TILERS | B11: Etienne Mamo | C11: leldor@onvol.net | D11: 79 441 229 | E11: Divine Mercy Triq Pawlu Balzan , Zebbug, Malta ZBG 1490 | F11: --------------
A12: TILERS | B12: FJ Tile Laying | C12: fjtiles@gmail.com | D12: 79268690 | E12: Triq il-Bronja , Zurrieq, Malta | F12: --------------
A13: TILERS | B13: Floors of Stone | C13: info@floorsofstone.com.mt | D13: 21 496 742 | E13: 115 Triq il-Wied Ta’ L-Imsida , B’Kara, Malta BKR 9021 | F13: --------------
A14: TILERS | B14: George Galea | C14: gorggalea@gmail.com | D14: 99459892 | E14: 58 Triq Dun Gwann Pullicino , Mosta, Malta MST 2703 | F14: --------------
A15: TILERS | B15: Saliba Tile Layer | C15: salibatilelayer@gmail.com | D15: 9984 6386 | E15: Żejtun, Malta | F15: --------------
A16: TILERS | B16: Camilleri Tile Layer | C16: frankiec029@gmail.com | D16: 9988 3005 | E16: Kerċem, Gozo | F16: --------------
A17: TILERS | B17: Malta Tiling | C17: malta.tiling@gmail.com | D17: 9956 2994 | F17: --------------
A18: TILERS | B18: Kibitec Ltd | C18: contact@kibitec.com | D18: 7777 1522 | E18: Triq Domenico Cachia 54, Birkirkara, Malta | F18: --------------
A19: TILERS | B19: R/O Finishing Work | C19: siamnd1985@gmail.com | D19: 9958 4175 | E19: Marsascala, Malta | F19: --------------
A20: TILERS | B20: Stephen DeBattista | C20: stephentilelayer@gmail.com | D20: 9948 6377 | E20: Triq Giovanni Maria Borg, Zurrieq, Malta | F20: --------------
A21: TILERS | B21: ZLT Marble and Tiling Services | C21: zltcontractor@gmail.com | D21: 9980 6762 | E21: ---------------- | F21: --------------
A22: TILERS | B22: ED Finishings Ltd | C22: edfinishings1@gmail.com | D22: 9979 9124 | E22: 115, Triq Il-Bwieraq, Birkirkara, Malta | F22: --------------
A23: TILERS | B23: CS Tile & Gypsum Works | C23: clifton_tilelaying@hotmail.com | D23: 9945 4749 | E23: ºClimarkei, Triq Il-Gizi, Il-Fgura, Malta FGR 1040 | F23: -
A24: TILERS | B24: AGF Turnkey Contractors | C24: jevgatt@maltanet.net | D24: 2141 7115 | E24: Galine, Josmar Complex, Triq Id-Difiza Civili, Il-Mosta, Malta | F24: ----------------------
A25: TILERS | B25: Vesko Merkov | C25: tilingforfuture@gmail.com | D25: 7744 4949 | E25: ---------------- | F25: -
A26: TILERS | B26: Norbert Genovese | C26: chantellemizzi@hotmail.com | D26: 9905 4441 | E26: Fisheye, Triq Mons. A. Buhagiar, Ir-Rabat, Malta
A27: SUPPLIERS | B27: Absolute | C27: info@absolute.com.mt | D27: 2141 7596 | E27: Triq Pantar, Hal Lija | F27: https://www.absolute.com.mt/
A28: TILERS | B28: GAD Finishings | C28: alex@gad.com.mt | D28: 9947 2226 | E28: 21, Triq Gellewza Sewda, Midland Park, D7 Burmarrad Road, Burmarrad LO Naxxar Malta | F28: https://www.gad.com.mt/
A29: TILERS | B29: ProMan Interiors | C29: info@promaninteriors.com | D29: 2131 0334 | E29: Proman Interiors, 115, Valley Road, B'Kara. BKR 9022. Malta. | F29: https://www.promaninteriors.com/
A30: TILERS | B30: DWarehouse | C30: tresortradingltd@gmail.com | D30: 9965 4837 | E30: J.Micallef BOATYARD and WAREHOUSE Ta ghadajma l/o Mqabba (Near STMicro Eletronics) Malta, Mqabba, Malta | F30: https://www.facebook.com/Dwarehouse23/
A31: TILERS | B31: Showtiles & MORE | C31: showtiles@gmail.com | D31: 9942 2632 | E31: 78, Triq San Pawl NXR 4016 Naxxar, Malta | F31: https://www.facebook.com/showtilesnaxxar/
A32: Tiles | B32: R Group Finishing Ltd | C32: info@rgroupmt.com | D32: 7709 2277 | F32: https://www.facebook.com/RGroupMalta
A33: Tiles | B33: MRCD | C33: info@mrcd.com.mt | D33: 21468770 | E33: MRCD Building, Karmenu Camilleri Street, Qormi, QRM4631 | F33: https://www.mrcd.com.mt/en/home.htm
A36: To send also to:
A37: info@amaasurfaces.com
A38: Japap@geblanaturali.com
A39: tilesandmore89@gmail.com
A40: zltcontractor@gmail.com
A41: info@rainbowlimited.com
A42: vitalityprimebuilders@gmail.com
A43: chris@compassfloorcare.com
A44: wayne_7489@msn.com

Sheet Tiles
A1: item | B1: supplier | C1: email | D1: phone number | E1: location | F1: website
A2: Tiles | B2: Tiles & Marble | C2: tilesandmarbleinfo@gmail.com | D2: 2143 6361
A3: Tiles | B3: Tiles At Wholesale Prices | C3: tilesatwholesaleprices@gmail.com
A4: Tiles | B4: Floors Of Stone | C4: sales@fos.mt
A5: Tiles | B5: Satariano | C5: info@satariano.com
A6: Tiles | B6: Vella Falzon Home | C6: showroom@vellafalzon.com
A7: Tiles | B7: A&A Tiles and Bathrooms | C7: info@aandatiles.com
A8: Ceramic Tiles | B8: Malta Tiles | C8: info@maltatiles.com
A9: Tiles | B9: The Tile | C9: info@the-tile.com
A10: Tiles | B10: Tile Warehouse Malta | C10: info@tilewarehousemalta.com
A11: Tiles | B11: IPERCERAMICA Malta | C11: malta@iperceramica.it
A12: Tiles | B12: D Warehouse Malta | C12: tresortradingltd@gmail.com
A13: Tiles | B13: Centro Bagno | C13: j.centrobagno@gmail.com
A14: Tiles | B14: UNIQ Tiles & Ceramic Boutique | C14: patrick@uniq.mt
... A44: Tiles | B44: Sogno Bagno | C44: neil.galea698@gmail.com

Sheet Seamless flooring 
A1: item | B1: supplier | C1: email | D1: phone number | E1: location | F1: website
A2: seamless floor | B2: Advanced Safety Solutions | C2: info@advancedsafety.com.mt | D2: 9999 0247 | E2: San Pawl il‑Baħar / Bugibba, Malta
A3: seamless floor | B3: Maduma Home Interiors | C3: info@itpmalta.com | D3: 2144 1611 / 7777 4240 | E3: 12, Triq il-Parroċċa SVR 1262 Santa Venera | F3: https://www.madumahomeinteriors.com/
A4: seamless floor | B4: Seamless | C4: sales@seamless.com.mt | D4: 7940 0404 | F4: https://seamless.com.mt/
A5: seamless floor | B5: MBM | C5: tcj@mbm.com.mt | D5: 9949 3628 | E5: M4 Shopping Complex, Triq il-Linja, Attard | F5: https://www.mbm.com.mt/
A6: seamless floor | B6: Malta Design | C6: sales@malta-design.com | D6: 77105385 | E6: San Giljan, Malta | F6: https://www.malta-design.com/en/?brid=OdwV4IO9rLodP231ucwrAg
A7: seamless floor | B7: kibitec | C7: contact@kibitec.com | D7: 7777 1522 | E7: Triq Domenico Cachia 54 Birkirkara, BKR1017, Malta | F7: https://kibitec.com/
A8: seamless floor | B8: GRF Malta | C8: info@grfmalta.com | D8: 21377378 | E8: 117 Triq L-Assemblea Nazzjonali, San Gwann SGN 3034, Malta | F8: https://grfmalta.com/contact/
A9: seamless floor | B9: Borg & Sons | C9: borgconstructionworks@gmail.com
B10: JM Vibro | C10: sales@jmvibro.com
B11: Microcement Malta | C11: Pronesti@mail.com
B12: DWarehouse | C12: tresortradingltd@gmail.com | F12: https://www.facebook.com/Dwarehouse23
B13: Giorgi Project Point | C13: giorgiprojectpointltd@gmail.com | F13: https://www.facebook.com/profile.php?id=61574532256025
B14: Vellmann | C14: info@vellmann.com
B15: The Tile | C15: info@the-tile.com | F15: https://www.the-tile.com/concrete-effect-tiles.html
B16: Pitre Bathrooms | C16: info@jpitre.com

Sheet Resin Flooring
A1: item | B1: supplier | C1: email | D1: phone number | E1: location | F1: website
A2: Resin flooring | B2: Resin Decor Design | C2: resindecordesign@gmail.com | D2: 7986 8924 | E2: Birkirkara, Malta | F2: https://resindecordesign.com/
A3: Resin flooring | B3: The Resin Centre | C3: info@theresincentre.com | D3: 2747 7647 | E3: The Resin & Membrane Centre 264, Old Railway Track Santa Venera | F3: https://theresincentre.com/
A4: Resin flooring | B4: Coleiro | C4: info@coleiro.com | D4: 2148 3131 | E4: Msida Valley, B’Kara | F4: https://coleiro.com/floor-coatings/
A5: Resin flooring | B5: Rado Flooring | C5: info@radosystems.eu | D5: 2737 0730 | E5: 278, Triq il-Baltiku,, Saint Julian's, Malta | F5: https://www.facebook.com/radoflooring/
A6: Resin flooring | B6: Flock Image | C6: info@flockimage.com | D6: 2157 2759 | E6: Flock Image, 5, Sir Luigi Preziosi Str, Mosta, MST 1521, MALTA | F6: https://flockimage.com/
A7: Resin flooring | B7: JMV Building Solutions | C7: sales@jmvibro.com | D7: 21467 421 | F7: http://www.jmvibro.com/
A8: Resin flooring | B8: J. Zerafa Ltd | C8: zerafa.john@gmail.com | D8: 99873834 | F8: https://www.checkyourtraders.com/listing/j-zerafa-ltd?fromCat=resin-flooring
A9: Resin flooring | B9: JV Turnkey (Gozo) | C9: jvturnkey.gozo@gmail.com | D9: 79934883 | F9: https://www.checkyourtraders.com/listing/jv-turnkey-gozo?fromCat=resin-flooring
A10: Epoxy Flooring | B10: Epoxy Malta | C10: sakhr.turnkeyjob@gmail.com | D10: 9933 4044 | E10: Bugibba, Malta | F10: https://www.facebook.com/p/Epoxy-Malta-100067612150590/
A11: Resin flooring | B11: Fodha Building Solutions | C11: info@Fodha.mt | D11: 9927 4185 | E11: OneOneO, Triq il-Pitkali, Attard ATD 2214, Malta | F11: https://fodha.mt/
A12: Resin flooring | B12: Air Solutions | C12: airsolutions@ezee.mt | D12: 7777 5495 | E12: 58, Donato del Piano Street, Zurrieq, ZRQ 2240, Malta | F12: https://www.airsolutionslimited.com/

Sheet Epoxy Flooring
A1: item | B1: supplier | C1: email | D1: phone number | E1: location | F1: website
A2: Epoxy Flooring | B2: Epoxy Malta | C2: sakhr.turnkeyjob@gmail.com | D2: 9933 4044 | E2: Bugibba, Malta | F2: https://www.facebook.com/p/Epoxy-Malta-100067612150590/
A3: Epoxy Flooring | B3: Flock Image Co Ltd | C3: info@flockimage.com | D3: 2157 2759 | E3: Mosta
A4: Epoxy Flooring
A5: Epoxy Flooring
A6: Epoxy Flooring
A7: Epoxy Flooring
A8: Epoxy Flooring

Sheet Vinyl Flooring
A1: item | B1: supplier | C1: email | D1: phone number | E1: location | F1: website
A2: Vinyl Flooring | B2: Vical Interiors | C2: info@vicalinteriors.com | D2: 99499925 | E2: 84, Qormi Road, Hamrun | F2: https://www.vicalinteriors.com/
A3: Vinyl Flooring | B3: Beta | C3: info@betacentre.com.mt | D3: 2166 2028 | E3: Zabbar Road, Fgura | F3: https://beta.com.mt/
A4: Vinyl Flooring | B4: Vinyl Tiles | C4: customer@devalier.com.mt | D4: 2155 6694 | E4: Fairline Centre, Santa Marta Str, Victoria Gozo, VCT 2552, Malta | F4: https://www.dv.mt/
A5: Vinyl Flooring | B5: Mega Store | C5: shop@megastore.com.mt | D5: 2141 6753 | E5: Warehouse No. 25, Hard Rocks Industrial Park, Burmarrad Road, Naxxar, Malta | F5: https://www.megastore.com.mt/en_MT/c/Vinyl/160976/2/default/5
A6: Vinyl Flooring

Sheet Underfloor Heating
A1: item | B1: supplier | C1: email | D1: phone number | E1: location | F1: website | G1: Installers?
A2: Underfloor heating | B2: Ecomaxx | C2: ecomaxxltd@gmail.com | D2: 9994 7280 | E2: 44, Triq Dun Karm, BKR9030, Birkirkara, Malta | F2: https://www.ecomaxxmalta.com | G2: Installers
A3: Underfloor heating | B3: Cutrico | C3: info@cutrico.com | D3: 2149 8658 | E3: Cutrico Ltd, Mriehel By-pass, Mriehel, Malta | F3: https://www.cutrico.com/en/home.htm | G3: Not installers
A4: Underfloor heating | B4: Panta | C4: enquiries@panta.mt | D4: 2144 1361 | E4: Valley Road, L-Imsida MSD 9024, Malta | F4: https://panta.mt/ | G4: Installers
A5: Underfloor heating | B5: Solar Solutions | C5: info@solarsolutions.com.mt | D5: 2142 4750 | E5: Triq tal-Balal, In-Naxxar | F5: https://solarsolutions.com.mt/underfloor-heating/ | G5: Installers
A6: Underfloor heating | B6: Klimaflo | C6: Info@klimaflo.com | D6: 9949 5000 / 2137 6968 | E6: Tower Rd, Birkirkara BKR 4016, Malta | F6: https://klimaflo.com/ | G6: Installers
A7: Underfloor heating | B7: Kibitec Ltd | C7: contact@kibitec.com | D7: 7777 1522 | E7: Triq Domenico Cachia 54 Birkirkara, BKR1017, Malta | F7: https://kibitec.com/ | G7: Installers
A8: Underfloor heating | B8: Alternative Technologies | C8: info@alternativetechnologies.com.mt | D8: 2138 0309 | E8: Triq Dun Guzepp Scerri, San Ġiljan, Malta | F8: https://www.alternativetechnologies.com.mt/underfloor-heating | G8: Unsure
A9: Underfloor heating | B9: Smart Effects | C9: info@smarteffects.com.mt | D9: 2144 9190 | E9: SMART EFFECTS LTD, MTP Business Centre, Level 3, Triq Dun Karm, Birkirkara, Malta | F9: https://smarteffects.com.mt/hvac-needs-contact/ | G9: Installers
A10: Underfloor heating | B10: Recowatt | C10: info@recowatt.com | D10: 2166 0546 | E10: Mdina Road, Haż-Żebbuġ, ZBG 9019 Malta | F10: https://recowatt.com/services/underfloor-heating/ | G10: Installers

Sheet Floor Levelling
A1: item | B1: supplier | C1: email | D1: phone number | E1: location | F1: website
A2: Levelling | B2: SP Building Materials | C2: sebastianpolitano@gmail.com
A3: Levelling | B3: Xuereb Installations | C3: xil@xuerebinstall.com
A4: Levelling | B4: Bitmac | C4: sales@bitmac.mt
A5: Levelling | B5: JMV | C5: sales@jmvibro.com
A6: Levelling | B6: Borg Construction Works | C6: borgconstructionworks@gmail.com
A7: Levelling | B7: Attard Bros Construction Materials | C7: antoine.scicluna@attardbros.com
A8: Levelling | B8: Shaw Contractors | C8: shawcontractors@gmail.com
A9: Levelling | B9: MS Concrete Works | C9: mscworks24@gmail.com
A10: Levelling | B10: Kibitec | C10: info@kibitec.com
A11: Levelling | B11: The Professionals Malta | C11: sales@theprofessionalsmalta.com
A12: Levelling | B12: Liquid Screed | C12: info@liquidscreed.mt
A13: Levelling | B13: Mediterranean Building Finishes | C13: info@mbfmalta.com
... A20: Levelling | B20: Evolve | C20: sales@rsgroup.com.mt

Sheet Garage doors
A1: item | B1: supplier | C1: email | D1: phone | E1: location | F1: website | G1: other
A2: garage doors | B2: MBL Garage Door Solutions | C2: mblmalta.com | D2: 2137 3603 | E2: 81, Triq tal-Mensija, San Ġwann SGN 1604
A3: garage doors | B3: Pd Gates & Garage Doors | C3: pdmalta.com | D3: 2141 9275 | E3: Midland Micro Enterprise Park, Block D, Triq Burmarrad, Naxxar NXR 6345
A4: garage doors | B4: FGP Limited | C4: sales@fgp.com.mt | D4: 2166 7107 / | E4: 109, Triq Valletta, Ħal Luqa LQA 1762
A5: garage doors | B5: Brand Imports Ltd | C5: sales@brandimports.com.mt | D5: 7925 9207 | E5: Showroom 26, Triq Haz-Zabbar, Paola | F5: https://www.brandimports.com.mt/en/
A6: garage doors | B6: BEN Malta Limited | C6: benmaltalimited@gmail.com | D6: 7908 1928 | E6: Ben Malta Limited Triq Dun Mikiel Xerri Attard ATD 2020 Malta | F6: https://benmaltalimited.com.mt/garage-doors | G6: No. 7971 0020 Store Address: BEN Malta Limited Stores No 32 Triq in-Nissieġ Zabbar
A7: garage doors | B7: Tree D | C7: info@treedfurniture.com | D7: 7944 5674
A8: garage doors | B8: General Automation Services LTD | C8: info@automationmalta.com | D8: 9944 7194 | E8: KKW 019G Qasam Industrijali, Kordin, Paola | F8: https://www.automationmalta.com/
E9: Paola

Sheet BBQ
A1: BBQ area
A2: item | B2: supplier | C2: email | D2: phone number | E2: location | F2: website
A3: Barbecue Grill | B3: SBL Lighting Solutions | C3: chrisbltd1@gmail.com | D3: 2123 0349 / 9949 5359 | E3: Triq Oscar Zammit, Hamrun | F3: https://bbqworldmalta.mt/?utm_source=Yellow&utm_medium=Yellow-Website&utm_campaign=Landing-Page
A4: Barbecue Grill | B4: ortis ltd | C4: info@ortis.biz | D4: 21418236 | E4: 5 triq L-Industrija Central business district,qormi Malta CBD 5030 | F4: www.ortismalta.com
A5: Barbecue Grill | B5: soundsmart | C5: info@soundsmart.com.mt | D5: 21430569 -79454867 | E5: TRIQ IL-Kostituzzjoni,Mosta, Malta MST 9050 | F5: https://bigmatmalta.com
A6: Barbecue Grill | B6: bull europe limited | C6: info@zamco.com.mt | D6: 22792222 | E6: zamco building Triq il-Mithna, Qormi, Malta | F6: www.bullbbq.eu/en/home.htm
A7: Barbecue Grill | B7: stone creations | C7: info@stonecreations.com.mt | D7: 99406493 | E7: triq il-kanun ,Qormi,Malta | F7: www.stonecreations.com.mt
A8: Barbecue Grill | B8: bbq store malta | C8: info@bbqstoremalta.com | D8: 27800778 | E8: triq id -difiza Civili, Mosta ,Malta | F8: www.bbqstoremalta.com
A9: Barbecue Grill | B9: bbq world malta | C9: info@sbl.com.mt | D9: 35621230349 | E9: 10 triq Oscar Zammit , HMR 1281 , MALTA | F9: www.bbqworldmalta.mt
A10: Barbecue Grill | B10: crosscraft | C10: info@crosscraft.com.mt | D10: 35621805805 | E10: Bypass Mriehel, Qormi, QRM 9052 | F10: www.crosscraft.com.mt
A11: Barbecue Grill | B11: big mat malta | C11: info@bigmatmalta.com | D11: 356 7950 8457. | E11: Zona Industrial, ATD 4000 Ta' Qali, Malta. | F11: https://bigmatmalta.com
A12: Barbecue Grill | B12: KHSmalta | C12: info@know-howsystems.net | D12: 270 40679 | E12: Susan Flats B, Flat 05, Triq Il-Prinjolata, Ta' Xbiex, XBX1130, Malta. | F12: www.khsmalta.com
A13: Barbecue Grill | B13: livelifeoutdoor | C13: info@livelifeoutdoor.com.mt | D13: 356 9946 7979. | E13: St. Paul Street, Naxxar, Malta, NXR 4010 | F13: https://livelifemalta.com.mt/
A14: Barbecue Grill | B14: Firm B Pullicino | C14: info@fbpmalta.com | D14: 2167 6627 | E14: 139, Bajada Street, Zabbar, Malta | F14: https://www.fbpmalta.com/index.php/products/household/bbqs
A15: Barbecue Grill | B15: Malta Design | C15: sales@malta-design.com | D15: 7710 5385 | E15: Malta Design 33 Triq l-Oleandru , San Giljan, Malta
A16: Barbecue Grill | B16: Homemate | C16: customercare@homemate.com.mt | D16: 2326 2000 | E16: Triq L-Imprendituri, Birkirkara BKR 3000 | F16: https://www.homemate.com.mt/
A17: Barbecue Grill | B17: Pitre Home | C17: home@jpitre.com | D17: 2746 3330 | E17: Pitre Home Ltd, Mdina Road, Qormi | F17: https://pitreonline.com/

Sheet Alum Apertures
A1: Apertures
A2: item | B2: supplier | C2: email | D2: phone number | E2: location | F2: website
A3: Window | B3: A M Projects Ltd | C3: info@pvc.com.mt / sales@ampmalta.com | D3: 2137 4563 | E3: 8 Triq il-Garra Victoria Gardens L-Ibrag, Swieqi | F3: www.pvc.com.mt
A4: Window | B4: KB Structures | C4: stakterinacons@outlook.com | D4: 9989 9781 / 9942 4136 | E4: Triq il-Kappella ta' Santa Marija, Naxxar | F4: www.kbstructuresltd.com
A5: Window | B5: St Anthony Woodworks Ltd | C5: info@stanthonyww.com | D5: 2141 3044 | E5: Triq il-Fortizza, Mosta | F5: www.stanthonyww.com
A6: Window | B6: Framegrip Industires Ltd | C6: info@framegrip.com | D6: 2141 9787 | E6: Triq il-Mosta, Lija | F6: www.framegrip.com
A7: Window | B7: J Lautier Co Ltd | C7: sales@jlautier.com | D7: 2134 4620 | E7: Triq it-Torri, Msida | F7: www.jlautier.com
A8: Window | B8: Styles Apertures Ltd | C8: sales@newstylesmalta.com | D8: 2125 7400 | E8: SUB 030A Qasam Industrijali, San Gwann | F8: www.newstylesmalta.com
A9: Window | B9: Grima Furniture (1960) Ltd | C9: info@grimafurniture.com | D9: 9947 5183 | E9: Zone 2 Triq L-Ghadam Central Business District, B'Kara | F9: www.grimafurniture.com
A10: Window | B10: Amabile Galea & Sons Ltd Iron & Aluminium Works | C10: info@amabilegalea.com | D10: 2182 4287 | E10: 34 Triq it-Torri San Gwann, Birgu | F10: www.amabilegalea.com
A11: Window | B11: Gozo Aluminium Ltd | C11: info@gozoaluminium.com | D11: 2155 1166 | E11: Factory GZB 2 Qasam Industrijali, Xewkija-Gozo | F11: https://www.facebook.com/GozoAluminium/
A12: Window | B12: A1 Finishes Limited | C12: info@a1finishesltd.com | D12: 7996 0410 | E12: 2 Triq Lorenzo Gafa, Zebbug | F12: _____
A13: Window | B13: John Spiteri Aluminium (II-Parus) | C13: parus984@gmail.com | D13: 9947 6549 | E13: 31 Triq il-Furnar, Qormi | F13: _____
... A52: Window | B52: Express Aluminium Ltd | C52: info@expressaluminium.com | D52: 2146 1078 | E52: Express Bldg Triq Gharram, Zebbug | F52: www.expressaluminium.com
A53: Window | B53: F & S Aluminium | C53: simdebwebb@hotmail.com | D53: 9947 2592 | E53: Oliand Triq Anthony John Coleiro Tal-Handaq, Qormi | F53: ______ | G53: EMAIL NOT DELIVERED
A54: Window | B54: Finestral | C54: sales@finestralmalta.com | D54: 2146 3522 | E54: SUB 029B Qasam Industrijali, San Gwann | F54: www.finestralmalta.com
A55: Window | B55: Friends Aluminium Works | C55: faworks123@gmail.com | D55: 70052 38925 | E55: Garage 144 Triq San Xmun, Fgura | F55: www.aluminiumworks.in
A56: Window | B56: George Aluminium | C56: azzopardimark8@gmail.com | D56: 9947 3343 | E56: 263 Triq il-Merhba, Fgura | F56: ______
A57: Window | B57: Giorgio Aluminium Co Ltd | C57: info@alugiorgio.com | D57: 9993 8509 | E57: Triq Mro Giuseppe Camilleri Tal-Hanhaq, Qormi | F57: https://www.facebook.com/p/Giorgio-Aluminium-Co-Ltd-100065044507710/
B58: Graham Aluminium & Sons Ltd | C58: info@grahamaluminium.com | D58: 2149 2908 | E58: 23 Graham Aluminium Triq John Michael Testa Tal-Handaq, Qormi | F58: www.grahamaluminium.com
A59: Window | B59: Guys Gypsum Installations, Soffits & Aluminium | C59: guysmalta@gmail.com | D59: 7965 7308 | E59: Drive in fi triq il-Belt Valletta, Qormi | F59: https://www.facebook.com/Guys21485785/
A60: Window | B60: Horvin Alum Ltd | C60: horvinltd@gmail.com | D60: 2122 6320 | E60: A 42 Qasam Industrijali, Marsa | F60: www.horvinltd.com
A61: Window | B61: I C S Aluminium | C61: charliecalleja@hotmail.com / icsaluminium@gmail.com | D61: 7972 7953 | E61: Qart D'Orange Garage Trejqet il-Wied, Qormi | F61: www.icsaluminium.yolasite.com
A62: Window | B62: J & B Aluminium Ltd | C62: johnjandb@gmail.com | D62: 9944 0946 | E62: Triq I-Imdina, Zebbug | F62: _____
A63: Window | B63: J C D Aluminium Works & Woodworks | C63: info@jcdaluminium.com | D63: 2748 5677 | E63: 13 Triq Mro Giorgio Zarb Tal-Handaq, Qormi | F63: www.jcdaluminium.com
A64: Window | B64: J & K Aluminium | C64: jk.aluminium@yahoo.com | D64: 7905 5395 | E64: John Garage Triq Haz-Zebbug, Attard | F64: www.jk-aluminium.com
A65: Window | B65: Jamar Malta Ltd | C65: admin@jamarmalta.com | D65: 9949 0300 | E65: 110, Triq Dun Bartilmew Attard, Zebbug | F65: www.jamarmalta.com
A66: Window | B66: Jason Aluminium Co Ltd | C66: info@jasonaluminium.com | D66: 2180 4756 | E66: KW 19J Qasam Industrijali, Kordin, Paola | F66: www.jasonaluminium.com
A67: Window | B67: K K Aluminium - Matthew | C67: kkalworks@gmail.com | D67: 2166 0170 | E67: Oceanis Triq tas-Sliema, Gzira | F67: https://www.facebook.com/KKAluWorks/
A68: Window | B68: Munita Aluminium | C68: bjorn.vassallo@gmail.com | D68: 9913 1020 | E68: 82 Triq il-Hareb, Ghaxaq | F68: https://www.facebook.com/p/Munita-Aluminium-100063476861515/
A69: Window | B69: Muscat George Aluminium | C69: gmuscat@live.com | D69: 9983 5642 | E69: 12 Triq Wenzu Despott, Tarxien | F69: ______
A70: Window | B70: N D Aluminium | C70: nicdimech@gmail.com | D70: 2169 5051 | E70: Garage 23 Triq il-Bizzilla, Ghaxaq | F70: ______
... A79: Window | B79: Simon Aluminium | C79: _____ | D79: 9942 2717 | E79: Zone 2 Triq ll-Ghain Central Business District, B'Kara | F79: ______
A80: Window | B80: SP Techniques | C80: info@sptechniques.com | D80: 99320809 | E80: F18, Lower Level Midland Industrial Oark Triq Burmarrad, Naxxar | F80: www.sptechniques.com
A81: Window | B81: Sun Aluminium | C81: sunaluminium@hotmail.com | D81: 9946 0052 | E81: 23 Triq Angelo Melilli, Zebbug | F81: ______
A82: Window | B82: TC Aluminium Works | C82: t.camillerialuminium@hotmail.com | D82: 9939 5416 | E82: 8 Triq ll-Madonna Ta' Pompej, B'Kara | F82: https://www.aluminium.mt/
A83: Window | B83: Tower Aluminium Ltd | C83: info@towergroupmalta.com | D83: 2146 5156 | E83: Towe Buildings Triq Graham, Zebbug | F83: www.towergroupmalta.com
A84: Window | B84: Trends Manufacturing Ltd | C84: info@trendsltdmalta.com | D84: 2180 8802 | E84: KK 011 Qasam Industrijali, Kordin, Paola | F84: www.trendsltdmalta.com
A85: Window | B85: Windmill Services Ltd | C85: mario@windmillmalta.com | D85: 2182 2143 | E85: MRA 053 Qasam Industrijali, Marsa | F85: https://www.facebook.com/windmillltd/
A86: Window | B86: Woodpecker Carpenter | C86: _____ | D86: 9984 7115 | E86: 77 Triq il-Ballut Qasam Industrijali, Mosta | F86: _____
A87: Window | B87: Woodware Ltd | C87: luke@woodware.com.mt | D87: 9945 0440 | E87: A8 Qasam Industrijali, Marsa | F87: www.facebook.com/bespokelocalfurniture
A88: Window | B88: Zammit Aluminium Ltd | C88: zammitalu@gmail.com | D88: 2155 4058 | E88: Sqaq Privat Triq tal-Ghajn, Fontana-Gozo | F88: www.facebook.com/zammitaluminum/
A90: Door | B90: A M Projects Ltd | C90: info@pvc.com.mt / sales@ampmalta.com | D90: 2137 4563 | E90: 8 Triq il-Garra Victoria Gardens L-Ibrag, Swieqi | F90: www.pvc.com.mt
A91: Door | B91: Framegrip Industires Ltd | C91: info@framegrip.com | D91: 2141 9787 | E91: Triq il-Mosta, Lija | F91: www.framegrip.com
A92: Door | B92: J Lautier Co Ltd | C92: sales@jlautier.com | D92: 2134 4620 | E92: Triq it-Torri, Msida | F92: www.jlautier.com
A93: Door | B93: A1 Finishes Limited | C93: info@a1finishesltd.com | D93: 7996 0410 | E93: 2 Triq Lorenzo Gafa, Zebbug | F93: https://a1finishesltd.com/
... A172: Door | B172: Zammit Aluminium Ltd | C172: zammitalu@gmail.com | D172: 2155 4058 | E172: Sqaq Privat Triq tal-Ghajn, Fontana-Gozo | F172: www.facebook.com/zammitaluminum/

Sheet Aluminum
A1: item | B1: supplier | C1: email | D1: phone number | E1: location | F1: website
A2: Aluminum | B2: ICS Aluminium | C2: charliecalleja@hotmail.com | D2: 79 727 953 | F2: https://www.yellow.com.mt/i-c-s-aluminium_aluminium-apertures-fixtures%2Bqormi/?utm_source=chatgpt.com | G2: WILL CHECK LATER - 23/04/2026
A3: Aluminum | B3: Philip Said Aluminium Works | C3: pmll.said@gmail.com | D3: 99890075 | F3: https://www.triedandtested.mt/listing/philip-said-aluminium-works | G3: SENT TO WRONG EMAIL - RESENT
A4: Aluminum | B4: Aluminium Ltd | C4: info@aluminiumltd.com | D4: 7949 1930 | F4: https://www.facebook.com/alultd/
A5: Aluminum | B5: Azzopardi Aluminium & Metal Works | C5: azzopardialumworks@gmail.com | D5: 99277571 | F5: https://www.checkyourtraders.com/listing/azzopardi-aluminium-metalworks?utm_source=chatgpt.com | G5: WILL CHECK LATER - 23/04/2026
A6: Aluminum | B6: Graham Aluminium & Sons Ltd | C6: info@grahamaluminium.com | D6: 2149 2908
A7: Aluminum | B7: A M Projects Ltd | C7: sales@ampmalta.com | G7: CANNOT
A8: Aluminum | B8: KB Structures | C8: structures@portofino.mt | G8: They dont work on Alum
A9: Aluminum | B9: Framegrip Industries Ltd | C9: info@framegrip.com | G9: Will reply back.
A10: Aluminum | B10: J Lautier Co Ltd | C10: sales@jlautier.com | G10: Will confirm with the design department that they are working on the quote
A11: Aluminum | B11: Styles Apertures Ltd | C11: sales@newstylesmalta.com
A12: Aluminum | B12: Amabile Galea & Sons Ltd Iron & Aluminium Works | C12: info@amabilegalea.com
A13: Aluminum | B13: Gozo Aluminium Ltd | C13: info@gozoaluminium.com | G13: Will reply back.
A14: Aluminum | B14: A1 Finishes Limited | C14: info@a1finishesltd.com
A15: Aluminum | B15: John Spiteri Aluminium (II-Parus) | C15: parus984@gmail.com | G15: Will reply back.
A16: Aluminum | B16: Afda Aluminium | C16: info@afdaaluminium.com
A17: Aluminum | B17: J 3 Alumiunium & Iron Works | C17: j3aluminium@gmail.com | G17: Number doesnt exist
A18: Aluminum | B18: Nu Aluminium | C18: nu-aluminium@outlook.com | G18: No reply
A19: Aluminum | B19: Nicholas Industries | C19: info@nicholas.mt | G19: Will call back Monday
A20: Aluminum | B20: Melvin Aluminium Works | C20: chayron186@gmail.com | G20: No reply
A21: Aluminum | B21: Josef Aluminium & Metal Works | C21: josefvella72@gmail.com
A22: Aluminum | B22: North Aluminium Works | C22: northalu@gmail.com
A23: Aluminum | B23: A. Goodchild Installations | C23: agood.installations@yahoo.com
A24: Aluminum | B24: Godwin Cristina Aluminium | C24: gsf-1200@hotmail.com
A25: Aluminum | B25: JBS Aluminium | C25: jsbaluminiumworks@gmail.com
A26: Aluminum | B26: A + Aluminium Gozo | C26: mario.camilleri9@gmail.com
A27: Aluminum | B27: A & C Aluminium Ltd | C27: info@acaluminium.com
A28: Aluminum | B28: A P Aluminium Works | C28: lexport@go.com.mt
A29: Aluminum | B29: Alfred Aluminium | C29: alfalu@melita.com
A30: Aluminum | B30: Almal Aluminium & Stained Glass Works | C30: xandrumallia@gmail.com
A31: Aluminum | B31: Alukey Aluminium | C31: info@alukey.com.mt
A32: Aluminum | B32: Aluminium Ltd | C32: info@aluminiumltd.com
A33: Aluminum | B33: Andrew Vella Aluminium Works | C33: andrewvella66@gmail.com
A34: Aluminum | B34: Azzopardi Aluminium & Metal Works | C34: info@aluminiumltd.com | D34: FIXED
A35: Aluminum | B35: Bason Aluminium | C35: info@basonaluminium.com
A36: Aluminum | B36: Borg Aluminium | C36: borgaluminiummalta@gmail.com
A37: Aluminum | B37: BP Apertures | C37: henry@bpapertures.com
A38: Aluminum | B38: C D S Aluminium Works Ltd | C38: carmelspiteri2010@gmail.com | D38: FIXED | G38: WILL CHECK LATER - 23/04/2026
A39: Aluminum | B39: CA Group | C39: info@cagroup.com.mt
A40: Aluminum | B40: Charles Grech Isolcasa | C40: mrgmv@onvol.net
A41: Aluminum | B41: Choco Aluminium Works | C41: chocoaluminium@gmail.com
A42: Aluminum | B42: Comforabita Ltd | C42: info@comforabita.com
A43: Aluminum | B43: Cuschieri Group | C43: cba@cba.com.mt | G43: Will call later.
A44: Aluminum | B44: Danio Barbara | C44: daniobarbara1977@gmail.com
A45: Aluminum | B45: Dimech Aluminium Works | C45: savdim65@gmail.com
A46: Aluminum | B46: Dingli Aluminium | C46: info@dinglialuminium.com | G46: Needs more details on the structure, more dims, glass type, etc.
A47: Aluminum | B47: Direct Developments Ltd | C47: sales@pvcmalta.com
A48: Aluminum | B48: DX Aluminium Works | C48: dxaluworks@gmail.com
A49: Aluminum | B49: Express Aluminium Ltd | C49: info@expressaluminium.com
A50: Aluminum | B50: F & S Aluminium | C50: simdebwebb@hotmail.com
A51: Aluminum | B51: Friends Aluminium Works | C51: faworks123@gmail.com
A52: Aluminum | B52: George Aluminium | C52: azzopardimark8@gmail.com
A53: Aluminum | B53: Giorgio Aluminium Co Ltd | C53: info@alugiorgio.com
A54: Aluminum | B54: Graham Aluminium & Sons Ltd | C54: info@grahamaluminium.com
A55: Aluminum | B55: Guys Gypsum Installations, Soffits & Aluminium | C55: guysmalta@gmail.com
A56: Aluminum | B56: Horvin Alum Ltd | C56: horvinltd@gmail.com
A57: Aluminum | B57: I C S Aluminium | C57: charliecalleja@hotmail.com / icsaluminium@gmail.com
A58: Aluminum | B58: J & B Aluminium Ltd | C58: johnjandb@gmail.com
... A83: Aluminum | B83: D.T Aluminium | C83: dt.aluminium@outlook.com
B84: Amato Home Improvements | C84: amatohomeimprovements@gmail.com | G84: Will reply back.

Sheet Skylight
A1: item | B1: supplier | C1: email | D1: phone number | E1: location | F1: website
A2: Skylight | B2: Perfectum | C2: Info@perfectum.mt | D2: 9921 5215 | E2: Valletta, Malta | F2: https://www.facebook.com/perfectummt/
A3: Skylight | B3: Valor Malta | C3: valormalta@gmail.com | D3: 9959 4709 | E3: Triq l-isturnell Roza, Hal Luqa, Malta | F3: https://valormalta.wixsite.com/valor
A4: Skylight | B4: Nigel Dimech | C4: info@nigeldimech.com | D4: 7943 4443 / 2143 4443 | E4: KKW 721, Corradino Industrial Estate Paola, PLA 3000, Malta | F4: https://nigeldimech.com/

Sheet Timber Apertures
A1: item | B1: supplier | C1: email | D1: phone number | E1: location | F1: website
A2: Woodwork | B2: Joseph Mifsud Woodworks Ltd. | C2: info@josephmifsud.com | D2: 79539185 / 21461178 | E2: Joseph Mifsud Woodworks Ltd 48, Triq Dun Luret Callus Zebbug ZBG 2495 Malta | F2: https://www.josephmifsud.com/en/home.htm
A3: Wooden apertures | B3: Grima Furniture | C3: info@grimafurniture.com | D3: 9947 5183 | E3: Zone 2, Triq L-Ghadam, Central Business District B’Kara - Malta CBD 2060 | F3: https://www.grimafurniture.com/
A4: Wooden apertures | B4: AM Projects | C4: sales@ampmalta.com | D4: 2137 4563 / 9999 6766 | E4: 8 Garra, Is-Swieqi | F4: https://www.pvc.com.mt/
A5: Wooden apertures | B5: adoremore | C5: sales@adoremore.eu | D5: 2145 6570 / 2145 6560 | E5: Adore More Triq Id-Difiza Civili. Mosta, MST 1743 Malta | F5: https://adoremore.com.mt/
A6: Wooden apertures | B6: Direct Developments Malta | C6: sales@pvcmalta.com | D6: 2138 2595 | E6: L, 52 Triq Il- Muzika, Iklin IKL 1091 | F6: https://www.pvcmalta.com/en/home.htm
A7: Doors | B7: Cassar Woodworks | C7: info@cassarwoodworks.com | D7: 2143 0936 / 9943 0936 | E7: George Cassar Woodworks Plot TQL027, Crafts Village, Ta’ Qali, | F7: https://cassarwoodworks.com/
A8: Wooden apertures | B8: St Anthony Woodworks | C8: info@stanthonyww.com | D8: 2141 3044 / 9943 7436 | E8: St. Anthony Woodworks Triq il-Fortizza, Mosta MST 4000 | F8: https://stanthonyww.com/
A9: Wooden apertures | B9: C and M Woodworks | C9: candmww@gmail.com | D9: 9989 7509 | E9: C & M Woodworks, Indri Psaila Street, Handaq Industrial Estate, Qormi | F9: https://candmwoodworks.com/
A10: Wooden apertures | B10: Pisani Woodworks | C10: info@pisaniwoodworks.com | D10: 2156 5946 / 9942 9340 | E10: Pisani Woodworks Co. Ltd. GGX 002B, Industrial Estate, Xewkija XWK3000, Gozo | F10: https://www.pisaniwoodworks.com/
A11: Wooden apertures | B11: MasterWoodMalta | C11: masterwoodmalta@gmail.com | D11: 99406626 / 21232190 | E11: 106, Ind Estate, Luqa, LQA 3000, Malta | F11: https://masterwoodmalta.net/
A12: Wooden apertures | B12: Gilbert Micallef Woodwork | C12: gilbertmicallef1@gmail.com | D12: 7930 5449 | E12: Pearl Court, Flat 1, Vjal Il-Helsien, Haz-Zebbug, Malta | F12: https://www.findit.com.mt/en/directory/listings/9529/gilbert-micallef-woodwork-malta.htm?utm_source=chatgpt.com
A13: Wooden apertures | B13: Classic Design Woodworks | C13: info@classicdesign.mt | D13: 2147 2304 | E13: Entrance 4 No:1 Triq Valletta Il-Marsa Marsa, Malta | F13: https://www.classicdesign.mt/
A14: Woodwork | B14: Kubek Furniture Works | C14: info@kubekgroup.com | D14: 21658888 | E14: Kubek Showroom, Mdina Road, Qormi | F14: https://www.findit.com.mt/en/directory/listings/5261/kubek-furniture-works.htm
A15: Wooden apertures | B15: Briffa & Axiaq Woodworks | C15: joseph.briffa.woodworks@hotmail.com | D15: 9947 3187 | E15: Triq Mastru Karmenu Mallia, Hal Qormi, Malta | F15: https://www.findit.com.mt/en/directory/listings/10200/joseph-briffa-woodworks.htm
A16: Wooden apertures | B16: Gauci Woodworks | C16: pdgl1969@gmail.com | D16: 2141 0441 / 9942 0685 | E16: Triq Il-Kappar, Il-Mosta, Malta MST 03 | F16: https://www.findit.com.mt/en/directory/listings/3681/gauci-woodworks.htm
A17: Wooden apertures | B17: Delia Woodworks | C17: info@deliaww.net | D17: 2122 0783 | E17: Factory A5a, Qasam Industrijali, Il-Marsa, Malta | F17: https://www.findit.com.mt/en/directory/listings/9171/delia-woodworks-ltd.htm
A18: Doors | B18: DDoor Company | C18: info@ddoorcompany.com | D18: 79794242 / 77707433 | E18: 128 Old Railway Track, Santa Venera | F18: https://ddoorcompany.com/
A19: Apertures | B19: Confort House | C19: info@conforthouse.mt | D19: 7749 4054 | E19: 71, Triq L-Imdina Qormi – Malta | F19: https://conforthouse.mt/
A20: Wooden apertures | B20: Baldacchino Woodworks | C20: info@baldacchinogroup.com | D20: 2168 5021 | E20: Baldacchino Builldings, Valletta road, Iz-Zurrieq, Malta | F20: https://baldacchinogroup.com/menu/home.html
A21: Wooden apertures | B21: Woodware | C21: luke@woodware.com.mt | D21: 7929 9248 | E21: A8, Industrial Estate, Marsa, Malta, MRS3000 | F21: https://www.facebook.com/bespokelocalfurniture/?utm_source=Yellow&utm_medium=Yellow-Website&utm_campaign=Landing-Page
A22: Woodwork | B22: Gatt Woodworks | C22: joelgattcarpentry@gmail.com | D22: 7933 297
A23: Doors | B23: Master Carpenter | C23: mastercarpentermalta@outlook.com | D23: 9952 4677 | E23: Ħal Għaxaq, Malta | F23: https://www.facebook.com/MasterCarpenter84/
A24: Wooden apertures | B24: Trends Ltd | C24: info@trendsltdmalta.com | D24: 2180 8802 | E24: KKW011, Corradino Industrial Estate, Paola, PLA 3000, Malta | F24: https://www.trendsltdmalta.com/
A25: Wooden apertures | B25: ProjektDar | C25: Projectdarmalta@gmail.com | D25: 7757 0506 | E25: Naxxar, Malta | F25: https://www.facebook.com/profile.php?id=61577138676789
A26: Wooden apertures | B26: Classic Design Woodworks | C26: info@classicdesign.mt | D26: 2147 2304 | E26: Triq Valletta Il-Marsa, Marsa, Malta | F26: https://www.classicdesign.mt/
A27: Wooden apertures | B27: Cieffe Joinery Ltd. | C27: cieffejoinery@fsh.com.mt | D27: 7977 3801 | E27: Hal Far Road, Birzebbugia, Malta | F27: https://www.facebook.com/profile.php?id=100063608976880

Sheet PVC Appertures
A1: item | B1: supplier | C1: email | D1: phone number | E1: location | F1: website
A2: PVC Window | B2: Doors and More | C2: sales@doorsandmore.in | D2: 2713 3292 / 7713 3292 | E2: 217, Doors and More Triq Salvo Psaila B'Kara BKR 9078 Malta | F2: https://www.facebook.com/doorsand.more.3/
A3: PVC Window | B3: SP Techniques | C3: info@sptechniques.com | D3: 9932 0809 | E3: Block F 18, Midland Industrial Park, Burmarrd Street, Naxxar, NXR 6345 | F3: https://www.sptechniques.com/
A4: PVC Window | B4: JCD Aluminium | C4: info@jcdaluminium.com | D4: 7924 8128 | E4: Triq MRU Giorgio Zarb, Ħal Qormi | F4: https://www.jcdaluminium.com/upvc-aluminium-doors-and-windows
A5: PVC Window | B5: adoremore | C5: sales@adoremore.eu | D5: 2145 6570 / 2145 6560 | E5: Adore More Triq Id-Difiza Civili. Mosta, MST 1743 Malta | F5: https://adoremore.com.mt/
A6: PVC Window | B6: Finestral | C6: info@finestralmalta.com | D6: 2146 3522 | E6: San Gwann Industrial Estate, SGN3000, Malta | F6: https://www.finestralmalta.com/
A7: PVC Window | B7: AM Projects | C7: sales@ampmalta.com | D7: 2137 4563 / 9999 6766 | E7: 8 Garra, Is-Swieqi | F7: https://www.pvc.com.mt/
A8: PVC Window | B8: Window World | C8: info@windowworldinternational.net | D8: 2347 2994 | E8: Zircon Suites Triq ta' Zejfa, Mosta, Malta | F8: https://windowworld.eu/
A9: PVC Window | B9: ProDoor | C9: sales@prodoormalta.com | D9: 7777 1108 | E9: Plot 35 Triq Mastru George Cachia Hal Qormi, Malta | F9: https://prodoormalta.com/
A10: PVC Window | B10: Perfectum | C10: Info@perfectum.mt | D10: 9921 5215 | E10: Valletta, Malta | F10: https://www.facebook.com/perfectummt/
A11: PVC Window | B11: Nigel Dimech | C11: info@nigeldimech.com | D11: 7943 4443 / 2143 4443 | E11: KKW 721, Corradino Industrial Estate Paola, PLA 3000, Malta | F11: https://nigeldimech.com/
A12: PVC Doors and Windows | B12: CASCONE Home | C12: info@casconeporteefinestre.it | D12: 2755 5525 | E12: Msida Valley Road, BKR9022 Birkirkara - Malta | F12: https://www.casconehome.com/en/index.php
B13: iHomes | C13: quotes@ihomes.com.mt
B14: Trends | C14: info@trendsltdmalta.com
B15: Confort | C15: info@conforthouse.mt
B16: Direct Development | C16: sales@pvcmalta.com
C17: info@classicdesign.mt
C18: info@cagroup.com.mt
C19: sales@ampmalta.com
C20: sales@newstylesmalta.com
C21: info@fourwalls.com.mt
C22: info@grahamaluminium.com
C23: office@ecoplast.com.mt
C24: info@a1finishesltd.com
C25: info@framegrip.com

Sheet uPVC Apertures
A1: item | B1: supplier | C1: email | D1: phone number | E1: location | F1: website
A2: uPVC Apertures | B2: Perfectum | C2: info@perfectum.mt | D2: 9921 5215 | E2: Valletta, Malta | F2: https://www.facebook.com/perfectummt/
A3: uPVC Apertures | B3: Valor Malta | C3: valormalta@gmail.com | D3: 9959 4709 | E3: Triq l-isturnell Roza, Hal Luqa, Malta | F3: https://valormalta.wixsite.com/valor
A4: uPVC Apertures | B4: Brand Imports Ltd | C4: sales@brandimports.com.mt | D4: 7925 9207 | E4: Showroom 26, Triq Haz-Zabbar, Paola | F4: https://www.brandimports.com.mt/en/
A5: uPVC Apertures | B5: BP Apertures | C5: henry@bpapertures.com | D5: 9920 7248 | E5: Mdina Road, Zebbug | F5: https://www.bpapertures.com/
A6: uPVC Apertures | B6: R Group Finishing Ltd | C6: info@rgroupmt.com | D6: 7709 2277 | F6: https://www.facebook.com/RGroupMalta

Sheet Pocket Doors & Sliding Doors
A1: item | B1: supplier | C1: email | D1: phone number | E1: location | F1: website
A2: Pocket doors / sliding doors | B2: MaltaDIY | C2: sales@maltadiy.com
A3: Pocket doors / sliding doors | B3: Iperceramica | C3: msida@iperceramica.mt
A4: Pocket doors / sliding doors | B4: MegaStore | C4: shop@megastore.com.mt
A5: Pocket doors / sliding doors | B5: Apertures and more | D5: 99463204
A6: Pocket doors / sliding doors | B6: Doors and more | C6: sales@doorsandmore.in
A7: Pocket doors / sliding doors | B7: DDoor Company | C7: info@ddoorcompany.com
A8: Pocket doors / sliding doors | B8: Deckor LTD | C8: info@deckor.com.mt
A9: Pocket doors / sliding doors | B9: Elena's Doors and More | C9: viorel.limited@gmail.com
A10: Pocket doors / sliding doors | B10: Bitmac | C10: sales@bitmac.mt
A11: Pocket doors / sliding doors | B11: RGroup | C11: info@rgroupmt.com
A12: Pocket doors / sliding doors | B12: Dimech Enterprises | C12: sales@dimech-ent.com

Sheet Restoration
A1: item | B1: supplier | C1: email | D1: phone number | E1: location | F1: website
A2: Building alterations and restorations | B2: Four VC | C2: fourvcltd@gmail.com | D2: 79998255 | 79468519 | E2: 8 Triq Salvu Cacciattolo , Zejtun | F2: https://www.fourvcmalta.com/
A3: Facade restorations | B3: WS Installations | C3: schembriw45@gmail.com | D3: 99 655 581 / 79 049 069 | E3: Triq San Edwardu, Qormi, Malta | F3: https://www.wsinstallationsmalta.com/
A4: Restorations | B4: NM Restorations | C4: neilborg9@gmail.com | D4: 77 454 813 | E4: 23 Nightingale Triq Dun Salvatore Zarb , Gharghur, Malta GHR 1620 | F4: https://www.yellow.com.mt/nm-restoration/building-restoration-conservation/
A5: Restorations | B5: Norob Installations | C5: norobturnkey@gmail.com | D5: 79 475 940 | E5: Triq John Borg Zejtun ZTN 2077 | F5: https://www.norobinstallations.com/?utm_source=Yellow&utm_medium=Yellow-Website&utm_campaign=Landing-Page
A6: Restorations | B6: Kiton Contractors | C6: kitonkeith@gmail.com | D6: 99823248 (Keith) / 99466511 (Tony) | E6: Santa Marija Flats, Flt 3 Triq tal-Wej , Mosta Malta MST 2462 | F6: https://kitonkeith.wixsite.com/kitoncontractors
A7: Building alterations | B7: Casa Completa | C7: info@casacompleta.net | D7: 21 414 933 | E7: Triq l-Imdina Attard | F7: https://www.casacompletamalta.com/
A8: Building restoration | B8: Abela Restoration | C8: abela.restoration@gmail.com | D8: 99 600 139 | E8: Abela Restoration 55 Tal-Grazzja Triq Bugharbiel , Zejtun, Malta ZTN 3435 | F8: https://www.yellow.com.mt/abela-restoration_building-restoration-conservation+zejtun/
